package okhttp3;

import java.io.IOException;
import okhttp3.internal.http.HttpEngine;

final class RealCall
  implements Call
{
  volatile boolean canceled;
  final OkHttpClient client;
  HttpEngine engine;
  private boolean executed;
  Request originalRequest;
  
  protected RealCall(OkHttpClient paramOkHttpClient, Request paramRequest)
  {
    client = paramOkHttpClient;
    originalRequest = paramRequest;
  }
  
  public final Response execute()
    throws IOException
  {
    try
    {
      if (executed) {
        throw new IllegalStateException("Already Executed");
      }
    }
    finally {}
    executed = true;
    try
    {
      client.dispatcher.executed(this);
      Response localResponse1 = new RealCall.ApplicationInterceptorChain(this, 0, originalRequest, false).proceed(originalRequest);
      if (localResponse1 == null) {
        throw new IOException("Canceled");
      }
    }
    finally
    {
      client.dispatcher.finished(this);
    }
    client.dispatcher.finished(this);
    return localResponse2;
  }
  
  /* Error */
  final Response getResponse(Request paramRequest, boolean paramBoolean)
    throws IOException
  {
    // Byte code:
    //   0: aload_1
    //   1: getfield 80	okhttp3/Request:body	Lokhttp3/RequestBody;
    //   4: astore 18
    //   6: aload_1
    //   7: astore 17
    //   9: aload 18
    //   11: ifnull +73 -> 84
    //   14: aload_1
    //   15: invokevirtual 84	okhttp3/Request:newBuilder	()Lokhttp3/Request$Builder;
    //   18: astore_1
    //   19: aload 18
    //   21: invokevirtual 90	okhttp3/RequestBody:contentType	()Lokhttp3/MediaType;
    //   24: astore 17
    //   26: aload 17
    //   28: ifnull +15 -> 43
    //   31: aload_1
    //   32: ldc 92
    //   34: aload 17
    //   36: invokevirtual 98	okhttp3/MediaType:toString	()Ljava/lang/String;
    //   39: invokevirtual 104	okhttp3/Request$Builder:header	(Ljava/lang/String;Ljava/lang/String;)Lokhttp3/Request$Builder;
    //   42: pop
    //   43: aload 18
    //   45: invokevirtual 108	okhttp3/RequestBody:contentLength	()J
    //   48: lstore 7
    //   50: lload 7
    //   52: ldc2_w 109
    //   55: lcmp
    //   56: ifeq +83 -> 139
    //   59: aload_1
    //   60: ldc 112
    //   62: lload 7
    //   64: invokestatic 117	java/lang/Long:toString	(J)Ljava/lang/String;
    //   67: invokevirtual 104	okhttp3/Request$Builder:header	(Ljava/lang/String;Ljava/lang/String;)Lokhttp3/Request$Builder;
    //   70: pop
    //   71: aload_1
    //   72: ldc 119
    //   74: invokevirtual 123	okhttp3/Request$Builder:removeHeader	(Ljava/lang/String;)Lokhttp3/Request$Builder;
    //   77: pop
    //   78: aload_1
    //   79: invokevirtual 127	okhttp3/Request$Builder:build	()Lokhttp3/Request;
    //   82: astore 17
    //   84: aload_0
    //   85: new 129	okhttp3/internal/http/HttpEngine
    //   88: dup
    //   89: aload_0
    //   90: getfield 24	okhttp3/RealCall:client	Lokhttp3/OkHttpClient;
    //   93: aload 17
    //   95: iconst_0
    //   96: iconst_0
    //   97: iload_2
    //   98: aconst_null
    //   99: aconst_null
    //   100: invokespecial 132	okhttp3/internal/http/HttpEngine:<init>	(Lokhttp3/OkHttpClient;Lokhttp3/Request;ZZZLokhttp3/internal/http/StreamAllocation;Lokhttp3/Response;)V
    //   103: putfield 134	okhttp3/RealCall:engine	Lokhttp3/internal/http/HttpEngine;
    //   106: iconst_0
    //   107: istore 4
    //   109: aload_0
    //   110: getfield 136	okhttp3/RealCall:canceled	Z
    //   113: ifeq +45 -> 158
    //   116: aload_0
    //   117: getfield 134	okhttp3/RealCall:engine	Lokhttp3/internal/http/HttpEngine;
    //   120: getfield 140	okhttp3/internal/http/HttpEngine:streamAllocation	Lokhttp3/internal/http/StreamAllocation;
    //   123: iconst_0
    //   124: iconst_1
    //   125: iconst_0
    //   126: invokevirtual 146	okhttp3/internal/http/StreamAllocation:deallocate	(ZZZ)V
    //   129: new 31	java/io/IOException
    //   132: dup
    //   133: ldc 62
    //   135: invokespecial 63	java/io/IOException:<init>	(Ljava/lang/String;)V
    //   138: athrow
    //   139: aload_1
    //   140: ldc 119
    //   142: ldc -108
    //   144: invokevirtual 104	okhttp3/Request$Builder:header	(Ljava/lang/String;Ljava/lang/String;)Lokhttp3/Request$Builder;
    //   147: pop
    //   148: aload_1
    //   149: ldc 112
    //   151: invokevirtual 123	okhttp3/Request$Builder:removeHeader	(Ljava/lang/String;)Lokhttp3/Request$Builder;
    //   154: pop
    //   155: goto -77 -> 78
    //   158: iconst_1
    //   159: istore 5
    //   161: iload 5
    //   163: istore_3
    //   164: aload_0
    //   165: getfield 134	okhttp3/RealCall:engine	Lokhttp3/internal/http/HttpEngine;
    //   168: astore 19
    //   170: iload 5
    //   172: istore_3
    //   173: aload 19
    //   175: getfield 152	okhttp3/internal/http/HttpEngine:cacheStrategy	Lokhttp3/internal/http/CacheStrategy;
    //   178: ifnonnull +581 -> 759
    //   181: iload 5
    //   183: istore_3
    //   184: aload 19
    //   186: getfield 156	okhttp3/internal/http/HttpEngine:httpStream	Lokhttp3/internal/http/HttpStream;
    //   189: ifnull +43 -> 232
    //   192: iload 5
    //   194: istore_3
    //   195: new 35	java/lang/IllegalStateException
    //   198: dup
    //   199: invokespecial 157	java/lang/IllegalStateException:<init>	()V
    //   202: athrow
    //   203: astore_1
    //   204: iload 5
    //   206: istore_3
    //   207: aload_1
    //   208: invokevirtual 161	okhttp3/internal/http/RequestException:getCause	()Ljava/io/IOException;
    //   211: athrow
    //   212: astore_1
    //   213: iload_3
    //   214: ifeq +16 -> 230
    //   217: aload_0
    //   218: getfield 134	okhttp3/RealCall:engine	Lokhttp3/internal/http/HttpEngine;
    //   221: invokevirtual 165	okhttp3/internal/http/HttpEngine:close	()Lokhttp3/internal/http/StreamAllocation;
    //   224: iconst_0
    //   225: iconst_1
    //   226: iconst_0
    //   227: invokevirtual 146	okhttp3/internal/http/StreamAllocation:deallocate	(ZZZ)V
    //   230: aload_1
    //   231: athrow
    //   232: iload 5
    //   234: istore_3
    //   235: aload 19
    //   237: getfield 168	okhttp3/internal/http/HttpEngine:userRequest	Lokhttp3/Request;
    //   240: astore_1
    //   241: iload 5
    //   243: istore_3
    //   244: aload_1
    //   245: invokevirtual 84	okhttp3/Request:newBuilder	()Lokhttp3/Request$Builder;
    //   248: astore 17
    //   250: iload 5
    //   252: istore_3
    //   253: aload_1
    //   254: ldc -86
    //   256: invokevirtual 173	okhttp3/Request:header	(Ljava/lang/String;)Ljava/lang/String;
    //   259: ifnonnull +22 -> 281
    //   262: iload 5
    //   264: istore_3
    //   265: aload 17
    //   267: ldc -86
    //   269: aload_1
    //   270: getfield 177	okhttp3/Request:url	Lokhttp3/HttpUrl;
    //   273: iconst_0
    //   274: invokestatic 183	okhttp3/internal/Util:hostHeader	(Lokhttp3/HttpUrl;Z)Ljava/lang/String;
    //   277: invokevirtual 104	okhttp3/Request$Builder:header	(Ljava/lang/String;Ljava/lang/String;)Lokhttp3/Request$Builder;
    //   280: pop
    //   281: iload 5
    //   283: istore_3
    //   284: aload_1
    //   285: ldc -71
    //   287: invokevirtual 173	okhttp3/Request:header	(Ljava/lang/String;)Ljava/lang/String;
    //   290: ifnonnull +16 -> 306
    //   293: iload 5
    //   295: istore_3
    //   296: aload 17
    //   298: ldc -71
    //   300: ldc -69
    //   302: invokevirtual 104	okhttp3/Request$Builder:header	(Ljava/lang/String;Ljava/lang/String;)Lokhttp3/Request$Builder;
    //   305: pop
    //   306: iload 5
    //   308: istore_3
    //   309: aload_1
    //   310: ldc -67
    //   312: invokevirtual 173	okhttp3/Request:header	(Ljava/lang/String;)Ljava/lang/String;
    //   315: ifnonnull +25 -> 340
    //   318: iload 5
    //   320: istore_3
    //   321: aload 19
    //   323: iconst_1
    //   324: putfield 192	okhttp3/internal/http/HttpEngine:transparentGzip	Z
    //   327: iload 5
    //   329: istore_3
    //   330: aload 17
    //   332: ldc -67
    //   334: ldc -62
    //   336: invokevirtual 104	okhttp3/Request$Builder:header	(Ljava/lang/String;Ljava/lang/String;)Lokhttp3/Request$Builder;
    //   339: pop
    //   340: iload 5
    //   342: istore_3
    //   343: aload 19
    //   345: getfield 195	okhttp3/internal/http/HttpEngine:client	Lokhttp3/OkHttpClient;
    //   348: getfield 199	okhttp3/OkHttpClient:cookieJar	Lokhttp3/CookieJar;
    //   351: aload_1
    //   352: getfield 177	okhttp3/Request:url	Lokhttp3/HttpUrl;
    //   355: invokeinterface 205 2 0
    //   360: astore 18
    //   362: iload 5
    //   364: istore_3
    //   365: aload 18
    //   367: invokeinterface 211 1 0
    //   372: ifne +19 -> 391
    //   375: iload 5
    //   377: istore_3
    //   378: aload 17
    //   380: ldc -43
    //   382: aload 18
    //   384: invokestatic 217	okhttp3/internal/http/HttpEngine:cookieHeader	(Ljava/util/List;)Ljava/lang/String;
    //   387: invokevirtual 104	okhttp3/Request$Builder:header	(Ljava/lang/String;Ljava/lang/String;)Lokhttp3/Request$Builder;
    //   390: pop
    //   391: iload 5
    //   393: istore_3
    //   394: aload_1
    //   395: ldc -37
    //   397: invokevirtual 173	okhttp3/Request:header	(Ljava/lang/String;)Ljava/lang/String;
    //   400: ifnonnull +16 -> 416
    //   403: iload 5
    //   405: istore_3
    //   406: aload 17
    //   408: ldc -37
    //   410: ldc -35
    //   412: invokevirtual 104	okhttp3/Request$Builder:header	(Ljava/lang/String;Ljava/lang/String;)Lokhttp3/Request$Builder;
    //   415: pop
    //   416: iload 5
    //   418: istore_3
    //   419: aload 17
    //   421: invokevirtual 127	okhttp3/Request$Builder:build	()Lokhttp3/Request;
    //   424: astore 20
    //   426: iload 5
    //   428: istore_3
    //   429: getstatic 227	okhttp3/internal/Internal:instance	Lokhttp3/internal/Internal;
    //   432: aload 19
    //   434: getfield 195	okhttp3/internal/http/HttpEngine:client	Lokhttp3/OkHttpClient;
    //   437: invokevirtual 231	okhttp3/internal/Internal:internalCache	(Lokhttp3/OkHttpClient;)Lokhttp3/internal/InternalCache;
    //   440: astore 21
    //   442: aload 21
    //   444: ifnull +404 -> 848
    //   447: iload 5
    //   449: istore_3
    //   450: aload 21
    //   452: aload 20
    //   454: invokeinterface 236 2 0
    //   459: astore 17
    //   461: iload 5
    //   463: istore_3
    //   464: new 238	okhttp3/internal/http/CacheStrategy$Factory
    //   467: dup
    //   468: invokestatic 243	java/lang/System:currentTimeMillis	()J
    //   471: aload 20
    //   473: aload 17
    //   475: invokespecial 246	okhttp3/internal/http/CacheStrategy$Factory:<init>	(JLokhttp3/Request;Lokhttp3/Response;)V
    //   478: astore 22
    //   480: iload 5
    //   482: istore_3
    //   483: aload 22
    //   485: getfield 250	okhttp3/internal/http/CacheStrategy$Factory:cacheResponse	Lokhttp3/Response;
    //   488: ifnonnull +366 -> 854
    //   491: iload 5
    //   493: istore_3
    //   494: new 252	okhttp3/internal/http/CacheStrategy
    //   497: dup
    //   498: aload 22
    //   500: getfield 255	okhttp3/internal/http/CacheStrategy$Factory:request	Lokhttp3/Request;
    //   503: aconst_null
    //   504: iconst_0
    //   505: invokespecial 258	okhttp3/internal/http/CacheStrategy:<init>	(Lokhttp3/Request;Lokhttp3/Response;B)V
    //   508: astore_1
    //   509: iload 5
    //   511: istore_3
    //   512: aload_1
    //   513: astore 18
    //   515: aload_1
    //   516: getfield 261	okhttp3/internal/http/CacheStrategy:networkRequest	Lokhttp3/Request;
    //   519: ifnull +38 -> 557
    //   522: iload 5
    //   524: istore_3
    //   525: aload_1
    //   526: astore 18
    //   528: aload 22
    //   530: getfield 255	okhttp3/internal/http/CacheStrategy$Factory:request	Lokhttp3/Request;
    //   533: invokevirtual 265	okhttp3/Request:cacheControl	()Lokhttp3/CacheControl;
    //   536: getfield 270	okhttp3/CacheControl:onlyIfCached	Z
    //   539: ifeq +18 -> 557
    //   542: iload 5
    //   544: istore_3
    //   545: new 252	okhttp3/internal/http/CacheStrategy
    //   548: dup
    //   549: aconst_null
    //   550: aconst_null
    //   551: iconst_0
    //   552: invokespecial 258	okhttp3/internal/http/CacheStrategy:<init>	(Lokhttp3/Request;Lokhttp3/Response;B)V
    //   555: astore 18
    //   557: iload 5
    //   559: istore_3
    //   560: aload 19
    //   562: aload 18
    //   564: putfield 152	okhttp3/internal/http/HttpEngine:cacheStrategy	Lokhttp3/internal/http/CacheStrategy;
    //   567: iload 5
    //   569: istore_3
    //   570: aload 19
    //   572: aload 19
    //   574: getfield 152	okhttp3/internal/http/HttpEngine:cacheStrategy	Lokhttp3/internal/http/CacheStrategy;
    //   577: getfield 261	okhttp3/internal/http/CacheStrategy:networkRequest	Lokhttp3/Request;
    //   580: putfield 271	okhttp3/internal/http/HttpEngine:networkRequest	Lokhttp3/Request;
    //   583: iload 5
    //   585: istore_3
    //   586: aload 19
    //   588: aload 19
    //   590: getfield 152	okhttp3/internal/http/HttpEngine:cacheStrategy	Lokhttp3/internal/http/CacheStrategy;
    //   593: getfield 272	okhttp3/internal/http/CacheStrategy:cacheResponse	Lokhttp3/Response;
    //   596: putfield 273	okhttp3/internal/http/HttpEngine:cacheResponse	Lokhttp3/Response;
    //   599: aload 21
    //   601: ifnull +18 -> 619
    //   604: iload 5
    //   606: istore_3
    //   607: aload 21
    //   609: aload 19
    //   611: getfield 152	okhttp3/internal/http/HttpEngine:cacheStrategy	Lokhttp3/internal/http/CacheStrategy;
    //   614: invokeinterface 277 2 0
    //   619: aload 17
    //   621: ifnull +25 -> 646
    //   624: iload 5
    //   626: istore_3
    //   627: aload 19
    //   629: getfield 273	okhttp3/internal/http/HttpEngine:cacheResponse	Lokhttp3/Response;
    //   632: ifnonnull +14 -> 646
    //   635: iload 5
    //   637: istore_3
    //   638: aload 17
    //   640: getfield 282	okhttp3/Response:body	Lokhttp3/ResponseBody;
    //   643: invokestatic 286	okhttp3/internal/Util:closeQuietly	(Ljava/io/Closeable;)V
    //   646: iload 5
    //   648: istore_3
    //   649: aload 19
    //   651: getfield 271	okhttp3/internal/http/HttpEngine:networkRequest	Lokhttp3/Request;
    //   654: ifnonnull +1175 -> 1829
    //   657: iload 5
    //   659: istore_3
    //   660: aload 19
    //   662: getfield 273	okhttp3/internal/http/HttpEngine:cacheResponse	Lokhttp3/Response;
    //   665: ifnonnull +1164 -> 1829
    //   668: iload 5
    //   670: istore_3
    //   671: new 288	okhttp3/Response$Builder
    //   674: dup
    //   675: invokespecial 289	okhttp3/Response$Builder:<init>	()V
    //   678: astore_1
    //   679: iload 5
    //   681: istore_3
    //   682: aload_1
    //   683: aload 19
    //   685: getfield 168	okhttp3/internal/http/HttpEngine:userRequest	Lokhttp3/Request;
    //   688: putfield 290	okhttp3/Response$Builder:request	Lokhttp3/Request;
    //   691: iload 5
    //   693: istore_3
    //   694: aload_1
    //   695: aload 19
    //   697: getfield 293	okhttp3/internal/http/HttpEngine:priorResponse	Lokhttp3/Response;
    //   700: invokestatic 297	okhttp3/internal/http/HttpEngine:stripBody	(Lokhttp3/Response;)Lokhttp3/Response;
    //   703: invokevirtual 300	okhttp3/Response$Builder:priorResponse	(Lokhttp3/Response;)Lokhttp3/Response$Builder;
    //   706: astore_1
    //   707: iload 5
    //   709: istore_3
    //   710: aload_1
    //   711: getstatic 306	okhttp3/Protocol:HTTP_1_1	Lokhttp3/Protocol;
    //   714: putfield 309	okhttp3/Response$Builder:protocol	Lokhttp3/Protocol;
    //   717: iload 5
    //   719: istore_3
    //   720: aload_1
    //   721: sipush 504
    //   724: putfield 313	okhttp3/Response$Builder:code	I
    //   727: iload 5
    //   729: istore_3
    //   730: aload_1
    //   731: ldc_w 315
    //   734: putfield 319	okhttp3/Response$Builder:message	Ljava/lang/String;
    //   737: iload 5
    //   739: istore_3
    //   740: aload_1
    //   741: getstatic 322	okhttp3/internal/http/HttpEngine:EMPTY_BODY	Lokhttp3/ResponseBody;
    //   744: putfield 323	okhttp3/Response$Builder:body	Lokhttp3/ResponseBody;
    //   747: iload 5
    //   749: istore_3
    //   750: aload 19
    //   752: aload_1
    //   753: invokevirtual 325	okhttp3/Response$Builder:build	()Lokhttp3/Response;
    //   756: putfield 328	okhttp3/internal/http/HttpEngine:userResponse	Lokhttp3/Response;
    //   759: iload 5
    //   761: istore_3
    //   762: aload_0
    //   763: getfield 134	okhttp3/RealCall:engine	Lokhttp3/internal/http/HttpEngine;
    //   766: astore 18
    //   768: iload 5
    //   770: istore_3
    //   771: aload 18
    //   773: getfield 328	okhttp3/internal/http/HttpEngine:userResponse	Lokhttp3/Response;
    //   776: ifnonnull +1678 -> 2454
    //   779: iload 5
    //   781: istore_3
    //   782: aload 18
    //   784: getfield 271	okhttp3/internal/http/HttpEngine:networkRequest	Lokhttp3/Request;
    //   787: ifnonnull +1409 -> 2196
    //   790: iload 5
    //   792: istore_3
    //   793: aload 18
    //   795: getfield 273	okhttp3/internal/http/HttpEngine:cacheResponse	Lokhttp3/Response;
    //   798: ifnonnull +1398 -> 2196
    //   801: iload 5
    //   803: istore_3
    //   804: new 35	java/lang/IllegalStateException
    //   807: dup
    //   808: ldc_w 330
    //   811: invokespecial 40	java/lang/IllegalStateException:<init>	(Ljava/lang/String;)V
    //   814: athrow
    //   815: astore_1
    //   816: iload 5
    //   818: istore_3
    //   819: aload_0
    //   820: getfield 134	okhttp3/RealCall:engine	Lokhttp3/internal/http/HttpEngine;
    //   823: aload_1
    //   824: getfield 334	okhttp3/internal/http/RouteException:lastException	Ljava/io/IOException;
    //   827: invokevirtual 338	okhttp3/internal/http/HttpEngine:recover$5d8a7524	(Ljava/io/IOException;)Lokhttp3/internal/http/HttpEngine;
    //   830: astore 17
    //   832: aload 17
    //   834: ifnull +2258 -> 3092
    //   837: iconst_0
    //   838: istore_3
    //   839: aload_0
    //   840: aload 17
    //   842: putfield 134	okhttp3/RealCall:engine	Lokhttp3/internal/http/HttpEngine;
    //   845: goto -736 -> 109
    //   848: aconst_null
    //   849: astore 17
    //   851: goto -390 -> 461
    //   854: iload 5
    //   856: istore_3
    //   857: aload 22
    //   859: getfield 255	okhttp3/internal/http/CacheStrategy$Factory:request	Lokhttp3/Request;
    //   862: getfield 177	okhttp3/Request:url	Lokhttp3/HttpUrl;
    //   865: invokevirtual 343	okhttp3/HttpUrl:isHttps	()Z
    //   868: ifeq +68 -> 936
    //   871: iload 5
    //   873: istore_3
    //   874: aload 22
    //   876: getfield 250	okhttp3/internal/http/CacheStrategy$Factory:cacheResponse	Lokhttp3/Response;
    //   879: getfield 347	okhttp3/Response:handshake	Lokhttp3/Handshake;
    //   882: ifnonnull +54 -> 936
    //   885: iload 5
    //   887: istore_3
    //   888: new 252	okhttp3/internal/http/CacheStrategy
    //   891: dup
    //   892: aload 22
    //   894: getfield 255	okhttp3/internal/http/CacheStrategy$Factory:request	Lokhttp3/Request;
    //   897: aconst_null
    //   898: iconst_0
    //   899: invokespecial 258	okhttp3/internal/http/CacheStrategy:<init>	(Lokhttp3/Request;Lokhttp3/Response;B)V
    //   902: astore_1
    //   903: goto -394 -> 509
    //   906: astore_1
    //   907: iload 5
    //   909: istore_3
    //   910: aload_0
    //   911: getfield 134	okhttp3/RealCall:engine	Lokhttp3/internal/http/HttpEngine;
    //   914: aload_1
    //   915: invokevirtual 338	okhttp3/internal/http/HttpEngine:recover$5d8a7524	(Ljava/io/IOException;)Lokhttp3/internal/http/HttpEngine;
    //   918: astore 17
    //   920: aload 17
    //   922: ifnull +2178 -> 3100
    //   925: iconst_0
    //   926: istore_3
    //   927: aload_0
    //   928: aload 17
    //   930: putfield 134	okhttp3/RealCall:engine	Lokhttp3/internal/http/HttpEngine;
    //   933: goto -824 -> 109
    //   936: iload 5
    //   938: istore_3
    //   939: aload 22
    //   941: getfield 250	okhttp3/internal/http/CacheStrategy$Factory:cacheResponse	Lokhttp3/Response;
    //   944: aload 22
    //   946: getfield 255	okhttp3/internal/http/CacheStrategy$Factory:request	Lokhttp3/Request;
    //   949: invokestatic 351	okhttp3/internal/http/CacheStrategy:isCacheable	(Lokhttp3/Response;Lokhttp3/Request;)Z
    //   952: ifne +24 -> 976
    //   955: iload 5
    //   957: istore_3
    //   958: new 252	okhttp3/internal/http/CacheStrategy
    //   961: dup
    //   962: aload 22
    //   964: getfield 255	okhttp3/internal/http/CacheStrategy$Factory:request	Lokhttp3/Request;
    //   967: aconst_null
    //   968: iconst_0
    //   969: invokespecial 258	okhttp3/internal/http/CacheStrategy:<init>	(Lokhttp3/Request;Lokhttp3/Response;B)V
    //   972: astore_1
    //   973: goto -464 -> 509
    //   976: iload 5
    //   978: istore_3
    //   979: aload 22
    //   981: getfield 255	okhttp3/internal/http/CacheStrategy$Factory:request	Lokhttp3/Request;
    //   984: invokevirtual 265	okhttp3/Request:cacheControl	()Lokhttp3/CacheControl;
    //   987: astore 18
    //   989: iload 5
    //   991: istore_3
    //   992: aload 18
    //   994: getfield 354	okhttp3/CacheControl:noCache	Z
    //   997: ifne +17 -> 1014
    //   1000: iload 5
    //   1002: istore_3
    //   1003: aload 22
    //   1005: getfield 255	okhttp3/internal/http/CacheStrategy$Factory:request	Lokhttp3/Request;
    //   1008: invokestatic 358	okhttp3/internal/http/CacheStrategy$Factory:hasConditions	(Lokhttp3/Request;)Z
    //   1011: ifeq +24 -> 1035
    //   1014: iload 5
    //   1016: istore_3
    //   1017: new 252	okhttp3/internal/http/CacheStrategy
    //   1020: dup
    //   1021: aload 22
    //   1023: getfield 255	okhttp3/internal/http/CacheStrategy$Factory:request	Lokhttp3/Request;
    //   1026: aconst_null
    //   1027: iconst_0
    //   1028: invokespecial 258	okhttp3/internal/http/CacheStrategy:<init>	(Lokhttp3/Request;Lokhttp3/Response;B)V
    //   1031: astore_1
    //   1032: goto -523 -> 509
    //   1035: iload 5
    //   1037: istore_3
    //   1038: aload 22
    //   1040: getfield 362	okhttp3/internal/http/CacheStrategy$Factory:servedDate	Ljava/util/Date;
    //   1043: ifnull +2686 -> 3729
    //   1046: iload 5
    //   1048: istore_3
    //   1049: lconst_0
    //   1050: aload 22
    //   1052: getfield 366	okhttp3/internal/http/CacheStrategy$Factory:receivedResponseMillis	J
    //   1055: aload 22
    //   1057: getfield 362	okhttp3/internal/http/CacheStrategy$Factory:servedDate	Ljava/util/Date;
    //   1060: invokevirtual 371	java/util/Date:getTime	()J
    //   1063: lsub
    //   1064: invokestatic 377	java/lang/Math:max	(JJ)J
    //   1067: lstore 7
    //   1069: iload 5
    //   1071: istore_3
    //   1072: lload 7
    //   1074: lstore 9
    //   1076: aload 22
    //   1078: getfield 380	okhttp3/internal/http/CacheStrategy$Factory:ageSeconds	I
    //   1081: iconst_m1
    //   1082: if_icmpeq +25 -> 1107
    //   1085: iload 5
    //   1087: istore_3
    //   1088: lload 7
    //   1090: getstatic 386	java/util/concurrent/TimeUnit:SECONDS	Ljava/util/concurrent/TimeUnit;
    //   1093: aload 22
    //   1095: getfield 380	okhttp3/internal/http/CacheStrategy$Factory:ageSeconds	I
    //   1098: i2l
    //   1099: invokevirtual 390	java/util/concurrent/TimeUnit:toMillis	(J)J
    //   1102: invokestatic 377	java/lang/Math:max	(JJ)J
    //   1105: lstore 9
    //   1107: iload 5
    //   1109: istore_3
    //   1110: lload 9
    //   1112: aload 22
    //   1114: getfield 366	okhttp3/internal/http/CacheStrategy$Factory:receivedResponseMillis	J
    //   1117: aload 22
    //   1119: getfield 393	okhttp3/internal/http/CacheStrategy$Factory:sentRequestMillis	J
    //   1122: lsub
    //   1123: ladd
    //   1124: aload 22
    //   1126: getfield 396	okhttp3/internal/http/CacheStrategy$Factory:nowMillis	J
    //   1129: aload 22
    //   1131: getfield 366	okhttp3/internal/http/CacheStrategy$Factory:receivedResponseMillis	J
    //   1134: lsub
    //   1135: ladd
    //   1136: lstore 15
    //   1138: iload 5
    //   1140: istore_3
    //   1141: aload 22
    //   1143: getfield 250	okhttp3/internal/http/CacheStrategy$Factory:cacheResponse	Lokhttp3/Response;
    //   1146: invokevirtual 397	okhttp3/Response:cacheControl	()Lokhttp3/CacheControl;
    //   1149: astore_1
    //   1150: iload 5
    //   1152: istore_3
    //   1153: aload_1
    //   1154: getfield 400	okhttp3/CacheControl:maxAgeSeconds	I
    //   1157: iconst_m1
    //   1158: if_icmpeq +283 -> 1441
    //   1161: iload 5
    //   1163: istore_3
    //   1164: getstatic 386	java/util/concurrent/TimeUnit:SECONDS	Ljava/util/concurrent/TimeUnit;
    //   1167: aload_1
    //   1168: getfield 400	okhttp3/CacheControl:maxAgeSeconds	I
    //   1171: i2l
    //   1172: invokevirtual 390	java/util/concurrent/TimeUnit:toMillis	(J)J
    //   1175: lstore 7
    //   1177: iload 5
    //   1179: istore_3
    //   1180: aload 18
    //   1182: getfield 400	okhttp3/CacheControl:maxAgeSeconds	I
    //   1185: iconst_m1
    //   1186: if_icmpeq +2540 -> 3726
    //   1189: iload 5
    //   1191: istore_3
    //   1192: lload 7
    //   1194: getstatic 386	java/util/concurrent/TimeUnit:SECONDS	Ljava/util/concurrent/TimeUnit;
    //   1197: aload 18
    //   1199: getfield 400	okhttp3/CacheControl:maxAgeSeconds	I
    //   1202: i2l
    //   1203: invokevirtual 390	java/util/concurrent/TimeUnit:toMillis	(J)J
    //   1206: invokestatic 403	java/lang/Math:min	(JJ)J
    //   1209: lstore 7
    //   1211: iload 5
    //   1213: istore_3
    //   1214: aload 18
    //   1216: getfield 406	okhttp3/CacheControl:minFreshSeconds	I
    //   1219: iconst_m1
    //   1220: if_icmpeq +2500 -> 3720
    //   1223: iload 5
    //   1225: istore_3
    //   1226: getstatic 386	java/util/concurrent/TimeUnit:SECONDS	Ljava/util/concurrent/TimeUnit;
    //   1229: aload 18
    //   1231: getfield 406	okhttp3/CacheControl:minFreshSeconds	I
    //   1234: i2l
    //   1235: invokevirtual 390	java/util/concurrent/TimeUnit:toMillis	(J)J
    //   1238: lstore 9
    //   1240: lconst_0
    //   1241: lstore 13
    //   1243: iload 5
    //   1245: istore_3
    //   1246: aload 22
    //   1248: getfield 250	okhttp3/internal/http/CacheStrategy$Factory:cacheResponse	Lokhttp3/Response;
    //   1251: invokevirtual 397	okhttp3/Response:cacheControl	()Lokhttp3/CacheControl;
    //   1254: astore_1
    //   1255: iload 5
    //   1257: istore_3
    //   1258: lload 13
    //   1260: lstore 11
    //   1262: aload_1
    //   1263: getfield 409	okhttp3/CacheControl:mustRevalidate	Z
    //   1266: ifne +36 -> 1302
    //   1269: iload 5
    //   1271: istore_3
    //   1272: lload 13
    //   1274: lstore 11
    //   1276: aload 18
    //   1278: getfield 412	okhttp3/CacheControl:maxStaleSeconds	I
    //   1281: iconst_m1
    //   1282: if_icmpeq +20 -> 1302
    //   1285: iload 5
    //   1287: istore_3
    //   1288: getstatic 386	java/util/concurrent/TimeUnit:SECONDS	Ljava/util/concurrent/TimeUnit;
    //   1291: aload 18
    //   1293: getfield 412	okhttp3/CacheControl:maxStaleSeconds	I
    //   1296: i2l
    //   1297: invokevirtual 390	java/util/concurrent/TimeUnit:toMillis	(J)J
    //   1300: lstore 11
    //   1302: iload 5
    //   1304: istore_3
    //   1305: aload_1
    //   1306: getfield 354	okhttp3/CacheControl:noCache	Z
    //   1309: ifne +365 -> 1674
    //   1312: lload 15
    //   1314: lload 9
    //   1316: ladd
    //   1317: lload 11
    //   1319: lload 7
    //   1321: ladd
    //   1322: lcmp
    //   1323: ifge +351 -> 1674
    //   1326: iload 5
    //   1328: istore_3
    //   1329: aload 22
    //   1331: getfield 250	okhttp3/internal/http/CacheStrategy$Factory:cacheResponse	Lokhttp3/Response;
    //   1334: invokevirtual 415	okhttp3/Response:newBuilder	()Lokhttp3/Response$Builder;
    //   1337: astore_1
    //   1338: lload 9
    //   1340: lload 15
    //   1342: ladd
    //   1343: lload 7
    //   1345: lcmp
    //   1346: iflt +17 -> 1363
    //   1349: iload 5
    //   1351: istore_3
    //   1352: aload_1
    //   1353: ldc_w 417
    //   1356: ldc_w 419
    //   1359: invokevirtual 423	okhttp3/Response$Builder:addHeader	(Ljava/lang/String;Ljava/lang/String;)Lokhttp3/Response$Builder;
    //   1362: pop
    //   1363: lload 15
    //   1365: ldc2_w 424
    //   1368: lcmp
    //   1369: ifle +52 -> 1421
    //   1372: iload 5
    //   1374: istore_3
    //   1375: aload 22
    //   1377: getfield 250	okhttp3/internal/http/CacheStrategy$Factory:cacheResponse	Lokhttp3/Response;
    //   1380: invokevirtual 397	okhttp3/Response:cacheControl	()Lokhttp3/CacheControl;
    //   1383: getfield 400	okhttp3/CacheControl:maxAgeSeconds	I
    //   1386: iconst_m1
    //   1387: if_icmpne +2360 -> 3747
    //   1390: iload 5
    //   1392: istore_3
    //   1393: aload 22
    //   1395: getfield 428	okhttp3/internal/http/CacheStrategy$Factory:expires	Ljava/util/Date;
    //   1398: ifnonnull +2349 -> 3747
    //   1401: iconst_1
    //   1402: istore_3
    //   1403: iload_3
    //   1404: ifeq +17 -> 1421
    //   1407: iload 5
    //   1409: istore_3
    //   1410: aload_1
    //   1411: ldc_w 417
    //   1414: ldc_w 430
    //   1417: invokevirtual 423	okhttp3/Response$Builder:addHeader	(Ljava/lang/String;Ljava/lang/String;)Lokhttp3/Response$Builder;
    //   1420: pop
    //   1421: iload 5
    //   1423: istore_3
    //   1424: new 252	okhttp3/internal/http/CacheStrategy
    //   1427: dup
    //   1428: aconst_null
    //   1429: aload_1
    //   1430: invokevirtual 325	okhttp3/Response$Builder:build	()Lokhttp3/Response;
    //   1433: iconst_0
    //   1434: invokespecial 258	okhttp3/internal/http/CacheStrategy:<init>	(Lokhttp3/Request;Lokhttp3/Response;B)V
    //   1437: astore_1
    //   1438: goto -929 -> 509
    //   1441: iload 5
    //   1443: istore_3
    //   1444: aload 22
    //   1446: getfield 428	okhttp3/internal/http/CacheStrategy$Factory:expires	Ljava/util/Date;
    //   1449: ifnull +73 -> 1522
    //   1452: iload 5
    //   1454: istore_3
    //   1455: aload 22
    //   1457: getfield 362	okhttp3/internal/http/CacheStrategy$Factory:servedDate	Ljava/util/Date;
    //   1460: ifnull +49 -> 1509
    //   1463: iload 5
    //   1465: istore_3
    //   1466: aload 22
    //   1468: getfield 362	okhttp3/internal/http/CacheStrategy$Factory:servedDate	Ljava/util/Date;
    //   1471: invokevirtual 371	java/util/Date:getTime	()J
    //   1474: lstore 7
    //   1476: iload 5
    //   1478: istore_3
    //   1479: aload 22
    //   1481: getfield 428	okhttp3/internal/http/CacheStrategy$Factory:expires	Ljava/util/Date;
    //   1484: invokevirtual 371	java/util/Date:getTime	()J
    //   1487: lload 7
    //   1489: lsub
    //   1490: lstore 9
    //   1492: lload 9
    //   1494: lstore 7
    //   1496: lload 9
    //   1498: lconst_0
    //   1499: lcmp
    //   1500: ifgt -323 -> 1177
    //   1503: lconst_0
    //   1504: lstore 7
    //   1506: goto -329 -> 1177
    //   1509: iload 5
    //   1511: istore_3
    //   1512: aload 22
    //   1514: getfield 366	okhttp3/internal/http/CacheStrategy$Factory:receivedResponseMillis	J
    //   1517: lstore 7
    //   1519: goto -43 -> 1476
    //   1522: iload 5
    //   1524: istore_3
    //   1525: aload 22
    //   1527: getfield 433	okhttp3/internal/http/CacheStrategy$Factory:lastModified	Ljava/util/Date;
    //   1530: ifnull +2211 -> 3741
    //   1533: iload 5
    //   1535: istore_3
    //   1536: aload 22
    //   1538: getfield 250	okhttp3/internal/http/CacheStrategy$Factory:cacheResponse	Lokhttp3/Response;
    //   1541: getfield 434	okhttp3/Response:request	Lokhttp3/Request;
    //   1544: getfield 177	okhttp3/Request:url	Lokhttp3/HttpUrl;
    //   1547: astore_1
    //   1548: iload 5
    //   1550: istore_3
    //   1551: aload_1
    //   1552: getfield 438	okhttp3/HttpUrl:queryNamesAndValues	Ljava/util/List;
    //   1555: ifnonnull +70 -> 1625
    //   1558: aconst_null
    //   1559: astore_1
    //   1560: aload_1
    //   1561: ifnonnull +2180 -> 3741
    //   1564: iload 5
    //   1566: istore_3
    //   1567: aload 22
    //   1569: getfield 362	okhttp3/internal/http/CacheStrategy$Factory:servedDate	Ljava/util/Date;
    //   1572: ifnull +89 -> 1661
    //   1575: iload 5
    //   1577: istore_3
    //   1578: aload 22
    //   1580: getfield 362	okhttp3/internal/http/CacheStrategy$Factory:servedDate	Ljava/util/Date;
    //   1583: invokevirtual 371	java/util/Date:getTime	()J
    //   1586: lstore 7
    //   1588: iload 5
    //   1590: istore_3
    //   1591: lload 7
    //   1593: aload 22
    //   1595: getfield 433	okhttp3/internal/http/CacheStrategy$Factory:lastModified	Ljava/util/Date;
    //   1598: invokevirtual 371	java/util/Date:getTime	()J
    //   1601: lsub
    //   1602: lstore 7
    //   1604: lload 7
    //   1606: lconst_0
    //   1607: lcmp
    //   1608: ifle +2127 -> 3735
    //   1611: iload 5
    //   1613: istore_3
    //   1614: lload 7
    //   1616: ldc2_w 439
    //   1619: ldiv
    //   1620: lstore 7
    //   1622: goto -445 -> 1177
    //   1625: iload 5
    //   1627: istore_3
    //   1628: new 442	java/lang/StringBuilder
    //   1631: dup
    //   1632: invokespecial 443	java/lang/StringBuilder:<init>	()V
    //   1635: astore 23
    //   1637: iload 5
    //   1639: istore_3
    //   1640: aload 23
    //   1642: aload_1
    //   1643: getfield 438	okhttp3/HttpUrl:queryNamesAndValues	Ljava/util/List;
    //   1646: invokestatic 447	okhttp3/HttpUrl:namesAndValuesToQueryString	(Ljava/lang/StringBuilder;Ljava/util/List;)V
    //   1649: iload 5
    //   1651: istore_3
    //   1652: aload 23
    //   1654: invokevirtual 448	java/lang/StringBuilder:toString	()Ljava/lang/String;
    //   1657: astore_1
    //   1658: goto -98 -> 1560
    //   1661: iload 5
    //   1663: istore_3
    //   1664: aload 22
    //   1666: getfield 393	okhttp3/internal/http/CacheStrategy$Factory:sentRequestMillis	J
    //   1669: lstore 7
    //   1671: goto -83 -> 1588
    //   1674: iload 5
    //   1676: istore_3
    //   1677: aload 22
    //   1679: getfield 255	okhttp3/internal/http/CacheStrategy$Factory:request	Lokhttp3/Request;
    //   1682: invokevirtual 84	okhttp3/Request:newBuilder	()Lokhttp3/Request$Builder;
    //   1685: astore_1
    //   1686: iload 5
    //   1688: istore_3
    //   1689: aload 22
    //   1691: getfield 451	okhttp3/internal/http/CacheStrategy$Factory:etag	Ljava/lang/String;
    //   1694: ifnull +58 -> 1752
    //   1697: iload 5
    //   1699: istore_3
    //   1700: aload_1
    //   1701: ldc_w 453
    //   1704: aload 22
    //   1706: getfield 451	okhttp3/internal/http/CacheStrategy$Factory:etag	Ljava/lang/String;
    //   1709: invokevirtual 104	okhttp3/Request$Builder:header	(Ljava/lang/String;Ljava/lang/String;)Lokhttp3/Request$Builder;
    //   1712: pop
    //   1713: iload 5
    //   1715: istore_3
    //   1716: aload_1
    //   1717: invokevirtual 127	okhttp3/Request$Builder:build	()Lokhttp3/Request;
    //   1720: astore_1
    //   1721: iload 5
    //   1723: istore_3
    //   1724: aload_1
    //   1725: invokestatic 358	okhttp3/internal/http/CacheStrategy$Factory:hasConditions	(Lokhttp3/Request;)Z
    //   1728: ifeq +84 -> 1812
    //   1731: iload 5
    //   1733: istore_3
    //   1734: new 252	okhttp3/internal/http/CacheStrategy
    //   1737: dup
    //   1738: aload_1
    //   1739: aload 22
    //   1741: getfield 250	okhttp3/internal/http/CacheStrategy$Factory:cacheResponse	Lokhttp3/Response;
    //   1744: iconst_0
    //   1745: invokespecial 258	okhttp3/internal/http/CacheStrategy:<init>	(Lokhttp3/Request;Lokhttp3/Response;B)V
    //   1748: astore_1
    //   1749: goto -1240 -> 509
    //   1752: iload 5
    //   1754: istore_3
    //   1755: aload 22
    //   1757: getfield 433	okhttp3/internal/http/CacheStrategy$Factory:lastModified	Ljava/util/Date;
    //   1760: ifnull +22 -> 1782
    //   1763: iload 5
    //   1765: istore_3
    //   1766: aload_1
    //   1767: ldc_w 455
    //   1770: aload 22
    //   1772: getfield 458	okhttp3/internal/http/CacheStrategy$Factory:lastModifiedString	Ljava/lang/String;
    //   1775: invokevirtual 104	okhttp3/Request$Builder:header	(Ljava/lang/String;Ljava/lang/String;)Lokhttp3/Request$Builder;
    //   1778: pop
    //   1779: goto -66 -> 1713
    //   1782: iload 5
    //   1784: istore_3
    //   1785: aload 22
    //   1787: getfield 362	okhttp3/internal/http/CacheStrategy$Factory:servedDate	Ljava/util/Date;
    //   1790: ifnull -77 -> 1713
    //   1793: iload 5
    //   1795: istore_3
    //   1796: aload_1
    //   1797: ldc_w 455
    //   1800: aload 22
    //   1802: getfield 461	okhttp3/internal/http/CacheStrategy$Factory:servedDateString	Ljava/lang/String;
    //   1805: invokevirtual 104	okhttp3/Request$Builder:header	(Ljava/lang/String;Ljava/lang/String;)Lokhttp3/Request$Builder;
    //   1808: pop
    //   1809: goto -96 -> 1713
    //   1812: iload 5
    //   1814: istore_3
    //   1815: new 252	okhttp3/internal/http/CacheStrategy
    //   1818: dup
    //   1819: aload_1
    //   1820: aconst_null
    //   1821: iconst_0
    //   1822: invokespecial 258	okhttp3/internal/http/CacheStrategy:<init>	(Lokhttp3/Request;Lokhttp3/Response;B)V
    //   1825: astore_1
    //   1826: goto -1317 -> 509
    //   1829: iload 5
    //   1831: istore_3
    //   1832: aload 19
    //   1834: getfield 271	okhttp3/internal/http/HttpEngine:networkRequest	Lokhttp3/Request;
    //   1837: ifnonnull +82 -> 1919
    //   1840: iload 5
    //   1842: istore_3
    //   1843: aload 19
    //   1845: getfield 273	okhttp3/internal/http/HttpEngine:cacheResponse	Lokhttp3/Response;
    //   1848: invokevirtual 415	okhttp3/Response:newBuilder	()Lokhttp3/Response$Builder;
    //   1851: astore_1
    //   1852: iload 5
    //   1854: istore_3
    //   1855: aload_1
    //   1856: aload 19
    //   1858: getfield 168	okhttp3/internal/http/HttpEngine:userRequest	Lokhttp3/Request;
    //   1861: putfield 290	okhttp3/Response$Builder:request	Lokhttp3/Request;
    //   1864: iload 5
    //   1866: istore_3
    //   1867: aload 19
    //   1869: aload_1
    //   1870: aload 19
    //   1872: getfield 293	okhttp3/internal/http/HttpEngine:priorResponse	Lokhttp3/Response;
    //   1875: invokestatic 297	okhttp3/internal/http/HttpEngine:stripBody	(Lokhttp3/Response;)Lokhttp3/Response;
    //   1878: invokevirtual 300	okhttp3/Response$Builder:priorResponse	(Lokhttp3/Response;)Lokhttp3/Response$Builder;
    //   1881: aload 19
    //   1883: getfield 273	okhttp3/internal/http/HttpEngine:cacheResponse	Lokhttp3/Response;
    //   1886: invokestatic 297	okhttp3/internal/http/HttpEngine:stripBody	(Lokhttp3/Response;)Lokhttp3/Response;
    //   1889: invokevirtual 463	okhttp3/Response$Builder:cacheResponse	(Lokhttp3/Response;)Lokhttp3/Response$Builder;
    //   1892: invokevirtual 325	okhttp3/Response$Builder:build	()Lokhttp3/Response;
    //   1895: putfield 328	okhttp3/internal/http/HttpEngine:userResponse	Lokhttp3/Response;
    //   1898: iload 5
    //   1900: istore_3
    //   1901: aload 19
    //   1903: aload 19
    //   1905: aload 19
    //   1907: getfield 328	okhttp3/internal/http/HttpEngine:userResponse	Lokhttp3/Response;
    //   1910: invokevirtual 466	okhttp3/internal/http/HttpEngine:unzip	(Lokhttp3/Response;)Lokhttp3/Response;
    //   1913: putfield 328	okhttp3/internal/http/HttpEngine:userResponse	Lokhttp3/Response;
    //   1916: goto -1157 -> 759
    //   1919: aload 19
    //   1921: getfield 271	okhttp3/internal/http/HttpEngine:networkRequest	Lokhttp3/Request;
    //   1924: getfield 469	okhttp3/Request:method	Ljava/lang/String;
    //   1927: ldc_w 471
    //   1930: invokevirtual 477	java/lang/String:equals	(Ljava/lang/Object;)Z
    //   1933: ifne +155 -> 2088
    //   1936: iconst_1
    //   1937: istore 6
    //   1939: aload 19
    //   1941: aload 19
    //   1943: getfield 140	okhttp3/internal/http/HttpEngine:streamAllocation	Lokhttp3/internal/http/StreamAllocation;
    //   1946: aload 19
    //   1948: getfield 195	okhttp3/internal/http/HttpEngine:client	Lokhttp3/OkHttpClient;
    //   1951: getfield 480	okhttp3/OkHttpClient:connectTimeout	I
    //   1954: aload 19
    //   1956: getfield 195	okhttp3/internal/http/HttpEngine:client	Lokhttp3/OkHttpClient;
    //   1959: getfield 483	okhttp3/OkHttpClient:readTimeout	I
    //   1962: aload 19
    //   1964: getfield 195	okhttp3/internal/http/HttpEngine:client	Lokhttp3/OkHttpClient;
    //   1967: getfield 486	okhttp3/OkHttpClient:writeTimeout	I
    //   1970: aload 19
    //   1972: getfield 195	okhttp3/internal/http/HttpEngine:client	Lokhttp3/OkHttpClient;
    //   1975: getfield 489	okhttp3/OkHttpClient:retryOnConnectionFailure	Z
    //   1978: iload 6
    //   1980: invokevirtual 493	okhttp3/internal/http/StreamAllocation:newStream	(IIIZZ)Lokhttp3/internal/http/HttpStream;
    //   1983: putfield 156	okhttp3/internal/http/HttpEngine:httpStream	Lokhttp3/internal/http/HttpStream;
    //   1986: aload 19
    //   1988: getfield 156	okhttp3/internal/http/HttpEngine:httpStream	Lokhttp3/internal/http/HttpStream;
    //   1991: aload 19
    //   1993: invokeinterface 499 2 0
    //   1998: aload 19
    //   2000: getfield 502	okhttp3/internal/http/HttpEngine:callerWritesRequestBody	Z
    //   2003: ifeq +91 -> 2094
    //   2006: aload 19
    //   2008: getfield 271	okhttp3/internal/http/HttpEngine:networkRequest	Lokhttp3/Request;
    //   2011: invokestatic 505	okhttp3/internal/http/HttpEngine:permitsRequestBody	(Lokhttp3/Request;)Z
    //   2014: ifeq +80 -> 2094
    //   2017: aload 19
    //   2019: getfield 509	okhttp3/internal/http/HttpEngine:requestBodyOut	Lokio/Sink;
    //   2022: ifnonnull +72 -> 2094
    //   2025: iconst_1
    //   2026: istore_3
    //   2027: iload_3
    //   2028: ifeq -1269 -> 759
    //   2031: aload 20
    //   2033: invokestatic 514	okhttp3/internal/http/OkHeaders:contentLength	(Lokhttp3/Request;)J
    //   2036: lstore 7
    //   2038: aload 19
    //   2040: getfield 517	okhttp3/internal/http/HttpEngine:bufferRequestBody	Z
    //   2043: ifeq +113 -> 2156
    //   2046: lload 7
    //   2048: ldc2_w 518
    //   2051: lcmp
    //   2052: ifle +47 -> 2099
    //   2055: new 35	java/lang/IllegalStateException
    //   2058: dup
    //   2059: ldc_w 521
    //   2062: invokespecial 40	java/lang/IllegalStateException:<init>	(Ljava/lang/String;)V
    //   2065: athrow
    //   2066: astore_1
    //   2067: aload 17
    //   2069: ifnull +14 -> 2083
    //   2072: iload 5
    //   2074: istore_3
    //   2075: aload 17
    //   2077: getfield 282	okhttp3/Response:body	Lokhttp3/ResponseBody;
    //   2080: invokestatic 286	okhttp3/internal/Util:closeQuietly	(Ljava/io/Closeable;)V
    //   2083: iload 5
    //   2085: istore_3
    //   2086: aload_1
    //   2087: athrow
    //   2088: iconst_0
    //   2089: istore 6
    //   2091: goto -152 -> 1939
    //   2094: iconst_0
    //   2095: istore_3
    //   2096: goto -69 -> 2027
    //   2099: lload 7
    //   2101: ldc2_w 109
    //   2104: lcmp
    //   2105: ifeq +36 -> 2141
    //   2108: aload 19
    //   2110: getfield 156	okhttp3/internal/http/HttpEngine:httpStream	Lokhttp3/internal/http/HttpStream;
    //   2113: aload 19
    //   2115: getfield 271	okhttp3/internal/http/HttpEngine:networkRequest	Lokhttp3/Request;
    //   2118: invokeinterface 525 2 0
    //   2123: aload 19
    //   2125: new 527	okhttp3/internal/http/RetryableSink
    //   2128: dup
    //   2129: lload 7
    //   2131: l2i
    //   2132: invokespecial 530	okhttp3/internal/http/RetryableSink:<init>	(I)V
    //   2135: putfield 509	okhttp3/internal/http/HttpEngine:requestBodyOut	Lokio/Sink;
    //   2138: goto -1379 -> 759
    //   2141: aload 19
    //   2143: new 527	okhttp3/internal/http/RetryableSink
    //   2146: dup
    //   2147: invokespecial 531	okhttp3/internal/http/RetryableSink:<init>	()V
    //   2150: putfield 509	okhttp3/internal/http/HttpEngine:requestBodyOut	Lokio/Sink;
    //   2153: goto -1394 -> 759
    //   2156: aload 19
    //   2158: getfield 156	okhttp3/internal/http/HttpEngine:httpStream	Lokhttp3/internal/http/HttpStream;
    //   2161: aload 19
    //   2163: getfield 271	okhttp3/internal/http/HttpEngine:networkRequest	Lokhttp3/Request;
    //   2166: invokeinterface 525 2 0
    //   2171: aload 19
    //   2173: aload 19
    //   2175: getfield 156	okhttp3/internal/http/HttpEngine:httpStream	Lokhttp3/internal/http/HttpStream;
    //   2178: aload 19
    //   2180: getfield 271	okhttp3/internal/http/HttpEngine:networkRequest	Lokhttp3/Request;
    //   2183: lload 7
    //   2185: invokeinterface 535 4 0
    //   2190: putfield 509	okhttp3/internal/http/HttpEngine:requestBodyOut	Lokio/Sink;
    //   2193: goto -1434 -> 759
    //   2196: iload 5
    //   2198: istore_3
    //   2199: aload 18
    //   2201: getfield 271	okhttp3/internal/http/HttpEngine:networkRequest	Lokhttp3/Request;
    //   2204: ifnull +250 -> 2454
    //   2207: iload 5
    //   2209: istore_3
    //   2210: aload 18
    //   2212: getfield 538	okhttp3/internal/http/HttpEngine:forWebSocket	Z
    //   2215: ifeq +259 -> 2474
    //   2218: iload 5
    //   2220: istore_3
    //   2221: aload 18
    //   2223: getfield 156	okhttp3/internal/http/HttpEngine:httpStream	Lokhttp3/internal/http/HttpStream;
    //   2226: aload 18
    //   2228: getfield 271	okhttp3/internal/http/HttpEngine:networkRequest	Lokhttp3/Request;
    //   2231: invokeinterface 525 2 0
    //   2236: iload 5
    //   2238: istore_3
    //   2239: aload 18
    //   2241: invokevirtual 541	okhttp3/internal/http/HttpEngine:readNetworkResponse	()Lokhttp3/Response;
    //   2244: astore_1
    //   2245: iload 5
    //   2247: istore_3
    //   2248: aload 18
    //   2250: aload_1
    //   2251: getfield 545	okhttp3/Response:headers	Lokhttp3/Headers;
    //   2254: invokevirtual 549	okhttp3/internal/http/HttpEngine:receiveHeaders	(Lokhttp3/Headers;)V
    //   2257: iload 5
    //   2259: istore_3
    //   2260: aload 18
    //   2262: getfield 273	okhttp3/internal/http/HttpEngine:cacheResponse	Lokhttp3/Response;
    //   2265: ifnull +512 -> 2777
    //   2268: iload 5
    //   2270: istore_3
    //   2271: aload 18
    //   2273: getfield 273	okhttp3/internal/http/HttpEngine:cacheResponse	Lokhttp3/Response;
    //   2276: aload_1
    //   2277: invokestatic 553	okhttp3/internal/http/HttpEngine:validate	(Lokhttp3/Response;Lokhttp3/Response;)Z
    //   2280: ifeq +483 -> 2763
    //   2283: iload 5
    //   2285: istore_3
    //   2286: aload 18
    //   2288: getfield 273	okhttp3/internal/http/HttpEngine:cacheResponse	Lokhttp3/Response;
    //   2291: invokevirtual 415	okhttp3/Response:newBuilder	()Lokhttp3/Response$Builder;
    //   2294: astore 17
    //   2296: iload 5
    //   2298: istore_3
    //   2299: aload 17
    //   2301: aload 18
    //   2303: getfield 168	okhttp3/internal/http/HttpEngine:userRequest	Lokhttp3/Request;
    //   2306: putfield 290	okhttp3/Response$Builder:request	Lokhttp3/Request;
    //   2309: iload 5
    //   2311: istore_3
    //   2312: aload 18
    //   2314: aload 17
    //   2316: aload 18
    //   2318: getfield 293	okhttp3/internal/http/HttpEngine:priorResponse	Lokhttp3/Response;
    //   2321: invokestatic 297	okhttp3/internal/http/HttpEngine:stripBody	(Lokhttp3/Response;)Lokhttp3/Response;
    //   2324: invokevirtual 300	okhttp3/Response$Builder:priorResponse	(Lokhttp3/Response;)Lokhttp3/Response$Builder;
    //   2327: aload 18
    //   2329: getfield 273	okhttp3/internal/http/HttpEngine:cacheResponse	Lokhttp3/Response;
    //   2332: getfield 545	okhttp3/Response:headers	Lokhttp3/Headers;
    //   2335: aload_1
    //   2336: getfield 545	okhttp3/Response:headers	Lokhttp3/Headers;
    //   2339: invokestatic 557	okhttp3/internal/http/HttpEngine:combine	(Lokhttp3/Headers;Lokhttp3/Headers;)Lokhttp3/Headers;
    //   2342: invokevirtual 560	okhttp3/Response$Builder:headers	(Lokhttp3/Headers;)Lokhttp3/Response$Builder;
    //   2345: aload 18
    //   2347: getfield 273	okhttp3/internal/http/HttpEngine:cacheResponse	Lokhttp3/Response;
    //   2350: invokestatic 297	okhttp3/internal/http/HttpEngine:stripBody	(Lokhttp3/Response;)Lokhttp3/Response;
    //   2353: invokevirtual 463	okhttp3/Response$Builder:cacheResponse	(Lokhttp3/Response;)Lokhttp3/Response$Builder;
    //   2356: aload_1
    //   2357: invokestatic 297	okhttp3/internal/http/HttpEngine:stripBody	(Lokhttp3/Response;)Lokhttp3/Response;
    //   2360: invokevirtual 563	okhttp3/Response$Builder:networkResponse	(Lokhttp3/Response;)Lokhttp3/Response$Builder;
    //   2363: invokevirtual 325	okhttp3/Response$Builder:build	()Lokhttp3/Response;
    //   2366: putfield 328	okhttp3/internal/http/HttpEngine:userResponse	Lokhttp3/Response;
    //   2369: iload 5
    //   2371: istore_3
    //   2372: aload_1
    //   2373: getfield 282	okhttp3/Response:body	Lokhttp3/ResponseBody;
    //   2376: invokevirtual 567	okhttp3/ResponseBody:close	()V
    //   2379: iload 5
    //   2381: istore_3
    //   2382: aload 18
    //   2384: getfield 140	okhttp3/internal/http/HttpEngine:streamAllocation	Lokhttp3/internal/http/StreamAllocation;
    //   2387: invokevirtual 570	okhttp3/internal/http/StreamAllocation:release	()V
    //   2390: iload 5
    //   2392: istore_3
    //   2393: getstatic 227	okhttp3/internal/Internal:instance	Lokhttp3/internal/Internal;
    //   2396: aload 18
    //   2398: getfield 195	okhttp3/internal/http/HttpEngine:client	Lokhttp3/OkHttpClient;
    //   2401: invokevirtual 231	okhttp3/internal/Internal:internalCache	(Lokhttp3/OkHttpClient;)Lokhttp3/internal/InternalCache;
    //   2404: astore_1
    //   2405: iload 5
    //   2407: istore_3
    //   2408: aload_1
    //   2409: invokeinterface 573 1 0
    //   2414: iload 5
    //   2416: istore_3
    //   2417: aload_1
    //   2418: aload 18
    //   2420: getfield 273	okhttp3/internal/http/HttpEngine:cacheResponse	Lokhttp3/Response;
    //   2423: aload 18
    //   2425: getfield 328	okhttp3/internal/http/HttpEngine:userResponse	Lokhttp3/Response;
    //   2428: invokestatic 297	okhttp3/internal/http/HttpEngine:stripBody	(Lokhttp3/Response;)Lokhttp3/Response;
    //   2431: invokeinterface 577 3 0
    //   2436: iload 5
    //   2438: istore_3
    //   2439: aload 18
    //   2441: aload 18
    //   2443: aload 18
    //   2445: getfield 328	okhttp3/internal/http/HttpEngine:userResponse	Lokhttp3/Response;
    //   2448: invokevirtual 466	okhttp3/internal/http/HttpEngine:unzip	(Lokhttp3/Response;)Lokhttp3/Response;
    //   2451: putfield 328	okhttp3/internal/http/HttpEngine:userResponse	Lokhttp3/Response;
    //   2454: aload_0
    //   2455: getfield 134	okhttp3/RealCall:engine	Lokhttp3/internal/http/HttpEngine;
    //   2458: astore_1
    //   2459: aload_1
    //   2460: getfield 328	okhttp3/internal/http/HttpEngine:userResponse	Lokhttp3/Response;
    //   2463: ifnonnull +642 -> 3105
    //   2466: new 35	java/lang/IllegalStateException
    //   2469: dup
    //   2470: invokespecial 157	java/lang/IllegalStateException:<init>	()V
    //   2473: athrow
    //   2474: iload 5
    //   2476: istore_3
    //   2477: aload 18
    //   2479: getfield 502	okhttp3/internal/http/HttpEngine:callerWritesRequestBody	Z
    //   2482: ifne +33 -> 2515
    //   2485: iload 5
    //   2487: istore_3
    //   2488: new 579	okhttp3/internal/http/HttpEngine$NetworkInterceptorChain
    //   2491: dup
    //   2492: aload 18
    //   2494: iconst_0
    //   2495: aload 18
    //   2497: getfield 271	okhttp3/internal/http/HttpEngine:networkRequest	Lokhttp3/Request;
    //   2500: invokespecial 582	okhttp3/internal/http/HttpEngine$NetworkInterceptorChain:<init>	(Lokhttp3/internal/http/HttpEngine;ILokhttp3/Request;)V
    //   2503: aload 18
    //   2505: getfield 271	okhttp3/internal/http/HttpEngine:networkRequest	Lokhttp3/Request;
    //   2508: invokevirtual 583	okhttp3/internal/http/HttpEngine$NetworkInterceptorChain:proceed	(Lokhttp3/Request;)Lokhttp3/Response;
    //   2511: astore_1
    //   2512: goto -267 -> 2245
    //   2515: iload 5
    //   2517: istore_3
    //   2518: aload 18
    //   2520: getfield 587	okhttp3/internal/http/HttpEngine:bufferedRequestBody	Lokio/BufferedSink;
    //   2523: ifnull +38 -> 2561
    //   2526: iload 5
    //   2528: istore_3
    //   2529: aload 18
    //   2531: getfield 587	okhttp3/internal/http/HttpEngine:bufferedRequestBody	Lokio/BufferedSink;
    //   2534: invokeinterface 593 1 0
    //   2539: getfield 598	okio/Buffer:size	J
    //   2542: lconst_0
    //   2543: lcmp
    //   2544: ifle +17 -> 2561
    //   2547: iload 5
    //   2549: istore_3
    //   2550: aload 18
    //   2552: getfield 587	okhttp3/internal/http/HttpEngine:bufferedRequestBody	Lokio/BufferedSink;
    //   2555: invokeinterface 602 1 0
    //   2560: pop
    //   2561: iload 5
    //   2563: istore_3
    //   2564: aload 18
    //   2566: getfield 603	okhttp3/internal/http/HttpEngine:sentRequestMillis	J
    //   2569: ldc2_w 109
    //   2572: lcmp
    //   2573: ifne +101 -> 2674
    //   2576: iload 5
    //   2578: istore_3
    //   2579: aload 18
    //   2581: getfield 271	okhttp3/internal/http/HttpEngine:networkRequest	Lokhttp3/Request;
    //   2584: invokestatic 514	okhttp3/internal/http/OkHeaders:contentLength	(Lokhttp3/Request;)J
    //   2587: ldc2_w 109
    //   2590: lcmp
    //   2591: ifne +65 -> 2656
    //   2594: iload 5
    //   2596: istore_3
    //   2597: aload 18
    //   2599: getfield 509	okhttp3/internal/http/HttpEngine:requestBodyOut	Lokio/Sink;
    //   2602: instanceof 527
    //   2605: ifeq +51 -> 2656
    //   2608: iload 5
    //   2610: istore_3
    //   2611: aload 18
    //   2613: getfield 509	okhttp3/internal/http/HttpEngine:requestBodyOut	Lokio/Sink;
    //   2616: checkcast 527	okhttp3/internal/http/RetryableSink
    //   2619: getfield 607	okhttp3/internal/http/RetryableSink:content	Lokio/Buffer;
    //   2622: getfield 598	okio/Buffer:size	J
    //   2625: lstore 7
    //   2627: iload 5
    //   2629: istore_3
    //   2630: aload 18
    //   2632: aload 18
    //   2634: getfield 271	okhttp3/internal/http/HttpEngine:networkRequest	Lokhttp3/Request;
    //   2637: invokevirtual 84	okhttp3/Request:newBuilder	()Lokhttp3/Request$Builder;
    //   2640: ldc 112
    //   2642: lload 7
    //   2644: invokestatic 117	java/lang/Long:toString	(J)Ljava/lang/String;
    //   2647: invokevirtual 104	okhttp3/Request$Builder:header	(Ljava/lang/String;Ljava/lang/String;)Lokhttp3/Request$Builder;
    //   2650: invokevirtual 127	okhttp3/Request$Builder:build	()Lokhttp3/Request;
    //   2653: putfield 271	okhttp3/internal/http/HttpEngine:networkRequest	Lokhttp3/Request;
    //   2656: iload 5
    //   2658: istore_3
    //   2659: aload 18
    //   2661: getfield 156	okhttp3/internal/http/HttpEngine:httpStream	Lokhttp3/internal/http/HttpStream;
    //   2664: aload 18
    //   2666: getfield 271	okhttp3/internal/http/HttpEngine:networkRequest	Lokhttp3/Request;
    //   2669: invokeinterface 525 2 0
    //   2674: iload 5
    //   2676: istore_3
    //   2677: aload 18
    //   2679: getfield 509	okhttp3/internal/http/HttpEngine:requestBodyOut	Lokio/Sink;
    //   2682: ifnull -446 -> 2236
    //   2685: iload 5
    //   2687: istore_3
    //   2688: aload 18
    //   2690: getfield 587	okhttp3/internal/http/HttpEngine:bufferedRequestBody	Lokio/BufferedSink;
    //   2693: ifnull +54 -> 2747
    //   2696: iload 5
    //   2698: istore_3
    //   2699: aload 18
    //   2701: getfield 587	okhttp3/internal/http/HttpEngine:bufferedRequestBody	Lokio/BufferedSink;
    //   2704: invokeinterface 608 1 0
    //   2709: iload 5
    //   2711: istore_3
    //   2712: aload 18
    //   2714: getfield 509	okhttp3/internal/http/HttpEngine:requestBodyOut	Lokio/Sink;
    //   2717: instanceof 527
    //   2720: ifeq -484 -> 2236
    //   2723: iload 5
    //   2725: istore_3
    //   2726: aload 18
    //   2728: getfield 156	okhttp3/internal/http/HttpEngine:httpStream	Lokhttp3/internal/http/HttpStream;
    //   2731: aload 18
    //   2733: getfield 509	okhttp3/internal/http/HttpEngine:requestBodyOut	Lokio/Sink;
    //   2736: checkcast 527	okhttp3/internal/http/RetryableSink
    //   2739: invokeinterface 612 2 0
    //   2744: goto -508 -> 2236
    //   2747: iload 5
    //   2749: istore_3
    //   2750: aload 18
    //   2752: getfield 509	okhttp3/internal/http/HttpEngine:requestBodyOut	Lokio/Sink;
    //   2755: invokeinterface 615 1 0
    //   2760: goto -51 -> 2709
    //   2763: iload 5
    //   2765: istore_3
    //   2766: aload 18
    //   2768: getfield 273	okhttp3/internal/http/HttpEngine:cacheResponse	Lokhttp3/Response;
    //   2771: getfield 282	okhttp3/Response:body	Lokhttp3/ResponseBody;
    //   2774: invokestatic 286	okhttp3/internal/Util:closeQuietly	(Ljava/io/Closeable;)V
    //   2777: iload 5
    //   2779: istore_3
    //   2780: aload_1
    //   2781: invokevirtual 415	okhttp3/Response:newBuilder	()Lokhttp3/Response$Builder;
    //   2784: astore 17
    //   2786: iload 5
    //   2788: istore_3
    //   2789: aload 17
    //   2791: aload 18
    //   2793: getfield 168	okhttp3/internal/http/HttpEngine:userRequest	Lokhttp3/Request;
    //   2796: putfield 290	okhttp3/Response$Builder:request	Lokhttp3/Request;
    //   2799: iload 5
    //   2801: istore_3
    //   2802: aload 18
    //   2804: aload 17
    //   2806: aload 18
    //   2808: getfield 293	okhttp3/internal/http/HttpEngine:priorResponse	Lokhttp3/Response;
    //   2811: invokestatic 297	okhttp3/internal/http/HttpEngine:stripBody	(Lokhttp3/Response;)Lokhttp3/Response;
    //   2814: invokevirtual 300	okhttp3/Response$Builder:priorResponse	(Lokhttp3/Response;)Lokhttp3/Response$Builder;
    //   2817: aload 18
    //   2819: getfield 273	okhttp3/internal/http/HttpEngine:cacheResponse	Lokhttp3/Response;
    //   2822: invokestatic 297	okhttp3/internal/http/HttpEngine:stripBody	(Lokhttp3/Response;)Lokhttp3/Response;
    //   2825: invokevirtual 463	okhttp3/Response$Builder:cacheResponse	(Lokhttp3/Response;)Lokhttp3/Response$Builder;
    //   2828: aload_1
    //   2829: invokestatic 297	okhttp3/internal/http/HttpEngine:stripBody	(Lokhttp3/Response;)Lokhttp3/Response;
    //   2832: invokevirtual 563	okhttp3/Response$Builder:networkResponse	(Lokhttp3/Response;)Lokhttp3/Response$Builder;
    //   2835: invokevirtual 325	okhttp3/Response$Builder:build	()Lokhttp3/Response;
    //   2838: putfield 328	okhttp3/internal/http/HttpEngine:userResponse	Lokhttp3/Response;
    //   2841: iload 5
    //   2843: istore_3
    //   2844: aload 18
    //   2846: getfield 328	okhttp3/internal/http/HttpEngine:userResponse	Lokhttp3/Response;
    //   2849: invokestatic 619	okhttp3/internal/http/HttpEngine:hasBody	(Lokhttp3/Response;)Z
    //   2852: ifeq -398 -> 2454
    //   2855: iload 5
    //   2857: istore_3
    //   2858: getstatic 227	okhttp3/internal/Internal:instance	Lokhttp3/internal/Internal;
    //   2861: aload 18
    //   2863: getfield 195	okhttp3/internal/http/HttpEngine:client	Lokhttp3/OkHttpClient;
    //   2866: invokevirtual 231	okhttp3/internal/Internal:internalCache	(Lokhttp3/OkHttpClient;)Lokhttp3/internal/InternalCache;
    //   2869: astore_1
    //   2870: aload_1
    //   2871: ifnull +57 -> 2928
    //   2874: iload 5
    //   2876: istore_3
    //   2877: aload 18
    //   2879: getfield 328	okhttp3/internal/http/HttpEngine:userResponse	Lokhttp3/Response;
    //   2882: aload 18
    //   2884: getfield 271	okhttp3/internal/http/HttpEngine:networkRequest	Lokhttp3/Request;
    //   2887: invokestatic 351	okhttp3/internal/http/CacheStrategy:isCacheable	(Lokhttp3/Response;Lokhttp3/Request;)Z
    //   2890: ifne +83 -> 2973
    //   2893: iload 5
    //   2895: istore_3
    //   2896: aload 18
    //   2898: getfield 271	okhttp3/internal/http/HttpEngine:networkRequest	Lokhttp3/Request;
    //   2901: getfield 469	okhttp3/Request:method	Ljava/lang/String;
    //   2904: invokestatic 625	okhttp3/internal/http/HttpMethod:invalidatesCache	(Ljava/lang/String;)Z
    //   2907: istore 6
    //   2909: iload 6
    //   2911: ifeq +17 -> 2928
    //   2914: iload 5
    //   2916: istore_3
    //   2917: aload_1
    //   2918: aload 18
    //   2920: getfield 271	okhttp3/internal/http/HttpEngine:networkRequest	Lokhttp3/Request;
    //   2923: invokeinterface 628 2 0
    //   2928: iload 5
    //   2930: istore_3
    //   2931: aload 18
    //   2933: getfield 632	okhttp3/internal/http/HttpEngine:storeRequest	Lokhttp3/internal/http/CacheRequest;
    //   2936: astore 19
    //   2938: iload 5
    //   2940: istore_3
    //   2941: aload 18
    //   2943: getfield 328	okhttp3/internal/http/HttpEngine:userResponse	Lokhttp3/Response;
    //   2946: astore 17
    //   2948: aload 19
    //   2950: ifnonnull +48 -> 2998
    //   2953: aload 17
    //   2955: astore_1
    //   2956: iload 5
    //   2958: istore_3
    //   2959: aload 18
    //   2961: aload 18
    //   2963: aload_1
    //   2964: invokevirtual 466	okhttp3/internal/http/HttpEngine:unzip	(Lokhttp3/Response;)Lokhttp3/Response;
    //   2967: putfield 328	okhttp3/internal/http/HttpEngine:userResponse	Lokhttp3/Response;
    //   2970: goto -516 -> 2454
    //   2973: iload 5
    //   2975: istore_3
    //   2976: aload 18
    //   2978: aload_1
    //   2979: aload 18
    //   2981: getfield 328	okhttp3/internal/http/HttpEngine:userResponse	Lokhttp3/Response;
    //   2984: invokestatic 297	okhttp3/internal/http/HttpEngine:stripBody	(Lokhttp3/Response;)Lokhttp3/Response;
    //   2987: invokeinterface 636 2 0
    //   2992: putfield 632	okhttp3/internal/http/HttpEngine:storeRequest	Lokhttp3/internal/http/CacheRequest;
    //   2995: goto -67 -> 2928
    //   2998: iload 5
    //   3000: istore_3
    //   3001: aload 19
    //   3003: invokeinterface 641 1 0
    //   3008: astore 20
    //   3010: aload 17
    //   3012: astore_1
    //   3013: aload 20
    //   3015: ifnull -59 -> 2956
    //   3018: iload 5
    //   3020: istore_3
    //   3021: new 643	okhttp3/internal/http/HttpEngine$2
    //   3024: dup
    //   3025: aload 18
    //   3027: aload 17
    //   3029: getfield 282	okhttp3/Response:body	Lokhttp3/ResponseBody;
    //   3032: invokevirtual 647	okhttp3/ResponseBody:source	()Lokio/BufferedSource;
    //   3035: aload 19
    //   3037: aload 20
    //   3039: invokestatic 652	okio/Okio:buffer	(Lokio/Sink;)Lokio/BufferedSink;
    //   3042: invokespecial 655	okhttp3/internal/http/HttpEngine$2:<init>	(Lokhttp3/internal/http/HttpEngine;Lokio/BufferedSource;Lokhttp3/internal/http/CacheRequest;Lokio/BufferedSink;)V
    //   3045: astore_1
    //   3046: iload 5
    //   3048: istore_3
    //   3049: aload 17
    //   3051: invokevirtual 415	okhttp3/Response:newBuilder	()Lokhttp3/Response$Builder;
    //   3054: astore 19
    //   3056: iload 5
    //   3058: istore_3
    //   3059: aload 19
    //   3061: new 657	okhttp3/internal/http/RealResponseBody
    //   3064: dup
    //   3065: aload 17
    //   3067: getfield 545	okhttp3/Response:headers	Lokhttp3/Headers;
    //   3070: aload_1
    //   3071: invokestatic 660	okio/Okio:buffer	(Lokio/Source;)Lokio/BufferedSource;
    //   3074: invokespecial 663	okhttp3/internal/http/RealResponseBody:<init>	(Lokhttp3/Headers;Lokio/BufferedSource;)V
    //   3077: putfield 323	okhttp3/Response$Builder:body	Lokhttp3/ResponseBody;
    //   3080: iload 5
    //   3082: istore_3
    //   3083: aload 19
    //   3085: invokevirtual 325	okhttp3/Response$Builder:build	()Lokhttp3/Response;
    //   3088: astore_1
    //   3089: goto -133 -> 2956
    //   3092: iload 5
    //   3094: istore_3
    //   3095: aload_1
    //   3096: getfield 334	okhttp3/internal/http/RouteException:lastException	Ljava/io/IOException;
    //   3099: athrow
    //   3100: iload 5
    //   3102: istore_3
    //   3103: aload_1
    //   3104: athrow
    //   3105: aload_1
    //   3106: getfield 328	okhttp3/internal/http/HttpEngine:userResponse	Lokhttp3/Response;
    //   3109: astore 19
    //   3111: aload_0
    //   3112: getfield 134	okhttp3/RealCall:engine	Lokhttp3/internal/http/HttpEngine;
    //   3115: astore 17
    //   3117: aload 17
    //   3119: getfield 328	okhttp3/internal/http/HttpEngine:userResponse	Lokhttp3/Response;
    //   3122: ifnonnull +11 -> 3133
    //   3125: new 35	java/lang/IllegalStateException
    //   3128: dup
    //   3129: invokespecial 157	java/lang/IllegalStateException:<init>	()V
    //   3132: athrow
    //   3133: aload 17
    //   3135: getfield 140	okhttp3/internal/http/HttpEngine:streamAllocation	Lokhttp3/internal/http/StreamAllocation;
    //   3138: invokevirtual 667	okhttp3/internal/http/StreamAllocation:connection	()Lokhttp3/internal/io/RealConnection;
    //   3141: astore_1
    //   3142: aload_1
    //   3143: ifnull +136 -> 3279
    //   3146: aload_1
    //   3147: invokeinterface 673 1 0
    //   3152: astore_1
    //   3153: aload 17
    //   3155: getfield 328	okhttp3/internal/http/HttpEngine:userResponse	Lokhttp3/Response;
    //   3158: getfield 674	okhttp3/Response:code	I
    //   3161: istore_3
    //   3162: aload 17
    //   3164: getfield 168	okhttp3/internal/http/HttpEngine:userRequest	Lokhttp3/Request;
    //   3167: getfield 469	okhttp3/Request:method	Ljava/lang/String;
    //   3170: astore 18
    //   3172: iload_3
    //   3173: lookupswitch	default:+83->3256, 300:+192->3365, 301:+192->3365, 302:+192->3365, 303:+192->3365, 307:+170->3343, 308:+170->3343, 401:+153->3326, 407:+111->3284, 408:+385->3558
    //   3256: aconst_null
    //   3257: astore_1
    //   3258: aload_1
    //   3259: ifnonnull +346 -> 3605
    //   3262: iload_2
    //   3263: ifne +13 -> 3276
    //   3266: aload_0
    //   3267: getfield 134	okhttp3/RealCall:engine	Lokhttp3/internal/http/HttpEngine;
    //   3270: getfield 140	okhttp3/internal/http/HttpEngine:streamAllocation	Lokhttp3/internal/http/StreamAllocation;
    //   3273: invokevirtual 570	okhttp3/internal/http/StreamAllocation:release	()V
    //   3276: aload 19
    //   3278: areturn
    //   3279: aconst_null
    //   3280: astore_1
    //   3281: goto -128 -> 3153
    //   3284: aload_1
    //   3285: ifnull +29 -> 3314
    //   3288: aload_1
    //   3289: getfield 680	okhttp3/Route:proxy	Ljava/net/Proxy;
    //   3292: astore_1
    //   3293: aload_1
    //   3294: invokevirtual 686	java/net/Proxy:type	()Ljava/net/Proxy$Type;
    //   3297: getstatic 692	java/net/Proxy$Type:HTTP	Ljava/net/Proxy$Type;
    //   3300: if_acmpeq +26 -> 3326
    //   3303: new 694	java/net/ProtocolException
    //   3306: dup
    //   3307: ldc_w 696
    //   3310: invokespecial 697	java/net/ProtocolException:<init>	(Ljava/lang/String;)V
    //   3313: athrow
    //   3314: aload 17
    //   3316: getfield 195	okhttp3/internal/http/HttpEngine:client	Lokhttp3/OkHttpClient;
    //   3319: getfield 698	okhttp3/OkHttpClient:proxy	Ljava/net/Proxy;
    //   3322: astore_1
    //   3323: goto -30 -> 3293
    //   3326: aload 17
    //   3328: getfield 195	okhttp3/internal/http/HttpEngine:client	Lokhttp3/OkHttpClient;
    //   3331: getfield 702	okhttp3/OkHttpClient:authenticator	Lokhttp3/Authenticator;
    //   3334: invokeinterface 707 1 0
    //   3339: astore_1
    //   3340: goto -82 -> 3258
    //   3343: aload 18
    //   3345: ldc_w 471
    //   3348: invokevirtual 477	java/lang/String:equals	(Ljava/lang/Object;)Z
    //   3351: ifne +14 -> 3365
    //   3354: aload 18
    //   3356: ldc_w 709
    //   3359: invokevirtual 477	java/lang/String:equals	(Ljava/lang/Object;)Z
    //   3362: ifeq -106 -> 3256
    //   3365: aload 17
    //   3367: getfield 195	okhttp3/internal/http/HttpEngine:client	Lokhttp3/OkHttpClient;
    //   3370: getfield 712	okhttp3/OkHttpClient:followRedirects	Z
    //   3373: ifeq -117 -> 3256
    //   3376: aload 17
    //   3378: getfield 328	okhttp3/internal/http/HttpEngine:userResponse	Lokhttp3/Response;
    //   3381: ldc_w 714
    //   3384: invokevirtual 715	okhttp3/Response:header	(Ljava/lang/String;)Ljava/lang/String;
    //   3387: astore_1
    //   3388: aload_1
    //   3389: ifnull -133 -> 3256
    //   3392: aload 17
    //   3394: getfield 168	okhttp3/internal/http/HttpEngine:userRequest	Lokhttp3/Request;
    //   3397: getfield 177	okhttp3/Request:url	Lokhttp3/HttpUrl;
    //   3400: aload_1
    //   3401: invokevirtual 719	okhttp3/HttpUrl:resolve	(Ljava/lang/String;)Lokhttp3/HttpUrl;
    //   3404: astore_1
    //   3405: aload_1
    //   3406: ifnull -150 -> 3256
    //   3409: aload_1
    //   3410: getfield 722	okhttp3/HttpUrl:scheme	Ljava/lang/String;
    //   3413: aload 17
    //   3415: getfield 168	okhttp3/internal/http/HttpEngine:userRequest	Lokhttp3/Request;
    //   3418: getfield 177	okhttp3/Request:url	Lokhttp3/HttpUrl;
    //   3421: getfield 722	okhttp3/HttpUrl:scheme	Ljava/lang/String;
    //   3424: invokevirtual 477	java/lang/String:equals	(Ljava/lang/Object;)Z
    //   3427: ifne +14 -> 3441
    //   3430: aload 17
    //   3432: getfield 195	okhttp3/internal/http/HttpEngine:client	Lokhttp3/OkHttpClient;
    //   3435: getfield 725	okhttp3/OkHttpClient:followSslRedirects	Z
    //   3438: ifeq -182 -> 3256
    //   3441: aload 17
    //   3443: getfield 168	okhttp3/internal/http/HttpEngine:userRequest	Lokhttp3/Request;
    //   3446: invokevirtual 84	okhttp3/Request:newBuilder	()Lokhttp3/Request$Builder;
    //   3449: astore 20
    //   3451: aload 18
    //   3453: invokestatic 727	okhttp3/internal/http/HttpMethod:permitsRequestBody	(Ljava/lang/String;)Z
    //   3456: ifeq +54 -> 3510
    //   3459: aload 18
    //   3461: ldc_w 729
    //   3464: invokevirtual 477	java/lang/String:equals	(Ljava/lang/Object;)Z
    //   3467: ifne +74 -> 3541
    //   3470: iconst_1
    //   3471: istore_3
    //   3472: iload_3
    //   3473: ifeq +73 -> 3546
    //   3476: aload 20
    //   3478: ldc_w 471
    //   3481: aconst_null
    //   3482: invokevirtual 732	okhttp3/Request$Builder:method	(Ljava/lang/String;Lokhttp3/RequestBody;)Lokhttp3/Request$Builder;
    //   3485: pop
    //   3486: aload 20
    //   3488: ldc 119
    //   3490: invokevirtual 123	okhttp3/Request$Builder:removeHeader	(Ljava/lang/String;)Lokhttp3/Request$Builder;
    //   3493: pop
    //   3494: aload 20
    //   3496: ldc 112
    //   3498: invokevirtual 123	okhttp3/Request$Builder:removeHeader	(Ljava/lang/String;)Lokhttp3/Request$Builder;
    //   3501: pop
    //   3502: aload 20
    //   3504: ldc 92
    //   3506: invokevirtual 123	okhttp3/Request$Builder:removeHeader	(Ljava/lang/String;)Lokhttp3/Request$Builder;
    //   3509: pop
    //   3510: aload 17
    //   3512: aload_1
    //   3513: invokevirtual 736	okhttp3/internal/http/HttpEngine:sameConnection	(Lokhttp3/HttpUrl;)Z
    //   3516: ifne +12 -> 3528
    //   3519: aload 20
    //   3521: ldc_w 738
    //   3524: invokevirtual 123	okhttp3/Request$Builder:removeHeader	(Ljava/lang/String;)Lokhttp3/Request$Builder;
    //   3527: pop
    //   3528: aload 20
    //   3530: aload_1
    //   3531: invokevirtual 741	okhttp3/Request$Builder:url	(Lokhttp3/HttpUrl;)Lokhttp3/Request$Builder;
    //   3534: invokevirtual 127	okhttp3/Request$Builder:build	()Lokhttp3/Request;
    //   3537: astore_1
    //   3538: goto -280 -> 3258
    //   3541: iconst_0
    //   3542: istore_3
    //   3543: goto -71 -> 3472
    //   3546: aload 20
    //   3548: aload 18
    //   3550: aconst_null
    //   3551: invokevirtual 732	okhttp3/Request$Builder:method	(Ljava/lang/String;Lokhttp3/RequestBody;)Lokhttp3/Request$Builder;
    //   3554: pop
    //   3555: goto -69 -> 3486
    //   3558: aload 17
    //   3560: getfield 509	okhttp3/internal/http/HttpEngine:requestBodyOut	Lokio/Sink;
    //   3563: ifnull +14 -> 3577
    //   3566: aload 17
    //   3568: getfield 509	okhttp3/internal/http/HttpEngine:requestBodyOut	Lokio/Sink;
    //   3571: instanceof 527
    //   3574: ifeq +26 -> 3600
    //   3577: iconst_1
    //   3578: istore_3
    //   3579: aload 17
    //   3581: getfield 502	okhttp3/internal/http/HttpEngine:callerWritesRequestBody	Z
    //   3584: ifeq +7 -> 3591
    //   3587: iload_3
    //   3588: ifeq -332 -> 3256
    //   3591: aload 17
    //   3593: getfield 168	okhttp3/internal/http/HttpEngine:userRequest	Lokhttp3/Request;
    //   3596: astore_1
    //   3597: goto -339 -> 3258
    //   3600: iconst_0
    //   3601: istore_3
    //   3602: goto -23 -> 3579
    //   3605: aload_0
    //   3606: getfield 134	okhttp3/RealCall:engine	Lokhttp3/internal/http/HttpEngine;
    //   3609: invokevirtual 165	okhttp3/internal/http/HttpEngine:close	()Lokhttp3/internal/http/StreamAllocation;
    //   3612: astore 18
    //   3614: iload 4
    //   3616: iconst_1
    //   3617: iadd
    //   3618: istore 4
    //   3620: iload 4
    //   3622: bipush 20
    //   3624: if_icmple +37 -> 3661
    //   3627: aload 18
    //   3629: iconst_0
    //   3630: iconst_1
    //   3631: iconst_0
    //   3632: invokevirtual 146	okhttp3/internal/http/StreamAllocation:deallocate	(ZZZ)V
    //   3635: new 694	java/net/ProtocolException
    //   3638: dup
    //   3639: new 442	java/lang/StringBuilder
    //   3642: dup
    //   3643: ldc_w 743
    //   3646: invokespecial 744	java/lang/StringBuilder:<init>	(Ljava/lang/String;)V
    //   3649: iload 4
    //   3651: invokevirtual 748	java/lang/StringBuilder:append	(I)Ljava/lang/StringBuilder;
    //   3654: invokevirtual 448	java/lang/StringBuilder:toString	()Ljava/lang/String;
    //   3657: invokespecial 697	java/net/ProtocolException:<init>	(Ljava/lang/String;)V
    //   3660: athrow
    //   3661: aload 18
    //   3663: astore 17
    //   3665: aload_0
    //   3666: getfield 134	okhttp3/RealCall:engine	Lokhttp3/internal/http/HttpEngine;
    //   3669: aload_1
    //   3670: getfield 177	okhttp3/Request:url	Lokhttp3/HttpUrl;
    //   3673: invokevirtual 736	okhttp3/internal/http/HttpEngine:sameConnection	(Lokhttp3/HttpUrl;)Z
    //   3676: ifne +14 -> 3690
    //   3679: aload 18
    //   3681: iconst_0
    //   3682: iconst_1
    //   3683: iconst_0
    //   3684: invokevirtual 146	okhttp3/internal/http/StreamAllocation:deallocate	(ZZZ)V
    //   3687: aconst_null
    //   3688: astore 17
    //   3690: aload_0
    //   3691: new 129	okhttp3/internal/http/HttpEngine
    //   3694: dup
    //   3695: aload_0
    //   3696: getfield 24	okhttp3/RealCall:client	Lokhttp3/OkHttpClient;
    //   3699: aload_1
    //   3700: iconst_0
    //   3701: iconst_0
    //   3702: iload_2
    //   3703: aload 17
    //   3705: aload 19
    //   3707: invokespecial 132	okhttp3/internal/http/HttpEngine:<init>	(Lokhttp3/OkHttpClient;Lokhttp3/Request;ZZZLokhttp3/internal/http/StreamAllocation;Lokhttp3/Response;)V
    //   3710: putfield 134	okhttp3/RealCall:engine	Lokhttp3/internal/http/HttpEngine;
    //   3713: goto -3604 -> 109
    //   3716: astore_1
    //   3717: goto -789 -> 2928
    //   3720: lconst_0
    //   3721: lstore 9
    //   3723: goto -2483 -> 1240
    //   3726: goto -2515 -> 1211
    //   3729: lconst_0
    //   3730: lstore 7
    //   3732: goto -2663 -> 1069
    //   3735: lconst_0
    //   3736: lstore 7
    //   3738: goto -2561 -> 1177
    //   3741: lconst_0
    //   3742: lstore 7
    //   3744: goto -2567 -> 1177
    //   3747: iconst_0
    //   3748: istore_3
    //   3749: goto -2346 -> 1403
    // Local variable table:
    //   start	length	slot	name	signature
    //   0	3752	0	this	RealCall
    //   0	3752	1	paramRequest	Request
    //   0	3752	2	paramBoolean	boolean
    //   163	3586	3	i	int
    //   107	3543	4	j	int
    //   159	2942	5	k	int
    //   1937	973	6	bool	boolean
    //   48	3695	7	l1	long
    //   1074	2648	9	l2	long
    //   1260	58	11	l3	long
    //   1241	32	13	l4	long
    //   1136	228	15	l5	long
    //   7	3697	17	localObject1	Object
    //   4	3676	18	localObject2	Object
    //   168	3538	19	localObject3	Object
    //   424	3123	20	localObject4	Object
    //   440	168	21	localInternalCache	okhttp3.internal.InternalCache
    //   478	1323	22	localFactory	okhttp3.internal.http.CacheStrategy.Factory
    //   1635	18	23	localStringBuilder	StringBuilder
    // Exception table:
    //   from	to	target	type
    //   164	170	203	okhttp3/internal/http/RequestException
    //   173	181	203	okhttp3/internal/http/RequestException
    //   184	192	203	okhttp3/internal/http/RequestException
    //   195	203	203	okhttp3/internal/http/RequestException
    //   235	241	203	okhttp3/internal/http/RequestException
    //   244	250	203	okhttp3/internal/http/RequestException
    //   253	262	203	okhttp3/internal/http/RequestException
    //   265	281	203	okhttp3/internal/http/RequestException
    //   284	293	203	okhttp3/internal/http/RequestException
    //   296	306	203	okhttp3/internal/http/RequestException
    //   309	318	203	okhttp3/internal/http/RequestException
    //   321	327	203	okhttp3/internal/http/RequestException
    //   330	340	203	okhttp3/internal/http/RequestException
    //   343	362	203	okhttp3/internal/http/RequestException
    //   365	375	203	okhttp3/internal/http/RequestException
    //   378	391	203	okhttp3/internal/http/RequestException
    //   394	403	203	okhttp3/internal/http/RequestException
    //   406	416	203	okhttp3/internal/http/RequestException
    //   419	426	203	okhttp3/internal/http/RequestException
    //   429	442	203	okhttp3/internal/http/RequestException
    //   450	461	203	okhttp3/internal/http/RequestException
    //   464	480	203	okhttp3/internal/http/RequestException
    //   483	491	203	okhttp3/internal/http/RequestException
    //   494	509	203	okhttp3/internal/http/RequestException
    //   515	522	203	okhttp3/internal/http/RequestException
    //   528	542	203	okhttp3/internal/http/RequestException
    //   545	557	203	okhttp3/internal/http/RequestException
    //   560	567	203	okhttp3/internal/http/RequestException
    //   570	583	203	okhttp3/internal/http/RequestException
    //   586	599	203	okhttp3/internal/http/RequestException
    //   607	619	203	okhttp3/internal/http/RequestException
    //   627	635	203	okhttp3/internal/http/RequestException
    //   638	646	203	okhttp3/internal/http/RequestException
    //   649	657	203	okhttp3/internal/http/RequestException
    //   660	668	203	okhttp3/internal/http/RequestException
    //   671	679	203	okhttp3/internal/http/RequestException
    //   682	691	203	okhttp3/internal/http/RequestException
    //   694	707	203	okhttp3/internal/http/RequestException
    //   710	717	203	okhttp3/internal/http/RequestException
    //   720	727	203	okhttp3/internal/http/RequestException
    //   730	737	203	okhttp3/internal/http/RequestException
    //   740	747	203	okhttp3/internal/http/RequestException
    //   750	759	203	okhttp3/internal/http/RequestException
    //   762	768	203	okhttp3/internal/http/RequestException
    //   771	779	203	okhttp3/internal/http/RequestException
    //   782	790	203	okhttp3/internal/http/RequestException
    //   793	801	203	okhttp3/internal/http/RequestException
    //   804	815	203	okhttp3/internal/http/RequestException
    //   857	871	203	okhttp3/internal/http/RequestException
    //   874	885	203	okhttp3/internal/http/RequestException
    //   888	903	203	okhttp3/internal/http/RequestException
    //   939	955	203	okhttp3/internal/http/RequestException
    //   958	973	203	okhttp3/internal/http/RequestException
    //   979	989	203	okhttp3/internal/http/RequestException
    //   992	1000	203	okhttp3/internal/http/RequestException
    //   1003	1014	203	okhttp3/internal/http/RequestException
    //   1017	1032	203	okhttp3/internal/http/RequestException
    //   1038	1046	203	okhttp3/internal/http/RequestException
    //   1049	1069	203	okhttp3/internal/http/RequestException
    //   1076	1085	203	okhttp3/internal/http/RequestException
    //   1088	1107	203	okhttp3/internal/http/RequestException
    //   1110	1138	203	okhttp3/internal/http/RequestException
    //   1141	1150	203	okhttp3/internal/http/RequestException
    //   1153	1161	203	okhttp3/internal/http/RequestException
    //   1164	1177	203	okhttp3/internal/http/RequestException
    //   1180	1189	203	okhttp3/internal/http/RequestException
    //   1192	1211	203	okhttp3/internal/http/RequestException
    //   1214	1223	203	okhttp3/internal/http/RequestException
    //   1226	1240	203	okhttp3/internal/http/RequestException
    //   1246	1255	203	okhttp3/internal/http/RequestException
    //   1262	1269	203	okhttp3/internal/http/RequestException
    //   1276	1285	203	okhttp3/internal/http/RequestException
    //   1288	1302	203	okhttp3/internal/http/RequestException
    //   1305	1312	203	okhttp3/internal/http/RequestException
    //   1329	1338	203	okhttp3/internal/http/RequestException
    //   1352	1363	203	okhttp3/internal/http/RequestException
    //   1375	1390	203	okhttp3/internal/http/RequestException
    //   1393	1401	203	okhttp3/internal/http/RequestException
    //   1410	1421	203	okhttp3/internal/http/RequestException
    //   1424	1438	203	okhttp3/internal/http/RequestException
    //   1444	1452	203	okhttp3/internal/http/RequestException
    //   1455	1463	203	okhttp3/internal/http/RequestException
    //   1466	1476	203	okhttp3/internal/http/RequestException
    //   1479	1492	203	okhttp3/internal/http/RequestException
    //   1512	1519	203	okhttp3/internal/http/RequestException
    //   1525	1533	203	okhttp3/internal/http/RequestException
    //   1536	1548	203	okhttp3/internal/http/RequestException
    //   1551	1558	203	okhttp3/internal/http/RequestException
    //   1567	1575	203	okhttp3/internal/http/RequestException
    //   1578	1588	203	okhttp3/internal/http/RequestException
    //   1591	1604	203	okhttp3/internal/http/RequestException
    //   1614	1622	203	okhttp3/internal/http/RequestException
    //   1628	1637	203	okhttp3/internal/http/RequestException
    //   1640	1649	203	okhttp3/internal/http/RequestException
    //   1652	1658	203	okhttp3/internal/http/RequestException
    //   1664	1671	203	okhttp3/internal/http/RequestException
    //   1677	1686	203	okhttp3/internal/http/RequestException
    //   1689	1697	203	okhttp3/internal/http/RequestException
    //   1700	1713	203	okhttp3/internal/http/RequestException
    //   1716	1721	203	okhttp3/internal/http/RequestException
    //   1724	1731	203	okhttp3/internal/http/RequestException
    //   1734	1749	203	okhttp3/internal/http/RequestException
    //   1755	1763	203	okhttp3/internal/http/RequestException
    //   1766	1779	203	okhttp3/internal/http/RequestException
    //   1785	1793	203	okhttp3/internal/http/RequestException
    //   1796	1809	203	okhttp3/internal/http/RequestException
    //   1815	1826	203	okhttp3/internal/http/RequestException
    //   1832	1840	203	okhttp3/internal/http/RequestException
    //   1843	1852	203	okhttp3/internal/http/RequestException
    //   1855	1864	203	okhttp3/internal/http/RequestException
    //   1867	1898	203	okhttp3/internal/http/RequestException
    //   1901	1916	203	okhttp3/internal/http/RequestException
    //   2075	2083	203	okhttp3/internal/http/RequestException
    //   2086	2088	203	okhttp3/internal/http/RequestException
    //   2199	2207	203	okhttp3/internal/http/RequestException
    //   2210	2218	203	okhttp3/internal/http/RequestException
    //   2221	2236	203	okhttp3/internal/http/RequestException
    //   2239	2245	203	okhttp3/internal/http/RequestException
    //   2248	2257	203	okhttp3/internal/http/RequestException
    //   2260	2268	203	okhttp3/internal/http/RequestException
    //   2271	2283	203	okhttp3/internal/http/RequestException
    //   2286	2296	203	okhttp3/internal/http/RequestException
    //   2299	2309	203	okhttp3/internal/http/RequestException
    //   2312	2369	203	okhttp3/internal/http/RequestException
    //   2372	2379	203	okhttp3/internal/http/RequestException
    //   2382	2390	203	okhttp3/internal/http/RequestException
    //   2393	2405	203	okhttp3/internal/http/RequestException
    //   2408	2414	203	okhttp3/internal/http/RequestException
    //   2417	2436	203	okhttp3/internal/http/RequestException
    //   2439	2454	203	okhttp3/internal/http/RequestException
    //   2477	2485	203	okhttp3/internal/http/RequestException
    //   2488	2512	203	okhttp3/internal/http/RequestException
    //   2518	2526	203	okhttp3/internal/http/RequestException
    //   2529	2547	203	okhttp3/internal/http/RequestException
    //   2550	2561	203	okhttp3/internal/http/RequestException
    //   2564	2576	203	okhttp3/internal/http/RequestException
    //   2579	2594	203	okhttp3/internal/http/RequestException
    //   2597	2608	203	okhttp3/internal/http/RequestException
    //   2611	2627	203	okhttp3/internal/http/RequestException
    //   2630	2656	203	okhttp3/internal/http/RequestException
    //   2659	2674	203	okhttp3/internal/http/RequestException
    //   2677	2685	203	okhttp3/internal/http/RequestException
    //   2688	2696	203	okhttp3/internal/http/RequestException
    //   2699	2709	203	okhttp3/internal/http/RequestException
    //   2712	2723	203	okhttp3/internal/http/RequestException
    //   2726	2744	203	okhttp3/internal/http/RequestException
    //   2750	2760	203	okhttp3/internal/http/RequestException
    //   2766	2777	203	okhttp3/internal/http/RequestException
    //   2780	2786	203	okhttp3/internal/http/RequestException
    //   2789	2799	203	okhttp3/internal/http/RequestException
    //   2802	2841	203	okhttp3/internal/http/RequestException
    //   2844	2855	203	okhttp3/internal/http/RequestException
    //   2858	2870	203	okhttp3/internal/http/RequestException
    //   2877	2893	203	okhttp3/internal/http/RequestException
    //   2896	2909	203	okhttp3/internal/http/RequestException
    //   2917	2928	203	okhttp3/internal/http/RequestException
    //   2931	2938	203	okhttp3/internal/http/RequestException
    //   2941	2948	203	okhttp3/internal/http/RequestException
    //   2959	2970	203	okhttp3/internal/http/RequestException
    //   2976	2995	203	okhttp3/internal/http/RequestException
    //   3001	3010	203	okhttp3/internal/http/RequestException
    //   3021	3046	203	okhttp3/internal/http/RequestException
    //   3049	3056	203	okhttp3/internal/http/RequestException
    //   3059	3080	203	okhttp3/internal/http/RequestException
    //   3083	3089	203	okhttp3/internal/http/RequestException
    //   164	170	212	finally
    //   173	181	212	finally
    //   184	192	212	finally
    //   195	203	212	finally
    //   207	212	212	finally
    //   235	241	212	finally
    //   244	250	212	finally
    //   253	262	212	finally
    //   265	281	212	finally
    //   284	293	212	finally
    //   296	306	212	finally
    //   309	318	212	finally
    //   321	327	212	finally
    //   330	340	212	finally
    //   343	362	212	finally
    //   365	375	212	finally
    //   378	391	212	finally
    //   394	403	212	finally
    //   406	416	212	finally
    //   419	426	212	finally
    //   429	442	212	finally
    //   450	461	212	finally
    //   464	480	212	finally
    //   483	491	212	finally
    //   494	509	212	finally
    //   515	522	212	finally
    //   528	542	212	finally
    //   545	557	212	finally
    //   560	567	212	finally
    //   570	583	212	finally
    //   586	599	212	finally
    //   607	619	212	finally
    //   627	635	212	finally
    //   638	646	212	finally
    //   649	657	212	finally
    //   660	668	212	finally
    //   671	679	212	finally
    //   682	691	212	finally
    //   694	707	212	finally
    //   710	717	212	finally
    //   720	727	212	finally
    //   730	737	212	finally
    //   740	747	212	finally
    //   750	759	212	finally
    //   762	768	212	finally
    //   771	779	212	finally
    //   782	790	212	finally
    //   793	801	212	finally
    //   804	815	212	finally
    //   819	832	212	finally
    //   839	845	212	finally
    //   857	871	212	finally
    //   874	885	212	finally
    //   888	903	212	finally
    //   910	920	212	finally
    //   927	933	212	finally
    //   939	955	212	finally
    //   958	973	212	finally
    //   979	989	212	finally
    //   992	1000	212	finally
    //   1003	1014	212	finally
    //   1017	1032	212	finally
    //   1038	1046	212	finally
    //   1049	1069	212	finally
    //   1076	1085	212	finally
    //   1088	1107	212	finally
    //   1110	1138	212	finally
    //   1141	1150	212	finally
    //   1153	1161	212	finally
    //   1164	1177	212	finally
    //   1180	1189	212	finally
    //   1192	1211	212	finally
    //   1214	1223	212	finally
    //   1226	1240	212	finally
    //   1246	1255	212	finally
    //   1262	1269	212	finally
    //   1276	1285	212	finally
    //   1288	1302	212	finally
    //   1305	1312	212	finally
    //   1329	1338	212	finally
    //   1352	1363	212	finally
    //   1375	1390	212	finally
    //   1393	1401	212	finally
    //   1410	1421	212	finally
    //   1424	1438	212	finally
    //   1444	1452	212	finally
    //   1455	1463	212	finally
    //   1466	1476	212	finally
    //   1479	1492	212	finally
    //   1512	1519	212	finally
    //   1525	1533	212	finally
    //   1536	1548	212	finally
    //   1551	1558	212	finally
    //   1567	1575	212	finally
    //   1578	1588	212	finally
    //   1591	1604	212	finally
    //   1614	1622	212	finally
    //   1628	1637	212	finally
    //   1640	1649	212	finally
    //   1652	1658	212	finally
    //   1664	1671	212	finally
    //   1677	1686	212	finally
    //   1689	1697	212	finally
    //   1700	1713	212	finally
    //   1716	1721	212	finally
    //   1724	1731	212	finally
    //   1734	1749	212	finally
    //   1755	1763	212	finally
    //   1766	1779	212	finally
    //   1785	1793	212	finally
    //   1796	1809	212	finally
    //   1815	1826	212	finally
    //   1832	1840	212	finally
    //   1843	1852	212	finally
    //   1855	1864	212	finally
    //   1867	1898	212	finally
    //   1901	1916	212	finally
    //   2075	2083	212	finally
    //   2086	2088	212	finally
    //   2199	2207	212	finally
    //   2210	2218	212	finally
    //   2221	2236	212	finally
    //   2239	2245	212	finally
    //   2248	2257	212	finally
    //   2260	2268	212	finally
    //   2271	2283	212	finally
    //   2286	2296	212	finally
    //   2299	2309	212	finally
    //   2312	2369	212	finally
    //   2372	2379	212	finally
    //   2382	2390	212	finally
    //   2393	2405	212	finally
    //   2408	2414	212	finally
    //   2417	2436	212	finally
    //   2439	2454	212	finally
    //   2477	2485	212	finally
    //   2488	2512	212	finally
    //   2518	2526	212	finally
    //   2529	2547	212	finally
    //   2550	2561	212	finally
    //   2564	2576	212	finally
    //   2579	2594	212	finally
    //   2597	2608	212	finally
    //   2611	2627	212	finally
    //   2630	2656	212	finally
    //   2659	2674	212	finally
    //   2677	2685	212	finally
    //   2688	2696	212	finally
    //   2699	2709	212	finally
    //   2712	2723	212	finally
    //   2726	2744	212	finally
    //   2750	2760	212	finally
    //   2766	2777	212	finally
    //   2780	2786	212	finally
    //   2789	2799	212	finally
    //   2802	2841	212	finally
    //   2844	2855	212	finally
    //   2858	2870	212	finally
    //   2877	2893	212	finally
    //   2896	2909	212	finally
    //   2917	2928	212	finally
    //   2931	2938	212	finally
    //   2941	2948	212	finally
    //   2959	2970	212	finally
    //   2976	2995	212	finally
    //   3001	3010	212	finally
    //   3021	3046	212	finally
    //   3049	3056	212	finally
    //   3059	3080	212	finally
    //   3083	3089	212	finally
    //   3095	3100	212	finally
    //   3103	3105	212	finally
    //   164	170	815	okhttp3/internal/http/RouteException
    //   173	181	815	okhttp3/internal/http/RouteException
    //   184	192	815	okhttp3/internal/http/RouteException
    //   195	203	815	okhttp3/internal/http/RouteException
    //   235	241	815	okhttp3/internal/http/RouteException
    //   244	250	815	okhttp3/internal/http/RouteException
    //   253	262	815	okhttp3/internal/http/RouteException
    //   265	281	815	okhttp3/internal/http/RouteException
    //   284	293	815	okhttp3/internal/http/RouteException
    //   296	306	815	okhttp3/internal/http/RouteException
    //   309	318	815	okhttp3/internal/http/RouteException
    //   321	327	815	okhttp3/internal/http/RouteException
    //   330	340	815	okhttp3/internal/http/RouteException
    //   343	362	815	okhttp3/internal/http/RouteException
    //   365	375	815	okhttp3/internal/http/RouteException
    //   378	391	815	okhttp3/internal/http/RouteException
    //   394	403	815	okhttp3/internal/http/RouteException
    //   406	416	815	okhttp3/internal/http/RouteException
    //   419	426	815	okhttp3/internal/http/RouteException
    //   429	442	815	okhttp3/internal/http/RouteException
    //   450	461	815	okhttp3/internal/http/RouteException
    //   464	480	815	okhttp3/internal/http/RouteException
    //   483	491	815	okhttp3/internal/http/RouteException
    //   494	509	815	okhttp3/internal/http/RouteException
    //   515	522	815	okhttp3/internal/http/RouteException
    //   528	542	815	okhttp3/internal/http/RouteException
    //   545	557	815	okhttp3/internal/http/RouteException
    //   560	567	815	okhttp3/internal/http/RouteException
    //   570	583	815	okhttp3/internal/http/RouteException
    //   586	599	815	okhttp3/internal/http/RouteException
    //   607	619	815	okhttp3/internal/http/RouteException
    //   627	635	815	okhttp3/internal/http/RouteException
    //   638	646	815	okhttp3/internal/http/RouteException
    //   649	657	815	okhttp3/internal/http/RouteException
    //   660	668	815	okhttp3/internal/http/RouteException
    //   671	679	815	okhttp3/internal/http/RouteException
    //   682	691	815	okhttp3/internal/http/RouteException
    //   694	707	815	okhttp3/internal/http/RouteException
    //   710	717	815	okhttp3/internal/http/RouteException
    //   720	727	815	okhttp3/internal/http/RouteException
    //   730	737	815	okhttp3/internal/http/RouteException
    //   740	747	815	okhttp3/internal/http/RouteException
    //   750	759	815	okhttp3/internal/http/RouteException
    //   762	768	815	okhttp3/internal/http/RouteException
    //   771	779	815	okhttp3/internal/http/RouteException
    //   782	790	815	okhttp3/internal/http/RouteException
    //   793	801	815	okhttp3/internal/http/RouteException
    //   804	815	815	okhttp3/internal/http/RouteException
    //   857	871	815	okhttp3/internal/http/RouteException
    //   874	885	815	okhttp3/internal/http/RouteException
    //   888	903	815	okhttp3/internal/http/RouteException
    //   939	955	815	okhttp3/internal/http/RouteException
    //   958	973	815	okhttp3/internal/http/RouteException
    //   979	989	815	okhttp3/internal/http/RouteException
    //   992	1000	815	okhttp3/internal/http/RouteException
    //   1003	1014	815	okhttp3/internal/http/RouteException
    //   1017	1032	815	okhttp3/internal/http/RouteException
    //   1038	1046	815	okhttp3/internal/http/RouteException
    //   1049	1069	815	okhttp3/internal/http/RouteException
    //   1076	1085	815	okhttp3/internal/http/RouteException
    //   1088	1107	815	okhttp3/internal/http/RouteException
    //   1110	1138	815	okhttp3/internal/http/RouteException
    //   1141	1150	815	okhttp3/internal/http/RouteException
    //   1153	1161	815	okhttp3/internal/http/RouteException
    //   1164	1177	815	okhttp3/internal/http/RouteException
    //   1180	1189	815	okhttp3/internal/http/RouteException
    //   1192	1211	815	okhttp3/internal/http/RouteException
    //   1214	1223	815	okhttp3/internal/http/RouteException
    //   1226	1240	815	okhttp3/internal/http/RouteException
    //   1246	1255	815	okhttp3/internal/http/RouteException
    //   1262	1269	815	okhttp3/internal/http/RouteException
    //   1276	1285	815	okhttp3/internal/http/RouteException
    //   1288	1302	815	okhttp3/internal/http/RouteException
    //   1305	1312	815	okhttp3/internal/http/RouteException
    //   1329	1338	815	okhttp3/internal/http/RouteException
    //   1352	1363	815	okhttp3/internal/http/RouteException
    //   1375	1390	815	okhttp3/internal/http/RouteException
    //   1393	1401	815	okhttp3/internal/http/RouteException
    //   1410	1421	815	okhttp3/internal/http/RouteException
    //   1424	1438	815	okhttp3/internal/http/RouteException
    //   1444	1452	815	okhttp3/internal/http/RouteException
    //   1455	1463	815	okhttp3/internal/http/RouteException
    //   1466	1476	815	okhttp3/internal/http/RouteException
    //   1479	1492	815	okhttp3/internal/http/RouteException
    //   1512	1519	815	okhttp3/internal/http/RouteException
    //   1525	1533	815	okhttp3/internal/http/RouteException
    //   1536	1548	815	okhttp3/internal/http/RouteException
    //   1551	1558	815	okhttp3/internal/http/RouteException
    //   1567	1575	815	okhttp3/internal/http/RouteException
    //   1578	1588	815	okhttp3/internal/http/RouteException
    //   1591	1604	815	okhttp3/internal/http/RouteException
    //   1614	1622	815	okhttp3/internal/http/RouteException
    //   1628	1637	815	okhttp3/internal/http/RouteException
    //   1640	1649	815	okhttp3/internal/http/RouteException
    //   1652	1658	815	okhttp3/internal/http/RouteException
    //   1664	1671	815	okhttp3/internal/http/RouteException
    //   1677	1686	815	okhttp3/internal/http/RouteException
    //   1689	1697	815	okhttp3/internal/http/RouteException
    //   1700	1713	815	okhttp3/internal/http/RouteException
    //   1716	1721	815	okhttp3/internal/http/RouteException
    //   1724	1731	815	okhttp3/internal/http/RouteException
    //   1734	1749	815	okhttp3/internal/http/RouteException
    //   1755	1763	815	okhttp3/internal/http/RouteException
    //   1766	1779	815	okhttp3/internal/http/RouteException
    //   1785	1793	815	okhttp3/internal/http/RouteException
    //   1796	1809	815	okhttp3/internal/http/RouteException
    //   1815	1826	815	okhttp3/internal/http/RouteException
    //   1832	1840	815	okhttp3/internal/http/RouteException
    //   1843	1852	815	okhttp3/internal/http/RouteException
    //   1855	1864	815	okhttp3/internal/http/RouteException
    //   1867	1898	815	okhttp3/internal/http/RouteException
    //   1901	1916	815	okhttp3/internal/http/RouteException
    //   2075	2083	815	okhttp3/internal/http/RouteException
    //   2086	2088	815	okhttp3/internal/http/RouteException
    //   2199	2207	815	okhttp3/internal/http/RouteException
    //   2210	2218	815	okhttp3/internal/http/RouteException
    //   2221	2236	815	okhttp3/internal/http/RouteException
    //   2239	2245	815	okhttp3/internal/http/RouteException
    //   2248	2257	815	okhttp3/internal/http/RouteException
    //   2260	2268	815	okhttp3/internal/http/RouteException
    //   2271	2283	815	okhttp3/internal/http/RouteException
    //   2286	2296	815	okhttp3/internal/http/RouteException
    //   2299	2309	815	okhttp3/internal/http/RouteException
    //   2312	2369	815	okhttp3/internal/http/RouteException
    //   2372	2379	815	okhttp3/internal/http/RouteException
    //   2382	2390	815	okhttp3/internal/http/RouteException
    //   2393	2405	815	okhttp3/internal/http/RouteException
    //   2408	2414	815	okhttp3/internal/http/RouteException
    //   2417	2436	815	okhttp3/internal/http/RouteException
    //   2439	2454	815	okhttp3/internal/http/RouteException
    //   2477	2485	815	okhttp3/internal/http/RouteException
    //   2488	2512	815	okhttp3/internal/http/RouteException
    //   2518	2526	815	okhttp3/internal/http/RouteException
    //   2529	2547	815	okhttp3/internal/http/RouteException
    //   2550	2561	815	okhttp3/internal/http/RouteException
    //   2564	2576	815	okhttp3/internal/http/RouteException
    //   2579	2594	815	okhttp3/internal/http/RouteException
    //   2597	2608	815	okhttp3/internal/http/RouteException
    //   2611	2627	815	okhttp3/internal/http/RouteException
    //   2630	2656	815	okhttp3/internal/http/RouteException
    //   2659	2674	815	okhttp3/internal/http/RouteException
    //   2677	2685	815	okhttp3/internal/http/RouteException
    //   2688	2696	815	okhttp3/internal/http/RouteException
    //   2699	2709	815	okhttp3/internal/http/RouteException
    //   2712	2723	815	okhttp3/internal/http/RouteException
    //   2726	2744	815	okhttp3/internal/http/RouteException
    //   2750	2760	815	okhttp3/internal/http/RouteException
    //   2766	2777	815	okhttp3/internal/http/RouteException
    //   2780	2786	815	okhttp3/internal/http/RouteException
    //   2789	2799	815	okhttp3/internal/http/RouteException
    //   2802	2841	815	okhttp3/internal/http/RouteException
    //   2844	2855	815	okhttp3/internal/http/RouteException
    //   2858	2870	815	okhttp3/internal/http/RouteException
    //   2877	2893	815	okhttp3/internal/http/RouteException
    //   2896	2909	815	okhttp3/internal/http/RouteException
    //   2917	2928	815	okhttp3/internal/http/RouteException
    //   2931	2938	815	okhttp3/internal/http/RouteException
    //   2941	2948	815	okhttp3/internal/http/RouteException
    //   2959	2970	815	okhttp3/internal/http/RouteException
    //   2976	2995	815	okhttp3/internal/http/RouteException
    //   3001	3010	815	okhttp3/internal/http/RouteException
    //   3021	3046	815	okhttp3/internal/http/RouteException
    //   3049	3056	815	okhttp3/internal/http/RouteException
    //   3059	3080	815	okhttp3/internal/http/RouteException
    //   3083	3089	815	okhttp3/internal/http/RouteException
    //   164	170	906	java/io/IOException
    //   173	181	906	java/io/IOException
    //   184	192	906	java/io/IOException
    //   195	203	906	java/io/IOException
    //   235	241	906	java/io/IOException
    //   244	250	906	java/io/IOException
    //   253	262	906	java/io/IOException
    //   265	281	906	java/io/IOException
    //   284	293	906	java/io/IOException
    //   296	306	906	java/io/IOException
    //   309	318	906	java/io/IOException
    //   321	327	906	java/io/IOException
    //   330	340	906	java/io/IOException
    //   343	362	906	java/io/IOException
    //   365	375	906	java/io/IOException
    //   378	391	906	java/io/IOException
    //   394	403	906	java/io/IOException
    //   406	416	906	java/io/IOException
    //   419	426	906	java/io/IOException
    //   429	442	906	java/io/IOException
    //   450	461	906	java/io/IOException
    //   464	480	906	java/io/IOException
    //   483	491	906	java/io/IOException
    //   494	509	906	java/io/IOException
    //   515	522	906	java/io/IOException
    //   528	542	906	java/io/IOException
    //   545	557	906	java/io/IOException
    //   560	567	906	java/io/IOException
    //   570	583	906	java/io/IOException
    //   586	599	906	java/io/IOException
    //   607	619	906	java/io/IOException
    //   627	635	906	java/io/IOException
    //   638	646	906	java/io/IOException
    //   649	657	906	java/io/IOException
    //   660	668	906	java/io/IOException
    //   671	679	906	java/io/IOException
    //   682	691	906	java/io/IOException
    //   694	707	906	java/io/IOException
    //   710	717	906	java/io/IOException
    //   720	727	906	java/io/IOException
    //   730	737	906	java/io/IOException
    //   740	747	906	java/io/IOException
    //   750	759	906	java/io/IOException
    //   762	768	906	java/io/IOException
    //   771	779	906	java/io/IOException
    //   782	790	906	java/io/IOException
    //   793	801	906	java/io/IOException
    //   804	815	906	java/io/IOException
    //   857	871	906	java/io/IOException
    //   874	885	906	java/io/IOException
    //   888	903	906	java/io/IOException
    //   939	955	906	java/io/IOException
    //   958	973	906	java/io/IOException
    //   979	989	906	java/io/IOException
    //   992	1000	906	java/io/IOException
    //   1003	1014	906	java/io/IOException
    //   1017	1032	906	java/io/IOException
    //   1038	1046	906	java/io/IOException
    //   1049	1069	906	java/io/IOException
    //   1076	1085	906	java/io/IOException
    //   1088	1107	906	java/io/IOException
    //   1110	1138	906	java/io/IOException
    //   1141	1150	906	java/io/IOException
    //   1153	1161	906	java/io/IOException
    //   1164	1177	906	java/io/IOException
    //   1180	1189	906	java/io/IOException
    //   1192	1211	906	java/io/IOException
    //   1214	1223	906	java/io/IOException
    //   1226	1240	906	java/io/IOException
    //   1246	1255	906	java/io/IOException
    //   1262	1269	906	java/io/IOException
    //   1276	1285	906	java/io/IOException
    //   1288	1302	906	java/io/IOException
    //   1305	1312	906	java/io/IOException
    //   1329	1338	906	java/io/IOException
    //   1352	1363	906	java/io/IOException
    //   1375	1390	906	java/io/IOException
    //   1393	1401	906	java/io/IOException
    //   1410	1421	906	java/io/IOException
    //   1424	1438	906	java/io/IOException
    //   1444	1452	906	java/io/IOException
    //   1455	1463	906	java/io/IOException
    //   1466	1476	906	java/io/IOException
    //   1479	1492	906	java/io/IOException
    //   1512	1519	906	java/io/IOException
    //   1525	1533	906	java/io/IOException
    //   1536	1548	906	java/io/IOException
    //   1551	1558	906	java/io/IOException
    //   1567	1575	906	java/io/IOException
    //   1578	1588	906	java/io/IOException
    //   1591	1604	906	java/io/IOException
    //   1614	1622	906	java/io/IOException
    //   1628	1637	906	java/io/IOException
    //   1640	1649	906	java/io/IOException
    //   1652	1658	906	java/io/IOException
    //   1664	1671	906	java/io/IOException
    //   1677	1686	906	java/io/IOException
    //   1689	1697	906	java/io/IOException
    //   1700	1713	906	java/io/IOException
    //   1716	1721	906	java/io/IOException
    //   1724	1731	906	java/io/IOException
    //   1734	1749	906	java/io/IOException
    //   1755	1763	906	java/io/IOException
    //   1766	1779	906	java/io/IOException
    //   1785	1793	906	java/io/IOException
    //   1796	1809	906	java/io/IOException
    //   1815	1826	906	java/io/IOException
    //   1832	1840	906	java/io/IOException
    //   1843	1852	906	java/io/IOException
    //   1855	1864	906	java/io/IOException
    //   1867	1898	906	java/io/IOException
    //   1901	1916	906	java/io/IOException
    //   2075	2083	906	java/io/IOException
    //   2086	2088	906	java/io/IOException
    //   2199	2207	906	java/io/IOException
    //   2210	2218	906	java/io/IOException
    //   2221	2236	906	java/io/IOException
    //   2239	2245	906	java/io/IOException
    //   2248	2257	906	java/io/IOException
    //   2260	2268	906	java/io/IOException
    //   2271	2283	906	java/io/IOException
    //   2286	2296	906	java/io/IOException
    //   2299	2309	906	java/io/IOException
    //   2312	2369	906	java/io/IOException
    //   2372	2379	906	java/io/IOException
    //   2382	2390	906	java/io/IOException
    //   2393	2405	906	java/io/IOException
    //   2408	2414	906	java/io/IOException
    //   2417	2436	906	java/io/IOException
    //   2439	2454	906	java/io/IOException
    //   2477	2485	906	java/io/IOException
    //   2488	2512	906	java/io/IOException
    //   2518	2526	906	java/io/IOException
    //   2529	2547	906	java/io/IOException
    //   2550	2561	906	java/io/IOException
    //   2564	2576	906	java/io/IOException
    //   2579	2594	906	java/io/IOException
    //   2597	2608	906	java/io/IOException
    //   2611	2627	906	java/io/IOException
    //   2630	2656	906	java/io/IOException
    //   2659	2674	906	java/io/IOException
    //   2677	2685	906	java/io/IOException
    //   2688	2696	906	java/io/IOException
    //   2699	2709	906	java/io/IOException
    //   2712	2723	906	java/io/IOException
    //   2726	2744	906	java/io/IOException
    //   2750	2760	906	java/io/IOException
    //   2766	2777	906	java/io/IOException
    //   2780	2786	906	java/io/IOException
    //   2789	2799	906	java/io/IOException
    //   2802	2841	906	java/io/IOException
    //   2844	2855	906	java/io/IOException
    //   2858	2870	906	java/io/IOException
    //   2877	2893	906	java/io/IOException
    //   2896	2909	906	java/io/IOException
    //   2931	2938	906	java/io/IOException
    //   2941	2948	906	java/io/IOException
    //   2959	2970	906	java/io/IOException
    //   2976	2995	906	java/io/IOException
    //   3001	3010	906	java/io/IOException
    //   3021	3046	906	java/io/IOException
    //   3049	3056	906	java/io/IOException
    //   3059	3080	906	java/io/IOException
    //   3083	3089	906	java/io/IOException
    //   1919	1936	2066	finally
    //   1939	2025	2066	finally
    //   2031	2046	2066	finally
    //   2055	2066	2066	finally
    //   2108	2138	2066	finally
    //   2141	2153	2066	finally
    //   2156	2193	2066	finally
    //   2917	2928	3716	java/io/IOException
  }
}

/* Location:
 * Qualified Name:     okhttp3.RealCall
 * Java Class Version: 6 (50.0)
 * JD-Core Version:    0.7.1
 */