package com.linkedin.android.liauthlib.thirdparty;

import com.linkedin.android.liauthlib.sso.LiSSOServiceBindingListener;

final class LiThirdPartyAuthorizeActivity$7
  implements LiSSOServiceBindingListener
{
  LiThirdPartyAuthorizeActivity$7(LiThirdPartyAuthorizeActivity paramLiThirdPartyAuthorizeActivity) {}
  
  /* Error */
  public final void onBindSuccess()
  {
    // Byte code:
    //   0: aload_0
    //   1: getfield 14	com/linkedin/android/liauthlib/thirdparty/LiThirdPartyAuthorizeActivity$7:this$0	Lcom/linkedin/android/liauthlib/thirdparty/LiThirdPartyAuthorizeActivity;
    //   4: getfield 25	com/linkedin/android/liauthlib/thirdparty/LiThirdPartyAuthorizeActivity:m_auth	Lcom/linkedin/android/liauthlib/LiAuth;
    //   7: invokeinterface 31 1 0
    //   12: astore_3
    //   13: aload_0
    //   14: getfield 14	com/linkedin/android/liauthlib/thirdparty/LiThirdPartyAuthorizeActivity$7:this$0	Lcom/linkedin/android/liauthlib/thirdparty/LiThirdPartyAuthorizeActivity;
    //   17: astore_2
    //   18: aload_3
    //   19: ifnull +14 -> 33
    //   22: aload_3
    //   23: invokeinterface 37 1 0
    //   28: istore_1
    //   29: iload_1
    //   30: ifeq +16 -> 46
    //   33: aload_0
    //   34: getfield 14	com/linkedin/android/liauthlib/thirdparty/LiThirdPartyAuthorizeActivity$7:this$0	Lcom/linkedin/android/liauthlib/thirdparty/LiThirdPartyAuthorizeActivity;
    //   37: getfield 25	com/linkedin/android/liauthlib/thirdparty/LiThirdPartyAuthorizeActivity:m_auth	Lcom/linkedin/android/liauthlib/LiAuth;
    //   40: invokeinterface 40 1 0
    //   45: return
    //   46: new 42	java/lang/StringBuilder
    //   49: dup
    //   50: ldc 44
    //   52: invokespecial 47	java/lang/StringBuilder:<init>	(Ljava/lang/String;)V
    //   55: aload_3
    //   56: invokeinterface 51 1 0
    //   61: invokevirtual 55	java/lang/StringBuilder:append	(I)Ljava/lang/StringBuilder;
    //   64: ldc 57
    //   66: invokevirtual 60	java/lang/StringBuilder:append	(Ljava/lang/String;)Ljava/lang/StringBuilder;
    //   69: aload_3
    //   70: iconst_0
    //   71: invokeinterface 64 2 0
    //   76: checkcast 66	com/linkedin/android/liauthlib/common/LiSSOInfo
    //   79: invokevirtual 70	com/linkedin/android/liauthlib/common/LiSSOInfo:toString	()Ljava/lang/String;
    //   82: invokevirtual 60	java/lang/StringBuilder:append	(Ljava/lang/String;)Ljava/lang/StringBuilder;
    //   85: pop
    //   86: new 42	java/lang/StringBuilder
    //   89: dup
    //   90: ldc 72
    //   92: invokespecial 47	java/lang/StringBuilder:<init>	(Ljava/lang/String;)V
    //   95: aload_3
    //   96: iconst_0
    //   97: invokeinterface 64 2 0
    //   102: checkcast 66	com/linkedin/android/liauthlib/common/LiSSOInfo
    //   105: getfield 76	com/linkedin/android/liauthlib/common/LiSSOInfo:pkgName	Ljava/lang/String;
    //   108: invokevirtual 60	java/lang/StringBuilder:append	(Ljava/lang/String;)Ljava/lang/StringBuilder;
    //   111: ldc 57
    //   113: invokevirtual 60	java/lang/StringBuilder:append	(Ljava/lang/String;)Ljava/lang/StringBuilder;
    //   116: aload_3
    //   117: iconst_0
    //   118: invokeinterface 64 2 0
    //   123: checkcast 66	com/linkedin/android/liauthlib/common/LiSSOInfo
    //   126: getfield 79	com/linkedin/android/liauthlib/common/LiSSOInfo:fullName	Ljava/lang/String;
    //   129: invokevirtual 60	java/lang/StringBuilder:append	(Ljava/lang/String;)Ljava/lang/StringBuilder;
    //   132: ldc 57
    //   134: invokevirtual 60	java/lang/StringBuilder:append	(Ljava/lang/String;)Ljava/lang/StringBuilder;
    //   137: aload_3
    //   138: iconst_0
    //   139: invokeinterface 64 2 0
    //   144: checkcast 66	com/linkedin/android/liauthlib/common/LiSSOInfo
    //   147: getfield 82	com/linkedin/android/liauthlib/common/LiSSOInfo:pictureUrl	Ljava/lang/String;
    //   150: invokevirtual 60	java/lang/StringBuilder:append	(Ljava/lang/String;)Ljava/lang/StringBuilder;
    //   153: pop
    //   154: aload_3
    //   155: iconst_0
    //   156: invokeinterface 64 2 0
    //   161: checkcast 66	com/linkedin/android/liauthlib/common/LiSSOInfo
    //   164: astore_3
    //   165: aload_2
    //   166: getfield 86	com/linkedin/android/liauthlib/thirdparty/LiThirdPartyAuthorizeActivity:m_appInfoHandler	Landroid/os/Handler;
    //   169: sipush 1001
    //   172: aload_3
    //   173: invokevirtual 92	android/os/Handler:obtainMessage	(ILjava/lang/Object;)Landroid/os/Message;
    //   176: astore_3
    //   177: aload_2
    //   178: getfield 86	com/linkedin/android/liauthlib/thirdparty/LiThirdPartyAuthorizeActivity:m_appInfoHandler	Landroid/os/Handler;
    //   181: aload_3
    //   182: invokevirtual 96	android/os/Handler:sendMessage	(Landroid/os/Message;)Z
    //   185: pop
    //   186: goto -153 -> 33
    //   189: astore_2
    //   190: new 42	java/lang/StringBuilder
    //   193: dup
    //   194: ldc 98
    //   196: invokespecial 47	java/lang/StringBuilder:<init>	(Ljava/lang/String;)V
    //   199: aload_2
    //   200: invokevirtual 99	java/lang/Exception:toString	()Ljava/lang/String;
    //   203: invokevirtual 60	java/lang/StringBuilder:append	(Ljava/lang/String;)Ljava/lang/StringBuilder;
    //   206: pop
    //   207: aload_0
    //   208: getfield 14	com/linkedin/android/liauthlib/thirdparty/LiThirdPartyAuthorizeActivity$7:this$0	Lcom/linkedin/android/liauthlib/thirdparty/LiThirdPartyAuthorizeActivity;
    //   211: getfield 103	com/linkedin/android/liauthlib/thirdparty/LiThirdPartyAuthorizeActivity:m_externalCallStatus	Lcom/linkedin/android/liauthlib/thirdparty/LiThirdPartyAuthorizeActivity$ExternalCallStatus;
    //   214: iconst_1
    //   215: putfield 109	com/linkedin/android/liauthlib/thirdparty/LiThirdPartyAuthorizeActivity$ExternalCallStatus:m_memberPicResolved	Z
    //   218: aload_0
    //   219: getfield 14	com/linkedin/android/liauthlib/thirdparty/LiThirdPartyAuthorizeActivity$7:this$0	Lcom/linkedin/android/liauthlib/thirdparty/LiThirdPartyAuthorizeActivity;
    //   222: getfield 25	com/linkedin/android/liauthlib/thirdparty/LiThirdPartyAuthorizeActivity:m_auth	Lcom/linkedin/android/liauthlib/LiAuth;
    //   225: invokeinterface 40 1 0
    //   230: return
    //   231: astore_2
    //   232: aload_0
    //   233: getfield 14	com/linkedin/android/liauthlib/thirdparty/LiThirdPartyAuthorizeActivity$7:this$0	Lcom/linkedin/android/liauthlib/thirdparty/LiThirdPartyAuthorizeActivity;
    //   236: getfield 25	com/linkedin/android/liauthlib/thirdparty/LiThirdPartyAuthorizeActivity:m_auth	Lcom/linkedin/android/liauthlib/LiAuth;
    //   239: invokeinterface 40 1 0
    //   244: aload_2
    //   245: athrow
    // Local variable table:
    //   start	length	slot	name	signature
    //   0	246	0	this	7
    //   28	2	1	bool	boolean
    //   17	161	2	localLiThirdPartyAuthorizeActivity	LiThirdPartyAuthorizeActivity
    //   189	11	2	localException	Exception
    //   231	14	2	localObject1	Object
    //   12	170	3	localObject2	Object
    // Exception table:
    //   from	to	target	type
    //   0	18	189	java/lang/Exception
    //   22	29	189	java/lang/Exception
    //   46	186	189	java/lang/Exception
    //   0	18	231	finally
    //   22	29	231	finally
    //   46	186	231	finally
    //   190	218	231	finally
  }
}

/* Location:
 * Qualified Name:     com.linkedin.android.liauthlib.thirdparty.LiThirdPartyAuthorizeActivity.7
 * Java Class Version: 6 (50.0)
 * JD-Core Version:    0.7.1
 */