package com.google.android.gms.internal;

import android.support.v4.util.ArrayMap;
import com.google.android.gms.ads.internal.zze;
import java.util.Collections;
import java.util.Map;

@zzhb
public final class zzdl
  implements zzdf
{
  static final Map<String, Integer> zzzC;
  private final zze zzzA;
  private final zzfn zzzB;
  
  static
  {
    ArrayMap localArrayMap = new ArrayMap(6);
    localArrayMap.put("resize", Integer.valueOf(1));
    localArrayMap.put("playVideo", Integer.valueOf(2));
    localArrayMap.put("storePicture", Integer.valueOf(3));
    localArrayMap.put("createCalendarEvent", Integer.valueOf(4));
    localArrayMap.put("setOrientationProperties", Integer.valueOf(5));
    localArrayMap.put("closeResizedAd", Integer.valueOf(6));
    zzzC = Collections.unmodifiableMap(localArrayMap);
  }
  
  public zzdl(zze paramzze, zzfn paramzzfn)
  {
    zzzA = paramzze;
    zzzB = paramzzfn;
  }
  
  /* Error */
  public final void zza(zzjp paramzzjp, Map<String, String> paramMap)
  {
    // Byte code:
    //   0: iconst_m1
    //   1: istore 5
    //   3: aload_2
    //   4: ldc 70
    //   6: invokeinterface 74 2 0
    //   11: checkcast 76	java/lang/String
    //   14: astore 9
    //   16: getstatic 54	com/google/android/gms/internal/zzdl:zzzC	Ljava/util/Map;
    //   19: aload 9
    //   21: invokeinterface 74 2 0
    //   26: checkcast 26	java/lang/Integer
    //   29: invokevirtual 80	java/lang/Integer:intValue	()I
    //   32: istore_3
    //   33: iload_3
    //   34: iconst_5
    //   35: if_icmpeq +26 -> 61
    //   38: aload_0
    //   39: getfield 60	com/google/android/gms/internal/zzdl:zzzA	Lcom/google/android/gms/ads/internal/zze;
    //   42: ifnull +19 -> 61
    //   45: aload_0
    //   46: getfield 60	com/google/android/gms/internal/zzdl:zzzA	Lcom/google/android/gms/ads/internal/zze;
    //   49: invokevirtual 86	com/google/android/gms/ads/internal/zze:zzbh	()Z
    //   52: ifne +9 -> 61
    //   55: ldc 88
    //   57: invokestatic 94	com/google/android/gms/internal/zzin:zzaI	(Ljava/lang/String;)V
    //   60: return
    //   61: iload_3
    //   62: tableswitch	default:+38->100, 1:+44->106, 2:+38->100, 3:+2400->2462, 4:+2246->2308, 5:+2667->2729, 6:+2767->2829
    //   100: ldc 96
    //   102: invokestatic 99	com/google/android/gms/internal/zzin:zzaJ	(Ljava/lang/String;)V
    //   105: return
    //   106: aload_0
    //   107: getfield 62	com/google/android/gms/internal/zzdl:zzzB	Lcom/google/android/gms/internal/zzfn;
    //   110: astore 10
    //   112: aload 10
    //   114: getfield 105	com/google/android/gms/internal/zzfn:zzpV	Ljava/lang/Object;
    //   117: astore 9
    //   119: aload 9
    //   121: monitorenter
    //   122: aload 10
    //   124: getfield 109	com/google/android/gms/internal/zzfn:zzDh	Landroid/app/Activity;
    //   127: ifnonnull +20 -> 147
    //   130: aload 10
    //   132: ldc 111
    //   134: invokevirtual 114	com/google/android/gms/internal/zzfn:zzam	(Ljava/lang/String;)V
    //   137: aload 9
    //   139: monitorexit
    //   140: return
    //   141: astore_1
    //   142: aload 9
    //   144: monitorexit
    //   145: aload_1
    //   146: athrow
    //   147: aload 10
    //   149: getfield 118	com/google/android/gms/internal/zzfn:zzpD	Lcom/google/android/gms/internal/zzjp;
    //   152: invokeinterface 124 1 0
    //   157: ifnonnull +14 -> 171
    //   160: aload 10
    //   162: ldc 126
    //   164: invokevirtual 114	com/google/android/gms/internal/zzfn:zzam	(Ljava/lang/String;)V
    //   167: aload 9
    //   169: monitorexit
    //   170: return
    //   171: aload 10
    //   173: getfield 118	com/google/android/gms/internal/zzfn:zzpD	Lcom/google/android/gms/internal/zzjp;
    //   176: invokeinterface 124 1 0
    //   181: getfield 132	com/google/android/gms/ads/internal/client/AdSizeParcel:zzui	Z
    //   184: ifeq +14 -> 198
    //   187: aload 10
    //   189: ldc -122
    //   191: invokevirtual 114	com/google/android/gms/internal/zzfn:zzam	(Ljava/lang/String;)V
    //   194: aload 9
    //   196: monitorexit
    //   197: return
    //   198: aload 10
    //   200: getfield 118	com/google/android/gms/internal/zzfn:zzpD	Lcom/google/android/gms/internal/zzjp;
    //   203: invokeinterface 137 1 0
    //   208: ifeq +14 -> 222
    //   211: aload 10
    //   213: ldc -117
    //   215: invokevirtual 114	com/google/android/gms/internal/zzfn:zzam	(Ljava/lang/String;)V
    //   218: aload 9
    //   220: monitorexit
    //   221: return
    //   222: aload_2
    //   223: ldc -115
    //   225: invokeinterface 74 2 0
    //   230: checkcast 143	java/lang/CharSequence
    //   233: invokestatic 149	android/text/TextUtils:isEmpty	(Ljava/lang/CharSequence;)Z
    //   236: ifne +26 -> 262
    //   239: invokestatic 155	com/google/android/gms/ads/internal/zzr:zzbC	()Lcom/google/android/gms/internal/zzir;
    //   242: pop
    //   243: aload 10
    //   245: aload_2
    //   246: ldc -115
    //   248: invokeinterface 74 2 0
    //   253: checkcast 76	java/lang/String
    //   256: invokestatic 161	com/google/android/gms/internal/zzir:zzaD	(Ljava/lang/String;)I
    //   259: putfield 165	com/google/android/gms/internal/zzfn:zzoG	I
    //   262: aload_2
    //   263: ldc -89
    //   265: invokeinterface 74 2 0
    //   270: checkcast 143	java/lang/CharSequence
    //   273: invokestatic 149	android/text/TextUtils:isEmpty	(Ljava/lang/CharSequence;)Z
    //   276: ifne +26 -> 302
    //   279: invokestatic 155	com/google/android/gms/ads/internal/zzr:zzbC	()Lcom/google/android/gms/internal/zzir;
    //   282: pop
    //   283: aload 10
    //   285: aload_2
    //   286: ldc -89
    //   288: invokeinterface 74 2 0
    //   293: checkcast 76	java/lang/String
    //   296: invokestatic 161	com/google/android/gms/internal/zzir:zzaD	(Ljava/lang/String;)I
    //   299: putfield 170	com/google/android/gms/internal/zzfn:zzoH	I
    //   302: aload_2
    //   303: ldc -84
    //   305: invokeinterface 74 2 0
    //   310: checkcast 143	java/lang/CharSequence
    //   313: invokestatic 149	android/text/TextUtils:isEmpty	(Ljava/lang/CharSequence;)Z
    //   316: ifne +26 -> 342
    //   319: invokestatic 155	com/google/android/gms/ads/internal/zzr:zzbC	()Lcom/google/android/gms/internal/zzir;
    //   322: pop
    //   323: aload 10
    //   325: aload_2
    //   326: ldc -84
    //   328: invokeinterface 74 2 0
    //   333: checkcast 76	java/lang/String
    //   336: invokestatic 161	com/google/android/gms/internal/zzir:zzaD	(Ljava/lang/String;)I
    //   339: putfield 175	com/google/android/gms/internal/zzfn:zzDf	I
    //   342: aload_2
    //   343: ldc -79
    //   345: invokeinterface 74 2 0
    //   350: checkcast 143	java/lang/CharSequence
    //   353: invokestatic 149	android/text/TextUtils:isEmpty	(Ljava/lang/CharSequence;)Z
    //   356: ifne +26 -> 382
    //   359: invokestatic 155	com/google/android/gms/ads/internal/zzr:zzbC	()Lcom/google/android/gms/internal/zzir;
    //   362: pop
    //   363: aload 10
    //   365: aload_2
    //   366: ldc -79
    //   368: invokeinterface 74 2 0
    //   373: checkcast 76	java/lang/String
    //   376: invokestatic 161	com/google/android/gms/internal/zzir:zzaD	(Ljava/lang/String;)I
    //   379: putfield 180	com/google/android/gms/internal/zzfn:zzDg	I
    //   382: aload_2
    //   383: ldc -74
    //   385: invokeinterface 74 2 0
    //   390: checkcast 143	java/lang/CharSequence
    //   393: invokestatic 149	android/text/TextUtils:isEmpty	(Ljava/lang/CharSequence;)Z
    //   396: ifne +22 -> 418
    //   399: aload 10
    //   401: aload_2
    //   402: ldc -74
    //   404: invokeinterface 74 2 0
    //   409: checkcast 76	java/lang/String
    //   412: invokestatic 188	java/lang/Boolean:parseBoolean	(Ljava/lang/String;)Z
    //   415: putfield 191	com/google/android/gms/internal/zzfn:zzDc	Z
    //   418: aload_2
    //   419: ldc -63
    //   421: invokeinterface 74 2 0
    //   426: checkcast 76	java/lang/String
    //   429: astore_1
    //   430: aload_1
    //   431: invokestatic 149	android/text/TextUtils:isEmpty	(Ljava/lang/CharSequence;)Z
    //   434: ifne +9 -> 443
    //   437: aload 10
    //   439: aload_1
    //   440: putfield 197	com/google/android/gms/internal/zzfn:zzDb	Ljava/lang/String;
    //   443: aload 10
    //   445: getfield 165	com/google/android/gms/internal/zzfn:zzoG	I
    //   448: iflt +2396 -> 2844
    //   451: aload 10
    //   453: getfield 170	com/google/android/gms/internal/zzfn:zzoH	I
    //   456: iflt +2388 -> 2844
    //   459: iconst_1
    //   460: istore_3
    //   461: iload_3
    //   462: ifne +14 -> 476
    //   465: aload 10
    //   467: ldc -57
    //   469: invokevirtual 114	com/google/android/gms/internal/zzfn:zzam	(Ljava/lang/String;)V
    //   472: aload 9
    //   474: monitorexit
    //   475: return
    //   476: aload 10
    //   478: getfield 109	com/google/android/gms/internal/zzfn:zzDh	Landroid/app/Activity;
    //   481: invokevirtual 205	android/app/Activity:getWindow	()Landroid/view/Window;
    //   484: astore_2
    //   485: aload_2
    //   486: ifnull +10 -> 496
    //   489: aload_2
    //   490: invokevirtual 211	android/view/Window:getDecorView	()Landroid/view/View;
    //   493: ifnonnull +14 -> 507
    //   496: aload 10
    //   498: ldc -43
    //   500: invokevirtual 114	com/google/android/gms/internal/zzfn:zzam	(Ljava/lang/String;)V
    //   503: aload 9
    //   505: monitorexit
    //   506: return
    //   507: invokestatic 155	com/google/android/gms/ads/internal/zzr:zzbC	()Lcom/google/android/gms/internal/zzir;
    //   510: pop
    //   511: aload 10
    //   513: getfield 109	com/google/android/gms/internal/zzfn:zzDh	Landroid/app/Activity;
    //   516: invokestatic 217	com/google/android/gms/internal/zzir:zzf	(Landroid/app/Activity;)[I
    //   519: astore 11
    //   521: invokestatic 155	com/google/android/gms/ads/internal/zzr:zzbC	()Lcom/google/android/gms/internal/zzir;
    //   524: pop
    //   525: aload 10
    //   527: getfield 109	com/google/android/gms/internal/zzfn:zzDh	Landroid/app/Activity;
    //   530: invokestatic 220	com/google/android/gms/internal/zzir:zzh	(Landroid/app/Activity;)[I
    //   533: astore_1
    //   534: aload 11
    //   536: iconst_0
    //   537: iaload
    //   538: istore 6
    //   540: aload 11
    //   542: iconst_1
    //   543: iaload
    //   544: istore_3
    //   545: aload 10
    //   547: getfield 165	com/google/android/gms/internal/zzfn:zzoG	I
    //   550: bipush 50
    //   552: if_icmplt +13 -> 565
    //   555: aload 10
    //   557: getfield 165	com/google/android/gms/internal/zzfn:zzoG	I
    //   560: iload 6
    //   562: if_icmple +28 -> 590
    //   565: ldc -34
    //   567: invokestatic 225	com/google/android/gms/internal/zzin:zzaK	(Ljava/lang/String;)V
    //   570: iconst_0
    //   571: istore_3
    //   572: goto +2277 -> 2849
    //   575: aload_1
    //   576: ifnonnull +713 -> 1289
    //   579: aload 10
    //   581: ldc -29
    //   583: invokevirtual 114	com/google/android/gms/internal/zzfn:zzam	(Ljava/lang/String;)V
    //   586: aload 9
    //   588: monitorexit
    //   589: return
    //   590: aload 10
    //   592: getfield 170	com/google/android/gms/internal/zzfn:zzoH	I
    //   595: bipush 50
    //   597: if_icmplt +12 -> 609
    //   600: aload 10
    //   602: getfield 170	com/google/android/gms/internal/zzfn:zzoH	I
    //   605: iload_3
    //   606: if_icmple +13 -> 619
    //   609: ldc -27
    //   611: invokestatic 225	com/google/android/gms/internal/zzin:zzaK	(Ljava/lang/String;)V
    //   614: iconst_0
    //   615: istore_3
    //   616: goto +2233 -> 2849
    //   619: aload 10
    //   621: getfield 170	com/google/android/gms/internal/zzfn:zzoH	I
    //   624: iload_3
    //   625: if_icmpne +23 -> 648
    //   628: aload 10
    //   630: getfield 165	com/google/android/gms/internal/zzfn:zzoG	I
    //   633: iload 6
    //   635: if_icmpne +13 -> 648
    //   638: ldc -25
    //   640: invokestatic 225	com/google/android/gms/internal/zzin:zzaK	(Ljava/lang/String;)V
    //   643: iconst_0
    //   644: istore_3
    //   645: goto +2204 -> 2849
    //   648: aload 10
    //   650: getfield 191	com/google/android/gms/internal/zzfn:zzDc	Z
    //   653: ifeq +2287 -> 2940
    //   656: aload 10
    //   658: getfield 197	com/google/android/gms/internal/zzfn:zzDb	Ljava/lang/String;
    //   661: astore 11
    //   663: aload 11
    //   665: invokevirtual 234	java/lang/String:hashCode	()I
    //   668: lookupswitch	default:+2190->2858, -1364013995:+127->795, -1012429441:+97->765, -655373719:+142->810, 1163912186:+172->840, 1288627767:+157->825, 1755462605:+112->780
    //   728: aload 10
    //   730: getfield 237	com/google/android/gms/internal/zzfn:zzDd	I
    //   733: aload 10
    //   735: getfield 175	com/google/android/gms/internal/zzfn:zzDf	I
    //   738: iadd
    //   739: aload 10
    //   741: getfield 165	com/google/android/gms/internal/zzfn:zzoG	I
    //   744: iadd
    //   745: bipush 50
    //   747: isub
    //   748: istore 4
    //   750: aload 10
    //   752: getfield 240	com/google/android/gms/internal/zzfn:zzDe	I
    //   755: aload 10
    //   757: getfield 180	com/google/android/gms/internal/zzfn:zzDg	I
    //   760: iadd
    //   761: istore_3
    //   762: goto +2141 -> 2903
    //   765: aload 11
    //   767: ldc -14
    //   769: invokevirtual 246	java/lang/String:equals	(Ljava/lang/Object;)Z
    //   772: ifeq +2086 -> 2858
    //   775: iconst_0
    //   776: istore_3
    //   777: goto +2083 -> 2860
    //   780: aload 11
    //   782: ldc -8
    //   784: invokevirtual 246	java/lang/String:equals	(Ljava/lang/Object;)Z
    //   787: ifeq +2071 -> 2858
    //   790: iconst_1
    //   791: istore_3
    //   792: goto +2068 -> 2860
    //   795: aload 11
    //   797: ldc -6
    //   799: invokevirtual 246	java/lang/String:equals	(Ljava/lang/Object;)Z
    //   802: ifeq +2056 -> 2858
    //   805: iconst_2
    //   806: istore_3
    //   807: goto +2053 -> 2860
    //   810: aload 11
    //   812: ldc -4
    //   814: invokevirtual 246	java/lang/String:equals	(Ljava/lang/Object;)Z
    //   817: ifeq +2041 -> 2858
    //   820: iconst_3
    //   821: istore_3
    //   822: goto +2038 -> 2860
    //   825: aload 11
    //   827: ldc -2
    //   829: invokevirtual 246	java/lang/String:equals	(Ljava/lang/Object;)Z
    //   832: ifeq +2026 -> 2858
    //   835: iconst_4
    //   836: istore_3
    //   837: goto +2023 -> 2860
    //   840: aload 11
    //   842: ldc_w 256
    //   845: invokevirtual 246	java/lang/String:equals	(Ljava/lang/Object;)Z
    //   848: ifeq +2010 -> 2858
    //   851: iconst_5
    //   852: istore_3
    //   853: goto +2007 -> 2860
    //   856: aload 10
    //   858: getfield 237	com/google/android/gms/internal/zzfn:zzDd	I
    //   861: istore_3
    //   862: aload 10
    //   864: getfield 175	com/google/android/gms/internal/zzfn:zzDf	I
    //   867: iload_3
    //   868: iadd
    //   869: istore 4
    //   871: aload 10
    //   873: getfield 240	com/google/android/gms/internal/zzfn:zzDe	I
    //   876: aload 10
    //   878: getfield 180	com/google/android/gms/internal/zzfn:zzDg	I
    //   881: iadd
    //   882: istore_3
    //   883: goto +2020 -> 2903
    //   886: aload 10
    //   888: getfield 237	com/google/android/gms/internal/zzfn:zzDd	I
    //   891: aload 10
    //   893: getfield 175	com/google/android/gms/internal/zzfn:zzDf	I
    //   896: iadd
    //   897: aload 10
    //   899: getfield 165	com/google/android/gms/internal/zzfn:zzoG	I
    //   902: iconst_2
    //   903: idiv
    //   904: iadd
    //   905: bipush 25
    //   907: isub
    //   908: istore 4
    //   910: aload 10
    //   912: getfield 240	com/google/android/gms/internal/zzfn:zzDe	I
    //   915: aload 10
    //   917: getfield 180	com/google/android/gms/internal/zzfn:zzDg	I
    //   920: iadd
    //   921: istore_3
    //   922: goto +1981 -> 2903
    //   925: aload 10
    //   927: getfield 237	com/google/android/gms/internal/zzfn:zzDd	I
    //   930: aload 10
    //   932: getfield 175	com/google/android/gms/internal/zzfn:zzDf	I
    //   935: iadd
    //   936: aload 10
    //   938: getfield 165	com/google/android/gms/internal/zzfn:zzoG	I
    //   941: iconst_2
    //   942: idiv
    //   943: iadd
    //   944: bipush 25
    //   946: isub
    //   947: istore 4
    //   949: aload 10
    //   951: getfield 240	com/google/android/gms/internal/zzfn:zzDe	I
    //   954: aload 10
    //   956: getfield 180	com/google/android/gms/internal/zzfn:zzDg	I
    //   959: iadd
    //   960: aload 10
    //   962: getfield 170	com/google/android/gms/internal/zzfn:zzoH	I
    //   965: iconst_2
    //   966: idiv
    //   967: iadd
    //   968: bipush 25
    //   970: isub
    //   971: istore_3
    //   972: goto +1931 -> 2903
    //   975: aload 10
    //   977: getfield 237	com/google/android/gms/internal/zzfn:zzDd	I
    //   980: istore_3
    //   981: aload 10
    //   983: getfield 175	com/google/android/gms/internal/zzfn:zzDf	I
    //   986: iload_3
    //   987: iadd
    //   988: istore 4
    //   990: aload 10
    //   992: getfield 240	com/google/android/gms/internal/zzfn:zzDe	I
    //   995: aload 10
    //   997: getfield 180	com/google/android/gms/internal/zzfn:zzDg	I
    //   1000: iadd
    //   1001: aload 10
    //   1003: getfield 170	com/google/android/gms/internal/zzfn:zzoH	I
    //   1006: iadd
    //   1007: bipush 50
    //   1009: isub
    //   1010: istore_3
    //   1011: goto +1892 -> 2903
    //   1014: aload 10
    //   1016: getfield 237	com/google/android/gms/internal/zzfn:zzDd	I
    //   1019: aload 10
    //   1021: getfield 175	com/google/android/gms/internal/zzfn:zzDf	I
    //   1024: iadd
    //   1025: aload 10
    //   1027: getfield 165	com/google/android/gms/internal/zzfn:zzoG	I
    //   1030: iconst_2
    //   1031: idiv
    //   1032: iadd
    //   1033: bipush 25
    //   1035: isub
    //   1036: istore 4
    //   1038: aload 10
    //   1040: getfield 240	com/google/android/gms/internal/zzfn:zzDe	I
    //   1043: aload 10
    //   1045: getfield 180	com/google/android/gms/internal/zzfn:zzDg	I
    //   1048: iadd
    //   1049: aload 10
    //   1051: getfield 170	com/google/android/gms/internal/zzfn:zzoH	I
    //   1054: iadd
    //   1055: bipush 50
    //   1057: isub
    //   1058: istore_3
    //   1059: goto +1844 -> 2903
    //   1062: aload 10
    //   1064: getfield 237	com/google/android/gms/internal/zzfn:zzDd	I
    //   1067: aload 10
    //   1069: getfield 175	com/google/android/gms/internal/zzfn:zzDf	I
    //   1072: iadd
    //   1073: aload 10
    //   1075: getfield 165	com/google/android/gms/internal/zzfn:zzoG	I
    //   1078: iadd
    //   1079: bipush 50
    //   1081: isub
    //   1082: istore 4
    //   1084: aload 10
    //   1086: getfield 240	com/google/android/gms/internal/zzfn:zzDe	I
    //   1089: aload 10
    //   1091: getfield 180	com/google/android/gms/internal/zzfn:zzDg	I
    //   1094: iadd
    //   1095: aload 10
    //   1097: getfield 170	com/google/android/gms/internal/zzfn:zzoH	I
    //   1100: iadd
    //   1101: bipush 50
    //   1103: isub
    //   1104: istore_3
    //   1105: goto +1798 -> 2903
    //   1108: aload 10
    //   1110: getfield 191	com/google/android/gms/internal/zzfn:zzDc	Z
    //   1113: ifeq +38 -> 1151
    //   1116: iconst_2
    //   1117: newarray <illegal type>
    //   1119: dup
    //   1120: iconst_0
    //   1121: aload 10
    //   1123: getfield 237	com/google/android/gms/internal/zzfn:zzDd	I
    //   1126: aload 10
    //   1128: getfield 175	com/google/android/gms/internal/zzfn:zzDf	I
    //   1131: iadd
    //   1132: iastore
    //   1133: dup
    //   1134: iconst_1
    //   1135: aload 10
    //   1137: getfield 240	com/google/android/gms/internal/zzfn:zzDe	I
    //   1140: aload 10
    //   1142: getfield 180	com/google/android/gms/internal/zzfn:zzDg	I
    //   1145: iadd
    //   1146: iastore
    //   1147: astore_1
    //   1148: goto -573 -> 575
    //   1151: invokestatic 155	com/google/android/gms/ads/internal/zzr:zzbC	()Lcom/google/android/gms/internal/zzir;
    //   1154: pop
    //   1155: aload 10
    //   1157: getfield 109	com/google/android/gms/internal/zzfn:zzDh	Landroid/app/Activity;
    //   1160: invokestatic 217	com/google/android/gms/internal/zzir:zzf	(Landroid/app/Activity;)[I
    //   1163: astore_1
    //   1164: invokestatic 155	com/google/android/gms/ads/internal/zzr:zzbC	()Lcom/google/android/gms/internal/zzir;
    //   1167: pop
    //   1168: aload 10
    //   1170: getfield 109	com/google/android/gms/internal/zzfn:zzDh	Landroid/app/Activity;
    //   1173: invokestatic 220	com/google/android/gms/internal/zzir:zzh	(Landroid/app/Activity;)[I
    //   1176: astore 11
    //   1178: aload_1
    //   1179: iconst_0
    //   1180: iaload
    //   1181: istore 6
    //   1183: aload 10
    //   1185: getfield 237	com/google/android/gms/internal/zzfn:zzDd	I
    //   1188: istore_3
    //   1189: aload 10
    //   1191: getfield 175	com/google/android/gms/internal/zzfn:zzDf	I
    //   1194: iload_3
    //   1195: iadd
    //   1196: istore_3
    //   1197: aload 10
    //   1199: getfield 240	com/google/android/gms/internal/zzfn:zzDe	I
    //   1202: aload 10
    //   1204: getfield 180	com/google/android/gms/internal/zzfn:zzDg	I
    //   1207: iadd
    //   1208: istore 4
    //   1210: iload_3
    //   1211: ifge +24 -> 1235
    //   1214: iconst_0
    //   1215: istore_3
    //   1216: goto +1729 -> 2945
    //   1219: iconst_2
    //   1220: newarray <illegal type>
    //   1222: dup
    //   1223: iconst_0
    //   1224: iload_3
    //   1225: iastore
    //   1226: dup
    //   1227: iconst_1
    //   1228: iload 4
    //   1230: iastore
    //   1231: astore_1
    //   1232: goto -657 -> 575
    //   1235: aload 10
    //   1237: getfield 165	com/google/android/gms/internal/zzfn:zzoG	I
    //   1240: iload_3
    //   1241: iadd
    //   1242: iload 6
    //   1244: if_icmple +1597 -> 2841
    //   1247: iload 6
    //   1249: aload 10
    //   1251: getfield 165	com/google/android/gms/internal/zzfn:zzoG	I
    //   1254: isub
    //   1255: istore_3
    //   1256: goto +1689 -> 2945
    //   1259: aload 10
    //   1261: getfield 170	com/google/android/gms/internal/zzfn:zzoH	I
    //   1264: iload 4
    //   1266: iadd
    //   1267: aload 11
    //   1269: iconst_1
    //   1270: iaload
    //   1271: if_icmple +1567 -> 2838
    //   1274: aload 11
    //   1276: iconst_1
    //   1277: iaload
    //   1278: aload 10
    //   1280: getfield 170	com/google/android/gms/internal/zzfn:zzoH	I
    //   1283: isub
    //   1284: istore 4
    //   1286: goto -67 -> 1219
    //   1289: invokestatic 262	com/google/android/gms/ads/internal/client/zzn:zzcS	()Lcom/google/android/gms/ads/internal/util/client/zza;
    //   1292: pop
    //   1293: aload 10
    //   1295: getfield 109	com/google/android/gms/internal/zzfn:zzDh	Landroid/app/Activity;
    //   1298: aload 10
    //   1300: getfield 165	com/google/android/gms/internal/zzfn:zzoG	I
    //   1303: invokestatic 268	com/google/android/gms/ads/internal/util/client/zza:zzb	(Landroid/content/Context;I)I
    //   1306: istore_3
    //   1307: invokestatic 262	com/google/android/gms/ads/internal/client/zzn:zzcS	()Lcom/google/android/gms/ads/internal/util/client/zza;
    //   1310: pop
    //   1311: aload 10
    //   1313: getfield 109	com/google/android/gms/internal/zzfn:zzDh	Landroid/app/Activity;
    //   1316: aload 10
    //   1318: getfield 170	com/google/android/gms/internal/zzfn:zzoH	I
    //   1321: invokestatic 268	com/google/android/gms/ads/internal/util/client/zza:zzb	(Landroid/content/Context;I)I
    //   1324: istore 4
    //   1326: aload 10
    //   1328: getfield 118	com/google/android/gms/internal/zzfn:zzpD	Lcom/google/android/gms/internal/zzjp;
    //   1331: invokeinterface 271 1 0
    //   1336: invokevirtual 277	android/view/View:getParent	()Landroid/view/ViewParent;
    //   1339: astore 11
    //   1341: aload 11
    //   1343: ifnull +636 -> 1979
    //   1346: aload 11
    //   1348: instanceof 279
    //   1351: ifeq +628 -> 1979
    //   1354: aload 11
    //   1356: checkcast 279	android/view/ViewGroup
    //   1359: aload 10
    //   1361: getfield 118	com/google/android/gms/internal/zzfn:zzpD	Lcom/google/android/gms/internal/zzjp;
    //   1364: invokeinterface 271 1 0
    //   1369: invokevirtual 283	android/view/ViewGroup:removeView	(Landroid/view/View;)V
    //   1372: aload 10
    //   1374: getfield 287	com/google/android/gms/internal/zzfn:zzDl	Landroid/widget/PopupWindow;
    //   1377: ifnonnull +591 -> 1968
    //   1380: aload 10
    //   1382: aload 11
    //   1384: checkcast 279	android/view/ViewGroup
    //   1387: putfield 291	com/google/android/gms/internal/zzfn:zzDn	Landroid/view/ViewGroup;
    //   1390: invokestatic 155	com/google/android/gms/ads/internal/zzr:zzbC	()Lcom/google/android/gms/internal/zzir;
    //   1393: pop
    //   1394: aload 10
    //   1396: getfield 118	com/google/android/gms/internal/zzfn:zzpD	Lcom/google/android/gms/internal/zzjp;
    //   1399: invokeinterface 271 1 0
    //   1404: invokestatic 295	com/google/android/gms/internal/zzir:zzk	(Landroid/view/View;)Landroid/graphics/Bitmap;
    //   1407: astore 11
    //   1409: aload 10
    //   1411: new 297	android/widget/ImageView
    //   1414: dup
    //   1415: aload 10
    //   1417: getfield 109	com/google/android/gms/internal/zzfn:zzDh	Landroid/app/Activity;
    //   1420: invokespecial 300	android/widget/ImageView:<init>	(Landroid/content/Context;)V
    //   1423: putfield 304	com/google/android/gms/internal/zzfn:zzDi	Landroid/widget/ImageView;
    //   1426: aload 10
    //   1428: getfield 304	com/google/android/gms/internal/zzfn:zzDi	Landroid/widget/ImageView;
    //   1431: aload 11
    //   1433: invokevirtual 308	android/widget/ImageView:setImageBitmap	(Landroid/graphics/Bitmap;)V
    //   1436: aload 10
    //   1438: aload 10
    //   1440: getfield 118	com/google/android/gms/internal/zzfn:zzpD	Lcom/google/android/gms/internal/zzjp;
    //   1443: invokeinterface 124 1 0
    //   1448: putfield 312	com/google/android/gms/internal/zzfn:zzCh	Lcom/google/android/gms/ads/internal/client/AdSizeParcel;
    //   1451: aload 10
    //   1453: getfield 291	com/google/android/gms/internal/zzfn:zzDn	Landroid/view/ViewGroup;
    //   1456: aload 10
    //   1458: getfield 304	com/google/android/gms/internal/zzfn:zzDi	Landroid/widget/ImageView;
    //   1461: invokevirtual 315	android/view/ViewGroup:addView	(Landroid/view/View;)V
    //   1464: aload 10
    //   1466: new 317	android/widget/RelativeLayout
    //   1469: dup
    //   1470: aload 10
    //   1472: getfield 109	com/google/android/gms/internal/zzfn:zzDh	Landroid/app/Activity;
    //   1475: invokespecial 318	android/widget/RelativeLayout:<init>	(Landroid/content/Context;)V
    //   1478: putfield 322	com/google/android/gms/internal/zzfn:zzDm	Landroid/widget/RelativeLayout;
    //   1481: aload 10
    //   1483: getfield 322	com/google/android/gms/internal/zzfn:zzDm	Landroid/widget/RelativeLayout;
    //   1486: iconst_0
    //   1487: invokevirtual 325	android/widget/RelativeLayout:setBackgroundColor	(I)V
    //   1490: aload 10
    //   1492: getfield 322	com/google/android/gms/internal/zzfn:zzDm	Landroid/widget/RelativeLayout;
    //   1495: new 327	android/view/ViewGroup$LayoutParams
    //   1498: dup
    //   1499: iload_3
    //   1500: iload 4
    //   1502: invokespecial 330	android/view/ViewGroup$LayoutParams:<init>	(II)V
    //   1505: invokevirtual 334	android/widget/RelativeLayout:setLayoutParams	(Landroid/view/ViewGroup$LayoutParams;)V
    //   1508: invokestatic 155	com/google/android/gms/ads/internal/zzr:zzbC	()Lcom/google/android/gms/internal/zzir;
    //   1511: pop
    //   1512: aload 10
    //   1514: aload 10
    //   1516: getfield 322	com/google/android/gms/internal/zzfn:zzDm	Landroid/widget/RelativeLayout;
    //   1519: iload_3
    //   1520: iload 4
    //   1522: invokestatic 338	com/google/android/gms/internal/zzir:zza$490f73c3	(Landroid/view/View;II)Landroid/widget/PopupWindow;
    //   1525: putfield 287	com/google/android/gms/internal/zzfn:zzDl	Landroid/widget/PopupWindow;
    //   1528: aload 10
    //   1530: getfield 287	com/google/android/gms/internal/zzfn:zzDl	Landroid/widget/PopupWindow;
    //   1533: iconst_1
    //   1534: invokevirtual 344	android/widget/PopupWindow:setOutsideTouchable	(Z)V
    //   1537: aload 10
    //   1539: getfield 287	com/google/android/gms/internal/zzfn:zzDl	Landroid/widget/PopupWindow;
    //   1542: iconst_1
    //   1543: invokevirtual 347	android/widget/PopupWindow:setTouchable	(Z)V
    //   1546: aload 10
    //   1548: getfield 287	com/google/android/gms/internal/zzfn:zzDl	Landroid/widget/PopupWindow;
    //   1551: astore 11
    //   1553: aload 10
    //   1555: getfield 191	com/google/android/gms/internal/zzfn:zzDc	Z
    //   1558: ifne +1449 -> 3007
    //   1561: iconst_1
    //   1562: istore 8
    //   1564: aload 11
    //   1566: iload 8
    //   1568: invokevirtual 350	android/widget/PopupWindow:setClippingEnabled	(Z)V
    //   1571: aload 10
    //   1573: getfield 322	com/google/android/gms/internal/zzfn:zzDm	Landroid/widget/RelativeLayout;
    //   1576: aload 10
    //   1578: getfield 118	com/google/android/gms/internal/zzfn:zzpD	Lcom/google/android/gms/internal/zzjp;
    //   1581: invokeinterface 271 1 0
    //   1586: iconst_m1
    //   1587: iconst_m1
    //   1588: invokevirtual 353	android/widget/RelativeLayout:addView	(Landroid/view/View;II)V
    //   1591: aload 10
    //   1593: new 355	android/widget/LinearLayout
    //   1596: dup
    //   1597: aload 10
    //   1599: getfield 109	com/google/android/gms/internal/zzfn:zzDh	Landroid/app/Activity;
    //   1602: invokespecial 356	android/widget/LinearLayout:<init>	(Landroid/content/Context;)V
    //   1605: putfield 360	com/google/android/gms/internal/zzfn:zzDj	Landroid/widget/LinearLayout;
    //   1608: invokestatic 262	com/google/android/gms/ads/internal/client/zzn:zzcS	()Lcom/google/android/gms/ads/internal/util/client/zza;
    //   1611: pop
    //   1612: aload 10
    //   1614: getfield 109	com/google/android/gms/internal/zzfn:zzDh	Landroid/app/Activity;
    //   1617: bipush 50
    //   1619: invokestatic 268	com/google/android/gms/ads/internal/util/client/zza:zzb	(Landroid/content/Context;I)I
    //   1622: istore_3
    //   1623: invokestatic 262	com/google/android/gms/ads/internal/client/zzn:zzcS	()Lcom/google/android/gms/ads/internal/util/client/zza;
    //   1626: pop
    //   1627: new 362	android/widget/RelativeLayout$LayoutParams
    //   1630: dup
    //   1631: iload_3
    //   1632: aload 10
    //   1634: getfield 109	com/google/android/gms/internal/zzfn:zzDh	Landroid/app/Activity;
    //   1637: bipush 50
    //   1639: invokestatic 268	com/google/android/gms/ads/internal/util/client/zza:zzb	(Landroid/content/Context;I)I
    //   1642: invokespecial 363	android/widget/RelativeLayout$LayoutParams:<init>	(II)V
    //   1645: astore 11
    //   1647: aload 10
    //   1649: getfield 197	com/google/android/gms/internal/zzfn:zzDb	Ljava/lang/String;
    //   1652: astore 12
    //   1654: aload 12
    //   1656: invokevirtual 234	java/lang/String:hashCode	()I
    //   1659: lookupswitch	default:+1304->2963, -1364013995:+368->2027, -1012429441:+332->1991, -655373719:+386->2045, 1163912186:+422->2081, 1288627767:+404->2063, 1755462605:+350->2009
    //   1716: aload 11
    //   1718: bipush 10
    //   1720: invokevirtual 366	android/widget/RelativeLayout$LayoutParams:addRule	(I)V
    //   1723: aload 11
    //   1725: bipush 11
    //   1727: invokevirtual 366	android/widget/RelativeLayout$LayoutParams:addRule	(I)V
    //   1730: aload 10
    //   1732: getfield 360	com/google/android/gms/internal/zzfn:zzDj	Landroid/widget/LinearLayout;
    //   1735: new 368	com/google/android/gms/internal/zzfn$1
    //   1738: dup
    //   1739: aload 10
    //   1741: invokespecial 371	com/google/android/gms/internal/zzfn$1:<init>	(Lcom/google/android/gms/internal/zzfn;)V
    //   1744: invokevirtual 375	android/widget/LinearLayout:setOnClickListener	(Landroid/view/View$OnClickListener;)V
    //   1747: aload 10
    //   1749: getfield 360	com/google/android/gms/internal/zzfn:zzDj	Landroid/widget/LinearLayout;
    //   1752: ldc_w 377
    //   1755: invokevirtual 381	android/widget/LinearLayout:setContentDescription	(Ljava/lang/CharSequence;)V
    //   1758: aload 10
    //   1760: getfield 322	com/google/android/gms/internal/zzfn:zzDm	Landroid/widget/RelativeLayout;
    //   1763: aload 10
    //   1765: getfield 360	com/google/android/gms/internal/zzfn:zzDj	Landroid/widget/LinearLayout;
    //   1768: aload 11
    //   1770: invokevirtual 384	android/widget/RelativeLayout:addView	(Landroid/view/View;Landroid/view/ViewGroup$LayoutParams;)V
    //   1773: aload 10
    //   1775: getfield 287	com/google/android/gms/internal/zzfn:zzDl	Landroid/widget/PopupWindow;
    //   1778: astore 11
    //   1780: aload_2
    //   1781: invokevirtual 211	android/view/Window:getDecorView	()Landroid/view/View;
    //   1784: astore_2
    //   1785: invokestatic 262	com/google/android/gms/ads/internal/client/zzn:zzcS	()Lcom/google/android/gms/ads/internal/util/client/zza;
    //   1788: pop
    //   1789: aload 10
    //   1791: getfield 109	com/google/android/gms/internal/zzfn:zzDh	Landroid/app/Activity;
    //   1794: aload_1
    //   1795: iconst_0
    //   1796: iaload
    //   1797: invokestatic 268	com/google/android/gms/ads/internal/util/client/zza:zzb	(Landroid/content/Context;I)I
    //   1800: istore_3
    //   1801: invokestatic 262	com/google/android/gms/ads/internal/client/zzn:zzcS	()Lcom/google/android/gms/ads/internal/util/client/zza;
    //   1804: pop
    //   1805: aload 11
    //   1807: aload_2
    //   1808: iconst_0
    //   1809: iload_3
    //   1810: aload 10
    //   1812: getfield 109	com/google/android/gms/internal/zzfn:zzDh	Landroid/app/Activity;
    //   1815: aload_1
    //   1816: iconst_1
    //   1817: iaload
    //   1818: invokestatic 268	com/google/android/gms/ads/internal/util/client/zza:zzb	(Landroid/content/Context;I)I
    //   1821: invokevirtual 388	android/widget/PopupWindow:showAtLocation	(Landroid/view/View;III)V
    //   1824: aload 10
    //   1826: getfield 118	com/google/android/gms/internal/zzfn:zzpD	Lcom/google/android/gms/internal/zzjp;
    //   1829: new 128	com/google/android/gms/ads/internal/client/AdSizeParcel
    //   1832: dup
    //   1833: aload 10
    //   1835: getfield 109	com/google/android/gms/internal/zzfn:zzDh	Landroid/app/Activity;
    //   1838: new 390	com/google/android/gms/ads/AdSize
    //   1841: dup
    //   1842: aload 10
    //   1844: getfield 165	com/google/android/gms/internal/zzfn:zzoG	I
    //   1847: aload 10
    //   1849: getfield 170	com/google/android/gms/internal/zzfn:zzoH	I
    //   1852: invokespecial 391	com/google/android/gms/ads/AdSize:<init>	(II)V
    //   1855: invokespecial 394	com/google/android/gms/ads/internal/client/AdSizeParcel:<init>	(Landroid/content/Context;Lcom/google/android/gms/ads/AdSize;)V
    //   1858: invokeinterface 397 2 0
    //   1863: aload_1
    //   1864: iconst_0
    //   1865: iaload
    //   1866: istore_3
    //   1867: aload_1
    //   1868: iconst_1
    //   1869: iaload
    //   1870: istore 4
    //   1872: invokestatic 155	com/google/android/gms/ads/internal/zzr:zzbC	()Lcom/google/android/gms/internal/zzir;
    //   1875: pop
    //   1876: aload 10
    //   1878: getfield 109	com/google/android/gms/internal/zzfn:zzDh	Landroid/app/Activity;
    //   1881: invokestatic 220	com/google/android/gms/internal/zzir:zzh	(Landroid/app/Activity;)[I
    //   1884: iconst_0
    //   1885: iaload
    //   1886: istore 5
    //   1888: aload 10
    //   1890: getfield 165	com/google/android/gms/internal/zzfn:zzoG	I
    //   1893: istore 6
    //   1895: aload 10
    //   1897: getfield 170	com/google/android/gms/internal/zzfn:zzoH	I
    //   1900: istore 7
    //   1902: new 399	org/json/JSONObject
    //   1905: dup
    //   1906: invokespecial 400	org/json/JSONObject:<init>	()V
    //   1909: ldc_w 402
    //   1912: iload_3
    //   1913: invokevirtual 405	org/json/JSONObject:put	(Ljava/lang/String;I)Lorg/json/JSONObject;
    //   1916: ldc_w 407
    //   1919: iload 4
    //   1921: iload 5
    //   1923: isub
    //   1924: invokevirtual 405	org/json/JSONObject:put	(Ljava/lang/String;I)Lorg/json/JSONObject;
    //   1927: ldc -115
    //   1929: iload 6
    //   1931: invokevirtual 405	org/json/JSONObject:put	(Ljava/lang/String;I)Lorg/json/JSONObject;
    //   1934: ldc -89
    //   1936: iload 7
    //   1938: invokevirtual 405	org/json/JSONObject:put	(Ljava/lang/String;I)Lorg/json/JSONObject;
    //   1941: astore_1
    //   1942: aload 10
    //   1944: getfield 410	com/google/android/gms/internal/zzfs:zzpD	Lcom/google/android/gms/internal/zzjp;
    //   1947: ldc_w 412
    //   1950: aload_1
    //   1951: invokeinterface 415 3 0
    //   1956: aload 10
    //   1958: ldc_w 417
    //   1961: invokevirtual 420	com/google/android/gms/internal/zzfn:zzao	(Ljava/lang/String;)V
    //   1964: aload 9
    //   1966: monitorexit
    //   1967: return
    //   1968: aload 10
    //   1970: getfield 287	com/google/android/gms/internal/zzfn:zzDl	Landroid/widget/PopupWindow;
    //   1973: invokevirtual 423	android/widget/PopupWindow:dismiss	()V
    //   1976: goto -512 -> 1464
    //   1979: aload 10
    //   1981: ldc_w 425
    //   1984: invokevirtual 114	com/google/android/gms/internal/zzfn:zzam	(Ljava/lang/String;)V
    //   1987: aload 9
    //   1989: monitorexit
    //   1990: return
    //   1991: iload 5
    //   1993: istore_3
    //   1994: aload 12
    //   1996: ldc -14
    //   1998: invokevirtual 246	java/lang/String:equals	(Ljava/lang/Object;)Z
    //   2001: ifeq +965 -> 2966
    //   2004: iconst_0
    //   2005: istore_3
    //   2006: goto +960 -> 2966
    //   2009: iload 5
    //   2011: istore_3
    //   2012: aload 12
    //   2014: ldc -8
    //   2016: invokevirtual 246	java/lang/String:equals	(Ljava/lang/Object;)Z
    //   2019: ifeq +947 -> 2966
    //   2022: iconst_1
    //   2023: istore_3
    //   2024: goto +942 -> 2966
    //   2027: iload 5
    //   2029: istore_3
    //   2030: aload 12
    //   2032: ldc -6
    //   2034: invokevirtual 246	java/lang/String:equals	(Ljava/lang/Object;)Z
    //   2037: ifeq +929 -> 2966
    //   2040: iconst_2
    //   2041: istore_3
    //   2042: goto +924 -> 2966
    //   2045: iload 5
    //   2047: istore_3
    //   2048: aload 12
    //   2050: ldc -4
    //   2052: invokevirtual 246	java/lang/String:equals	(Ljava/lang/Object;)Z
    //   2055: ifeq +911 -> 2966
    //   2058: iconst_3
    //   2059: istore_3
    //   2060: goto +906 -> 2966
    //   2063: iload 5
    //   2065: istore_3
    //   2066: aload 12
    //   2068: ldc -2
    //   2070: invokevirtual 246	java/lang/String:equals	(Ljava/lang/Object;)Z
    //   2073: ifeq +893 -> 2966
    //   2076: iconst_4
    //   2077: istore_3
    //   2078: goto +888 -> 2966
    //   2081: iload 5
    //   2083: istore_3
    //   2084: aload 12
    //   2086: ldc_w 256
    //   2089: invokevirtual 246	java/lang/String:equals	(Ljava/lang/Object;)Z
    //   2092: ifeq +874 -> 2966
    //   2095: iconst_5
    //   2096: istore_3
    //   2097: goto +869 -> 2966
    //   2100: aload 11
    //   2102: bipush 10
    //   2104: invokevirtual 366	android/widget/RelativeLayout$LayoutParams:addRule	(I)V
    //   2107: aload 11
    //   2109: bipush 9
    //   2111: invokevirtual 366	android/widget/RelativeLayout$LayoutParams:addRule	(I)V
    //   2114: goto -384 -> 1730
    //   2117: aload 11
    //   2119: bipush 10
    //   2121: invokevirtual 366	android/widget/RelativeLayout$LayoutParams:addRule	(I)V
    //   2124: aload 11
    //   2126: bipush 14
    //   2128: invokevirtual 366	android/widget/RelativeLayout$LayoutParams:addRule	(I)V
    //   2131: goto -401 -> 1730
    //   2134: aload 11
    //   2136: bipush 13
    //   2138: invokevirtual 366	android/widget/RelativeLayout$LayoutParams:addRule	(I)V
    //   2141: goto -411 -> 1730
    //   2144: aload 11
    //   2146: bipush 12
    //   2148: invokevirtual 366	android/widget/RelativeLayout$LayoutParams:addRule	(I)V
    //   2151: aload 11
    //   2153: bipush 9
    //   2155: invokevirtual 366	android/widget/RelativeLayout$LayoutParams:addRule	(I)V
    //   2158: goto -428 -> 1730
    //   2161: aload 11
    //   2163: bipush 12
    //   2165: invokevirtual 366	android/widget/RelativeLayout$LayoutParams:addRule	(I)V
    //   2168: aload 11
    //   2170: bipush 14
    //   2172: invokevirtual 366	android/widget/RelativeLayout$LayoutParams:addRule	(I)V
    //   2175: goto -445 -> 1730
    //   2178: aload 11
    //   2180: bipush 12
    //   2182: invokevirtual 366	android/widget/RelativeLayout$LayoutParams:addRule	(I)V
    //   2185: aload 11
    //   2187: bipush 11
    //   2189: invokevirtual 366	android/widget/RelativeLayout$LayoutParams:addRule	(I)V
    //   2192: goto -462 -> 1730
    //   2195: astore_1
    //   2196: aload 10
    //   2198: new 427	java/lang/StringBuilder
    //   2201: dup
    //   2202: ldc_w 429
    //   2205: invokespecial 431	java/lang/StringBuilder:<init>	(Ljava/lang/String;)V
    //   2208: aload_1
    //   2209: invokevirtual 435	java/lang/RuntimeException:getMessage	()Ljava/lang/String;
    //   2212: invokevirtual 439	java/lang/StringBuilder:append	(Ljava/lang/String;)Ljava/lang/StringBuilder;
    //   2215: invokevirtual 442	java/lang/StringBuilder:toString	()Ljava/lang/String;
    //   2218: invokevirtual 114	com/google/android/gms/internal/zzfn:zzam	(Ljava/lang/String;)V
    //   2221: aload 10
    //   2223: getfield 322	com/google/android/gms/internal/zzfn:zzDm	Landroid/widget/RelativeLayout;
    //   2226: aload 10
    //   2228: getfield 118	com/google/android/gms/internal/zzfn:zzpD	Lcom/google/android/gms/internal/zzjp;
    //   2231: invokeinterface 271 1 0
    //   2236: invokevirtual 443	android/widget/RelativeLayout:removeView	(Landroid/view/View;)V
    //   2239: aload 10
    //   2241: getfield 291	com/google/android/gms/internal/zzfn:zzDn	Landroid/view/ViewGroup;
    //   2244: ifnull +49 -> 2293
    //   2247: aload 10
    //   2249: getfield 291	com/google/android/gms/internal/zzfn:zzDn	Landroid/view/ViewGroup;
    //   2252: aload 10
    //   2254: getfield 304	com/google/android/gms/internal/zzfn:zzDi	Landroid/widget/ImageView;
    //   2257: invokevirtual 283	android/view/ViewGroup:removeView	(Landroid/view/View;)V
    //   2260: aload 10
    //   2262: getfield 291	com/google/android/gms/internal/zzfn:zzDn	Landroid/view/ViewGroup;
    //   2265: aload 10
    //   2267: getfield 118	com/google/android/gms/internal/zzfn:zzpD	Lcom/google/android/gms/internal/zzjp;
    //   2270: invokeinterface 271 1 0
    //   2275: invokevirtual 315	android/view/ViewGroup:addView	(Landroid/view/View;)V
    //   2278: aload 10
    //   2280: getfield 118	com/google/android/gms/internal/zzfn:zzpD	Lcom/google/android/gms/internal/zzjp;
    //   2283: aload 10
    //   2285: getfield 312	com/google/android/gms/internal/zzfn:zzCh	Lcom/google/android/gms/ads/internal/client/AdSizeParcel;
    //   2288: invokeinterface 397 2 0
    //   2293: aload 9
    //   2295: monitorexit
    //   2296: return
    //   2297: astore_1
    //   2298: ldc_w 445
    //   2301: aload_1
    //   2302: invokestatic 448	com/google/android/gms/internal/zzin:zzb	(Ljava/lang/String;Ljava/lang/Throwable;)V
    //   2305: goto -349 -> 1956
    //   2308: new 450	com/google/android/gms/internal/zzfm
    //   2311: dup
    //   2312: aload_1
    //   2313: aload_2
    //   2314: invokespecial 452	com/google/android/gms/internal/zzfm:<init>	(Lcom/google/android/gms/internal/zzjp;Ljava/util/Map;)V
    //   2317: astore_1
    //   2318: aload_1
    //   2319: getfield 456	com/google/android/gms/internal/zzfm:mContext	Landroid/content/Context;
    //   2322: ifnonnull +11 -> 2333
    //   2325: aload_1
    //   2326: ldc_w 458
    //   2329: invokevirtual 459	com/google/android/gms/internal/zzfm:zzam	(Ljava/lang/String;)V
    //   2332: return
    //   2333: invokestatic 155	com/google/android/gms/ads/internal/zzr:zzbC	()Lcom/google/android/gms/internal/zzir;
    //   2336: pop
    //   2337: aload_1
    //   2338: getfield 456	com/google/android/gms/internal/zzfm:mContext	Landroid/content/Context;
    //   2341: invokestatic 463	com/google/android/gms/internal/zzir:zzM	(Landroid/content/Context;)Lcom/google/android/gms/internal/zzbl;
    //   2344: invokevirtual 468	com/google/android/gms/internal/zzbl:zzdo	()Z
    //   2347: ifne +11 -> 2358
    //   2350: aload_1
    //   2351: ldc_w 470
    //   2354: invokevirtual 459	com/google/android/gms/internal/zzfm:zzam	(Ljava/lang/String;)V
    //   2357: return
    //   2358: invokestatic 155	com/google/android/gms/ads/internal/zzr:zzbC	()Lcom/google/android/gms/internal/zzir;
    //   2361: pop
    //   2362: aload_1
    //   2363: getfield 456	com/google/android/gms/internal/zzfm:mContext	Landroid/content/Context;
    //   2366: invokestatic 474	com/google/android/gms/internal/zzir:zzL	(Landroid/content/Context;)Landroid/app/AlertDialog$Builder;
    //   2369: astore_2
    //   2370: aload_2
    //   2371: invokestatic 478	com/google/android/gms/ads/internal/zzr:zzbF	()Lcom/google/android/gms/internal/zzih;
    //   2374: getstatic 483	com/google/android/gms/R$string:create_calendar_title	I
    //   2377: ldc_w 485
    //   2380: invokevirtual 491	com/google/android/gms/internal/zzih:zzd	(ILjava/lang/String;)Ljava/lang/String;
    //   2383: invokevirtual 497	android/app/AlertDialog$Builder:setTitle	(Ljava/lang/CharSequence;)Landroid/app/AlertDialog$Builder;
    //   2386: pop
    //   2387: aload_2
    //   2388: invokestatic 478	com/google/android/gms/ads/internal/zzr:zzbF	()Lcom/google/android/gms/internal/zzih;
    //   2391: getstatic 500	com/google/android/gms/R$string:create_calendar_message	I
    //   2394: ldc_w 502
    //   2397: invokevirtual 491	com/google/android/gms/internal/zzih:zzd	(ILjava/lang/String;)Ljava/lang/String;
    //   2400: invokevirtual 505	android/app/AlertDialog$Builder:setMessage	(Ljava/lang/CharSequence;)Landroid/app/AlertDialog$Builder;
    //   2403: pop
    //   2404: aload_2
    //   2405: invokestatic 478	com/google/android/gms/ads/internal/zzr:zzbF	()Lcom/google/android/gms/internal/zzih;
    //   2408: getstatic 508	com/google/android/gms/R$string:accept	I
    //   2411: ldc_w 510
    //   2414: invokevirtual 491	com/google/android/gms/internal/zzih:zzd	(ILjava/lang/String;)Ljava/lang/String;
    //   2417: new 512	com/google/android/gms/internal/zzfm$1
    //   2420: dup
    //   2421: aload_1
    //   2422: invokespecial 515	com/google/android/gms/internal/zzfm$1:<init>	(Lcom/google/android/gms/internal/zzfm;)V
    //   2425: invokevirtual 519	android/app/AlertDialog$Builder:setPositiveButton	(Ljava/lang/CharSequence;Landroid/content/DialogInterface$OnClickListener;)Landroid/app/AlertDialog$Builder;
    //   2428: pop
    //   2429: aload_2
    //   2430: invokestatic 478	com/google/android/gms/ads/internal/zzr:zzbF	()Lcom/google/android/gms/internal/zzih;
    //   2433: getstatic 522	com/google/android/gms/R$string:decline	I
    //   2436: ldc_w 524
    //   2439: invokevirtual 491	com/google/android/gms/internal/zzih:zzd	(ILjava/lang/String;)Ljava/lang/String;
    //   2442: new 526	com/google/android/gms/internal/zzfm$2
    //   2445: dup
    //   2446: aload_1
    //   2447: invokespecial 527	com/google/android/gms/internal/zzfm$2:<init>	(Lcom/google/android/gms/internal/zzfm;)V
    //   2450: invokevirtual 530	android/app/AlertDialog$Builder:setNegativeButton	(Ljava/lang/CharSequence;Landroid/content/DialogInterface$OnClickListener;)Landroid/app/AlertDialog$Builder;
    //   2453: pop
    //   2454: aload_2
    //   2455: invokevirtual 534	android/app/AlertDialog$Builder:create	()Landroid/app/AlertDialog;
    //   2458: invokevirtual 539	android/app/AlertDialog:show	()V
    //   2461: return
    //   2462: new 541	com/google/android/gms/internal/zzfp
    //   2465: dup
    //   2466: aload_1
    //   2467: aload_2
    //   2468: invokespecial 542	com/google/android/gms/internal/zzfp:<init>	(Lcom/google/android/gms/internal/zzjp;Ljava/util/Map;)V
    //   2471: astore_1
    //   2472: aload_1
    //   2473: getfield 543	com/google/android/gms/internal/zzfp:mContext	Landroid/content/Context;
    //   2476: ifnonnull +11 -> 2487
    //   2479: aload_1
    //   2480: ldc_w 545
    //   2483: invokevirtual 546	com/google/android/gms/internal/zzfp:zzam	(Ljava/lang/String;)V
    //   2486: return
    //   2487: invokestatic 155	com/google/android/gms/ads/internal/zzr:zzbC	()Lcom/google/android/gms/internal/zzir;
    //   2490: pop
    //   2491: aload_1
    //   2492: getfield 543	com/google/android/gms/internal/zzfp:mContext	Landroid/content/Context;
    //   2495: invokestatic 463	com/google/android/gms/internal/zzir:zzM	(Landroid/content/Context;)Lcom/google/android/gms/internal/zzbl;
    //   2498: invokevirtual 549	com/google/android/gms/internal/zzbl:zzdl	()Z
    //   2501: ifne +11 -> 2512
    //   2504: aload_1
    //   2505: ldc_w 551
    //   2508: invokevirtual 546	com/google/android/gms/internal/zzfp:zzam	(Ljava/lang/String;)V
    //   2511: return
    //   2512: aload_1
    //   2513: getfield 554	com/google/android/gms/internal/zzfp:zzxA	Ljava/util/Map;
    //   2516: ldc_w 556
    //   2519: invokeinterface 74 2 0
    //   2524: checkcast 76	java/lang/String
    //   2527: astore_2
    //   2528: aload_2
    //   2529: invokestatic 149	android/text/TextUtils:isEmpty	(Ljava/lang/CharSequence;)Z
    //   2532: ifeq +11 -> 2543
    //   2535: aload_1
    //   2536: ldc_w 558
    //   2539: invokevirtual 546	com/google/android/gms/internal/zzfp:zzam	(Ljava/lang/String;)V
    //   2542: return
    //   2543: aload_2
    //   2544: invokestatic 563	android/webkit/URLUtil:isValidUrl	(Ljava/lang/String;)Z
    //   2547: ifne +25 -> 2572
    //   2550: aload_1
    //   2551: new 427	java/lang/StringBuilder
    //   2554: dup
    //   2555: ldc_w 565
    //   2558: invokespecial 431	java/lang/StringBuilder:<init>	(Ljava/lang/String;)V
    //   2561: aload_2
    //   2562: invokevirtual 439	java/lang/StringBuilder:append	(Ljava/lang/String;)Ljava/lang/StringBuilder;
    //   2565: invokevirtual 442	java/lang/StringBuilder:toString	()Ljava/lang/String;
    //   2568: invokevirtual 546	com/google/android/gms/internal/zzfp:zzam	(Ljava/lang/String;)V
    //   2571: return
    //   2572: aload_2
    //   2573: invokestatic 571	android/net/Uri:parse	(Ljava/lang/String;)Landroid/net/Uri;
    //   2576: invokevirtual 574	android/net/Uri:getLastPathSegment	()Ljava/lang/String;
    //   2579: astore 9
    //   2581: invokestatic 155	com/google/android/gms/ads/internal/zzr:zzbC	()Lcom/google/android/gms/internal/zzir;
    //   2584: pop
    //   2585: aload 9
    //   2587: invokestatic 577	com/google/android/gms/internal/zzir:zzaE	(Ljava/lang/String;)Z
    //   2590: ifne +26 -> 2616
    //   2593: aload_1
    //   2594: new 427	java/lang/StringBuilder
    //   2597: dup
    //   2598: ldc_w 579
    //   2601: invokespecial 431	java/lang/StringBuilder:<init>	(Ljava/lang/String;)V
    //   2604: aload 9
    //   2606: invokevirtual 439	java/lang/StringBuilder:append	(Ljava/lang/String;)Ljava/lang/StringBuilder;
    //   2609: invokevirtual 442	java/lang/StringBuilder:toString	()Ljava/lang/String;
    //   2612: invokevirtual 546	com/google/android/gms/internal/zzfp:zzam	(Ljava/lang/String;)V
    //   2615: return
    //   2616: invokestatic 155	com/google/android/gms/ads/internal/zzr:zzbC	()Lcom/google/android/gms/internal/zzir;
    //   2619: pop
    //   2620: aload_1
    //   2621: getfield 543	com/google/android/gms/internal/zzfp:mContext	Landroid/content/Context;
    //   2624: invokestatic 474	com/google/android/gms/internal/zzir:zzL	(Landroid/content/Context;)Landroid/app/AlertDialog$Builder;
    //   2627: astore 10
    //   2629: aload 10
    //   2631: invokestatic 478	com/google/android/gms/ads/internal/zzr:zzbF	()Lcom/google/android/gms/internal/zzih;
    //   2634: getstatic 582	com/google/android/gms/R$string:store_picture_title	I
    //   2637: ldc_w 584
    //   2640: invokevirtual 491	com/google/android/gms/internal/zzih:zzd	(ILjava/lang/String;)Ljava/lang/String;
    //   2643: invokevirtual 497	android/app/AlertDialog$Builder:setTitle	(Ljava/lang/CharSequence;)Landroid/app/AlertDialog$Builder;
    //   2646: pop
    //   2647: aload 10
    //   2649: invokestatic 478	com/google/android/gms/ads/internal/zzr:zzbF	()Lcom/google/android/gms/internal/zzih;
    //   2652: getstatic 587	com/google/android/gms/R$string:store_picture_message	I
    //   2655: ldc_w 589
    //   2658: invokevirtual 491	com/google/android/gms/internal/zzih:zzd	(ILjava/lang/String;)Ljava/lang/String;
    //   2661: invokevirtual 505	android/app/AlertDialog$Builder:setMessage	(Ljava/lang/CharSequence;)Landroid/app/AlertDialog$Builder;
    //   2664: pop
    //   2665: aload 10
    //   2667: invokestatic 478	com/google/android/gms/ads/internal/zzr:zzbF	()Lcom/google/android/gms/internal/zzih;
    //   2670: getstatic 508	com/google/android/gms/R$string:accept	I
    //   2673: ldc_w 510
    //   2676: invokevirtual 491	com/google/android/gms/internal/zzih:zzd	(ILjava/lang/String;)Ljava/lang/String;
    //   2679: new 591	com/google/android/gms/internal/zzfp$1
    //   2682: dup
    //   2683: aload_1
    //   2684: aload_2
    //   2685: aload 9
    //   2687: invokespecial 594	com/google/android/gms/internal/zzfp$1:<init>	(Lcom/google/android/gms/internal/zzfp;Ljava/lang/String;Ljava/lang/String;)V
    //   2690: invokevirtual 519	android/app/AlertDialog$Builder:setPositiveButton	(Ljava/lang/CharSequence;Landroid/content/DialogInterface$OnClickListener;)Landroid/app/AlertDialog$Builder;
    //   2693: pop
    //   2694: aload 10
    //   2696: invokestatic 478	com/google/android/gms/ads/internal/zzr:zzbF	()Lcom/google/android/gms/internal/zzih;
    //   2699: getstatic 522	com/google/android/gms/R$string:decline	I
    //   2702: ldc_w 524
    //   2705: invokevirtual 491	com/google/android/gms/internal/zzih:zzd	(ILjava/lang/String;)Ljava/lang/String;
    //   2708: new 596	com/google/android/gms/internal/zzfp$2
    //   2711: dup
    //   2712: aload_1
    //   2713: invokespecial 599	com/google/android/gms/internal/zzfp$2:<init>	(Lcom/google/android/gms/internal/zzfp;)V
    //   2716: invokevirtual 530	android/app/AlertDialog$Builder:setNegativeButton	(Ljava/lang/CharSequence;Landroid/content/DialogInterface$OnClickListener;)Landroid/app/AlertDialog$Builder;
    //   2719: pop
    //   2720: aload 10
    //   2722: invokevirtual 534	android/app/AlertDialog$Builder:create	()Landroid/app/AlertDialog;
    //   2725: invokevirtual 539	android/app/AlertDialog:show	()V
    //   2728: return
    //   2729: new 601	com/google/android/gms/internal/zzfo
    //   2732: dup
    //   2733: aload_1
    //   2734: aload_2
    //   2735: invokespecial 602	com/google/android/gms/internal/zzfo:<init>	(Lcom/google/android/gms/internal/zzjp;Ljava/util/Map;)V
    //   2738: astore_1
    //   2739: aload_1
    //   2740: getfield 603	com/google/android/gms/internal/zzfo:zzpD	Lcom/google/android/gms/internal/zzjp;
    //   2743: ifnonnull +10 -> 2753
    //   2746: ldc_w 605
    //   2749: invokestatic 225	com/google/android/gms/internal/zzin:zzaK	(Ljava/lang/String;)V
    //   2752: return
    //   2753: ldc_w 607
    //   2756: aload_1
    //   2757: getfield 610	com/google/android/gms/internal/zzfo:zzDq	Ljava/lang/String;
    //   2760: invokevirtual 613	java/lang/String:equalsIgnoreCase	(Ljava/lang/String;)Z
    //   2763: ifeq +21 -> 2784
    //   2766: invokestatic 617	com/google/android/gms/ads/internal/zzr:zzbE	()Lcom/google/android/gms/internal/zzis;
    //   2769: invokevirtual 622	com/google/android/gms/internal/zzis:zzhw	()I
    //   2772: istore_3
    //   2773: aload_1
    //   2774: getfield 603	com/google/android/gms/internal/zzfo:zzpD	Lcom/google/android/gms/internal/zzjp;
    //   2777: iload_3
    //   2778: invokeinterface 625 2 0
    //   2783: return
    //   2784: ldc_w 627
    //   2787: aload_1
    //   2788: getfield 610	com/google/android/gms/internal/zzfo:zzDq	Ljava/lang/String;
    //   2791: invokevirtual 613	java/lang/String:equalsIgnoreCase	(Ljava/lang/String;)Z
    //   2794: ifeq +13 -> 2807
    //   2797: invokestatic 617	com/google/android/gms/ads/internal/zzr:zzbE	()Lcom/google/android/gms/internal/zzis;
    //   2800: invokevirtual 630	com/google/android/gms/internal/zzis:zzhv	()I
    //   2803: istore_3
    //   2804: goto -31 -> 2773
    //   2807: aload_1
    //   2808: getfield 633	com/google/android/gms/internal/zzfo:zzDp	Z
    //   2811: ifeq +8 -> 2819
    //   2814: iconst_m1
    //   2815: istore_3
    //   2816: goto -43 -> 2773
    //   2819: invokestatic 617	com/google/android/gms/ads/internal/zzr:zzbE	()Lcom/google/android/gms/internal/zzis;
    //   2822: invokevirtual 636	com/google/android/gms/internal/zzis:zzhx	()I
    //   2825: istore_3
    //   2826: goto -53 -> 2773
    //   2829: aload_0
    //   2830: getfield 62	com/google/android/gms/internal/zzdl:zzzB	Lcom/google/android/gms/internal/zzfn;
    //   2833: iconst_1
    //   2834: invokevirtual 639	com/google/android/gms/internal/zzfn:zzp	(Z)V
    //   2837: return
    //   2838: goto -1619 -> 1219
    //   2841: goto +104 -> 2945
    //   2844: iconst_0
    //   2845: istore_3
    //   2846: goto -2385 -> 461
    //   2849: iload_3
    //   2850: ifne -1742 -> 1108
    //   2853: aconst_null
    //   2854: astore_1
    //   2855: goto -2280 -> 575
    //   2858: iconst_m1
    //   2859: istore_3
    //   2860: iload_3
    //   2861: tableswitch	default:+39->2900, 0:+-2005->856, 1:+-1975->886, 2:+-1936->925, 3:+-1886->975, 4:+-1847->1014, 5:+-1799->1062
    //   2900: goto -2172 -> 728
    //   2903: iload 4
    //   2905: iflt +30 -> 2935
    //   2908: iload 4
    //   2910: bipush 50
    //   2912: iadd
    //   2913: iload 6
    //   2915: if_icmpgt +20 -> 2935
    //   2918: iload_3
    //   2919: aload_1
    //   2920: iconst_0
    //   2921: iaload
    //   2922: if_icmplt +13 -> 2935
    //   2925: iload_3
    //   2926: bipush 50
    //   2928: iadd
    //   2929: aload_1
    //   2930: iconst_1
    //   2931: iaload
    //   2932: if_icmple +8 -> 2940
    //   2935: iconst_0
    //   2936: istore_3
    //   2937: goto -88 -> 2849
    //   2940: iconst_1
    //   2941: istore_3
    //   2942: goto -93 -> 2849
    //   2945: iload 4
    //   2947: aload 11
    //   2949: iconst_0
    //   2950: iaload
    //   2951: if_icmpge -1692 -> 1259
    //   2954: aload 11
    //   2956: iconst_0
    //   2957: iaload
    //   2958: istore 4
    //   2960: goto -1741 -> 1219
    //   2963: iload 5
    //   2965: istore_3
    //   2966: iload_3
    //   2967: tableswitch	default:+37->3004, 0:+-867->2100, 1:+-850->2117, 2:+-833->2134, 3:+-823->2144, 4:+-806->2161, 5:+-789->2178
    //   3004: goto -1288 -> 1716
    //   3007: iconst_0
    //   3008: istore 8
    //   3010: goto -1446 -> 1564
    // Local variable table:
    //   start	length	slot	name	signature
    //   0	3013	0	this	zzdl
    //   0	3013	1	paramzzjp	zzjp
    //   0	3013	2	paramMap	Map<String, String>
    //   32	2935	3	i	int
    //   748	2211	4	j	int
    //   1	2963	5	k	int
    //   538	2378	6	m	int
    //   1900	37	7	n	int
    //   1562	1447	8	bool	boolean
    //   14	2672	9	localObject1	Object
    //   110	2611	10	localObject2	Object
    //   519	2436	11	localObject3	Object
    //   1652	433	12	str	String
    // Exception table:
    //   from	to	target	type
    //   122	140	141	finally
    //   142	145	141	finally
    //   147	170	141	finally
    //   171	197	141	finally
    //   198	221	141	finally
    //   222	262	141	finally
    //   262	302	141	finally
    //   302	342	141	finally
    //   342	382	141	finally
    //   382	418	141	finally
    //   418	443	141	finally
    //   443	459	141	finally
    //   465	475	141	finally
    //   476	485	141	finally
    //   489	496	141	finally
    //   496	506	141	finally
    //   507	534	141	finally
    //   545	565	141	finally
    //   565	570	141	finally
    //   579	589	141	finally
    //   590	609	141	finally
    //   609	614	141	finally
    //   619	643	141	finally
    //   648	728	141	finally
    //   728	762	141	finally
    //   765	775	141	finally
    //   780	790	141	finally
    //   795	805	141	finally
    //   810	820	141	finally
    //   825	835	141	finally
    //   840	851	141	finally
    //   856	883	141	finally
    //   886	922	141	finally
    //   925	972	141	finally
    //   975	1011	141	finally
    //   1014	1059	141	finally
    //   1062	1105	141	finally
    //   1108	1148	141	finally
    //   1151	1178	141	finally
    //   1183	1210	141	finally
    //   1219	1232	141	finally
    //   1235	1256	141	finally
    //   1259	1286	141	finally
    //   1289	1341	141	finally
    //   1346	1464	141	finally
    //   1464	1561	141	finally
    //   1564	1716	141	finally
    //   1716	1730	141	finally
    //   1730	1773	141	finally
    //   1773	1824	141	finally
    //   1824	1863	141	finally
    //   1872	1902	141	finally
    //   1902	1956	141	finally
    //   1956	1967	141	finally
    //   1968	1976	141	finally
    //   1979	1990	141	finally
    //   1994	2004	141	finally
    //   2012	2022	141	finally
    //   2030	2040	141	finally
    //   2048	2058	141	finally
    //   2066	2076	141	finally
    //   2084	2095	141	finally
    //   2100	2114	141	finally
    //   2117	2131	141	finally
    //   2134	2141	141	finally
    //   2144	2158	141	finally
    //   2161	2175	141	finally
    //   2178	2192	141	finally
    //   2196	2293	141	finally
    //   2293	2296	141	finally
    //   2298	2305	141	finally
    //   1773	1824	2195	java/lang/RuntimeException
    //   1902	1956	2297	org/json/JSONException
  }
}

/* Location:
 * Qualified Name:     com.google.android.gms.internal.zzdl
 * Java Class Version: 6 (50.0)
 * JD-Core Version:    0.7.1
 */